**CGNode:** Node: < Application, Lcom/squareup/okhttp/internal/DiskLruCache, open(Ljava/io/File;IIJ)Lcom/squareup/okhttp/internal/DiskLruCache; > Context: JavaTypeContext<point: <Primordial,Ljava/io/File>>
**IR:** < Application, Lcom/squareup/okhttp/internal/DiskLruCache, open(Ljava/io/File;IIJ)Lcom/squareup/okhttp/internal/DiskLruCache; >
CFG:
BB0[-1..-2]
    -> BB1
BB1[0..4]
    -> BB5
    -> BB2
BB2[5..5]
    -> BB3
    -> BB52
BB3[6..8]
    -> BB4
    -> BB52
BB4[9..9]
    -> BB52
BB5[10..12]
    -> BB9
    -> BB6
BB6[13..13]
    -> BB7
    -> BB52
BB7[14..16]
    -> BB8
    -> BB52
BB8[17..17]
    -> BB52
BB9[18..18]
    -> BB10
    -> BB52
BB10[19..22]
    -> BB11
    -> BB52
BB11[23..25]
    -> BB12
    -> BB52
BB12[26..27]
    -> BB20
    -> BB13
BB13[28..28]
    -> BB14
    -> BB52
BB14[29..32]
    -> BB15
    -> BB52
BB15[33..35]
    -> BB16
    -> BB52
BB16[36..37]
    -> BB19
    -> BB17
BB17[38..39]
    -> BB18
    -> BB52
BB18[40..41]
    -> BB20
BB19[42..45]
    -> BB20
    -> BB52
BB20[46..46]
    -> BB21
    -> BB52
BB21[47..52]
    -> BB22
    -> BB52
BB22[53..55]
    -> BB23
    -> BB52
BB23[56..56]
    -> BB24
    -> BB52
BB24[57..58]
    -> BB47
    -> BB25
BB25[59..60]
    -> BB26
    -> BB36
    -> BB52
BB26[61..62]
    -> BB27
    -> BB36
    -> BB52
BB27[63..64]
    -> BB28
    -> BB52
BB28[65..66]
    -> BB29
    -> BB52
BB29[67..68]
    -> BB30
    -> BB52
BB30[69..71]
    -> BB31
    -> BB52
BB31[72..73]
    -> BB32
    -> BB36
    -> BB52
BB32[74..75]
    -> BB33
    -> BB52
BB33[76..76]
    -> BB34
    -> BB52
BB34[77..77]
    -> BB35
    -> BB52
BB35[78..79]
    -> BB52
BB36[80..81]
    -> BB37
    -> BB52
BB37[82..82]
    -> BB38
    -> BB52
BB38[83..85]
    -> BB39
    -> BB52
BB39[86..87]
    -> BB40
    -> BB52
BB40[88..89]
    -> BB41
    -> BB52
BB41[90..91]
    -> BB42
    -> BB52
BB42[92..92]
    -> BB43
    -> BB52
BB43[93..94]
    -> BB44
    -> BB52
BB44[95..95]
    -> BB45
    -> BB52
BB45[96..96]
    -> BB46
    -> BB52
BB46[97..98]
    -> BB47
    -> BB52
BB47[99..100]
    -> BB48
    -> BB52
BB48[101..102]
    -> BB49
    -> BB52
BB49[103..108]
    -> BB50
    -> BB52
BB50[109..111]
    -> BB51
    -> BB52
BB51[112..113]
    -> BB52
BB52[-1..-2]
Instructions:
BB0
BB1
2   v7 = compare v4,v6:#0 opcode=cmp         (line 204)
4   conditional branch(gt) v7,v8:#0          (line 204)
BB2
5   v69 = new <Application,Ljava/lang/IllegalArgumentException>@6(line 205)
BB3
8   invokespecial < Application, Ljava/lang/IllegalArgumentException, <init>(Ljava/lang/String;)V > v69,v70:#maxSize <= 0 @12 exception:v71(line 205)
BB4
9   throw v69                                (line 205)
BB5
12   conditional branch(gt) v3,v8:#0         (line 207)
BB6
13   v66 = new <Application,Ljava/lang/IllegalArgumentException>@20(line 208)
BB7
16   invokespecial < Application, Ljava/lang/IllegalArgumentException, <init>(Ljava/lang/String;)V > v66,v67:#valueCount <= 0 @26 exception:v68(line 208)
BB8
17   throw v66                               (line 208)
BB9
18   v9 = new <Application,Ljava/io/File>@30 (line 212)
BB10
22   invokespecial < Application, Ljava/io/File, <init>(Ljava/io/File;Ljava/lang/String;)V > v9,v1,v10:#journal.bkp @37 exception:v11(line 212)
BB11
25   v13 = invokevirtual < Application, Ljava/io/File, exists()Z > v9 @44 exception:v12(line 213)
BB12
27   conditional branch(eq) v13,v8:#0        (line 213)
BB13
28   v14 = new <Application,Ljava/io/File>@50(line 214)
BB14
32   invokespecial < Application, Ljava/io/File, <init>(Ljava/io/File;Ljava/lang/String;)V > v14,v1,v15:#journal @57 exception:v16(line 214)
BB15
35   v18 = invokevirtual < Application, Ljava/io/File, exists()Z > v14 @64 exception:v17(line 216)
BB16
37   conditional branch(eq) v18,v8:#0        (line 216)
BB17
39   v21 = invokevirtual < Application, Ljava/io/File, delete()Z > v9 @72 exception:v20(line 217)
BB18
41   goto                                    (line 217)
BB19
45   invokestatic < Application, Lcom/squareup/okhttp/internal/DiskLruCache, renameTo(Ljava/io/File;Ljava/io/File;Z)V > v9,v14,v8:#0 @84 exception:v19(line 219)
BB20
46   v22 = new <Application,Lcom/squareup/okhttp/internal/DiskLruCache>@87(line 224)
BB21
52   invokespecial < Application, Lcom/squareup/okhttp/internal/DiskLruCache, <init>(Ljava/io/File;IIJ)V > v22,v1,v2,v3,v4 @95 exception:v23(line 224)
BB22
55   v24 = getfield < Application, Lcom/squareup/okhttp/internal/DiskLruCache, journalFile, <Application,Ljava/io/File> > v22(line 225)
BB23
56   v26 = invokevirtual < Application, Ljava/io/File, exists()Z > v24 @105 exception:v25(line 225)
BB24
58   conditional branch(eq) v26,v8:#0        (line 225)
BB25
60   invokespecial < Application, Lcom/squareup/okhttp/internal/DiskLruCache, readJournal()V > v22 @113 exception:v27(line 227)
BB26
62   invokespecial < Application, Lcom/squareup/okhttp/internal/DiskLruCache, processJournal()V > v22 @118 exception:v28(line 228)
BB27
64   v29 = new <Application,Ljava/io/BufferedWriter>@123(line 229)
BB28
66   v30 = new <Application,Ljava/io/OutputStreamWriter>@127(line 229)
BB29
68   v31 = new <Application,Ljava/io/FileOutputStream>@131(line 230)
BB30
71   v32 = getfield < Application, Lcom/squareup/okhttp/internal/DiskLruCache, journalFile, <Application,Ljava/io/File> > v22(line 230)
BB31
73   invokespecial < Application, Ljava/io/FileOutputStream, <init>(Ljava/io/File;Z)V > v31,v32,v33:#1 @141 exception:v34(line 230)
BB32
74   v63 = getstatic < Application, Lcom/squareup/okhttp/internal/Util, US_ASCII, <Application,Ljava/nio/charset/Charset> >(line 230)
75   invokespecial < Application, Ljava/io/OutputStreamWriter, <init>(Ljava/io/OutputStream;Ljava/nio/charset/Charset;)V > v30,v31,v63 @147 exception:v64(line 230)
BB33
76   invokespecial < Application, Ljava/io/BufferedWriter, <init>(Ljava/io/Writer;)V > v29,v30 @150 exception:v65(line 230)
BB34
77   putfield v22 = v29 < Application, Lcom/squareup/okhttp/internal/DiskLruCache, journalWriter, <Application,Ljava/io/Writer> >(line 229)
BB35
79   return v22                              (line 231)
BB36<Handler>
           v35 = getCaughtException 
81   v37 = invokestatic < Application, Lcom/squareup/okhttp/internal/Platform, get()Lcom/squareup/okhttp/internal/Platform; > @161 exception:v36(line 233)
BB37
82   v38 = new <Application,Ljava/lang/StringBuilder>@164(line 233)
BB38
85   invokespecial < Application, Ljava/lang/StringBuilder, <init>(Ljava/lang/String;)V > v38,v39:#DiskLruCache  @170 exception:v40(line 233)
BB39
87   v42 = invokevirtual < Application, Ljava/lang/StringBuilder, append(Ljava/lang/Object;)Ljava/lang/StringBuilder; > v38,v1 @174 exception:v41(line 233)
BB40
89   v45 = invokevirtual < Application, Ljava/lang/StringBuilder, append(Ljava/lang/String;)Ljava/lang/StringBuilder; > v42,v43:# is corrupt:  @179 exception:v44(line 233)
BB41
91   v47 = invokevirtual < Application, Ljava/io/IOException, getMessage()Ljava/lang/String; > v35 @184 exception:v46(line 234)
BB42
92   v49 = invokevirtual < Application, Ljava/lang/StringBuilder, append(Ljava/lang/String;)Ljava/lang/StringBuilder; > v45,v47 @187 exception:v48(line 234)
BB43
94   v52 = invokevirtual < Application, Ljava/lang/StringBuilder, append(Ljava/lang/String;)Ljava/lang/StringBuilder; > v49,v50:#, removing @192 exception:v51(line 234)
BB44
95   v54 = invokevirtual < Application, Ljava/lang/StringBuilder, toString()Ljava/lang/String; > v52 @195 exception:v53(line 234)
BB45
96   invokevirtual < Application, Lcom/squareup/okhttp/internal/Platform, logW(Ljava/lang/String;)V > v37,v54 @198 exception:v55(line 233)
BB46
98   invokevirtual < Application, Lcom/squareup/okhttp/internal/DiskLruCache, delete()V > v22 @203 exception:v56(line 235)
BB47
100   v59 = invokevirtual < Application, Ljava/io/File, mkdirs()Z > v1 @207 exception:v58(line 240)
BB48
102   v60 = new <Application,Lcom/squareup/okhttp/internal/DiskLruCache>@211(line 241)
BB49
108   invokespecial < Application, Lcom/squareup/okhttp/internal/DiskLruCache, <init>(Ljava/io/File;IIJ)V > v60,v1,v2,v3,v4 @219 exception:v61(line 241)
BB50
111   invokespecial < Application, Lcom/squareup/okhttp/internal/DiskLruCache, rebuildJournal()V > v60 @226 exception:v62(line 242)
BB51
113   return v60                             (line 243)
BB52

**CGNode:** Node: < Application, Lcom/squareup/okhttp/internal/DiskLruCache, <clinit>()V > Context: Everywhere
**IR:** < Application, Lcom/squareup/okhttp/internal/DiskLruCache, <clinit>()V >
CFG:
BB0[-1..-2]
    -> BB1
BB1[0..1]
    -> BB2
    -> BB5
BB2[2..3]
    -> BB3
    -> BB5
BB3[4..5]
    -> BB4
    -> BB5
BB4[6..7]
    -> BB5
BB5[-1..-2]
Instructions:
BB0
BB1
1   v4 = invokestatic < Application, Ljava/util/regex/Pattern, compile(Ljava/lang/String;)Ljava/util/regex/Pattern; > v2:#[a-z0-9_-]{1,64} @2 exception:v3(line 97)
BB2
2   putstatic v4 < Application, Lcom/squareup/okhttp/internal/DiskLruCache, LEGAL_KEY_PATTERN, <Application,Ljava/util/regex/Pattern> >(line 97)
3   v5 = new <Application,Lcom/squareup/okhttp/internal/DiskLruCache$2>@8(line 731)
BB3
5   invokespecial < Application, Lcom/squareup/okhttp/internal/DiskLruCache$2, <init>()V > v5 @12 exception:v6(line 731)
BB4
6   putstatic v5 < Application, Lcom/squareup/okhttp/internal/DiskLruCache, NULL_OUTPUT_STREAM, <Application,Ljava/io/OutputStream> >(line 731)
7   return                                   (line 90)
BB5

**CGNode:** Node: < Application, Lcom/squareup/okhttp/internal/spdy/SpdyConnection, <clinit>()V > Context: Everywhere
**IR:** < Application, Lcom/squareup/okhttp/internal/spdy/SpdyConnection, <clinit>()V >
CFG:
BB0[-1..-2]
    -> BB1
BB1[0..0]
    -> BB2
    -> BB12
BB2[1..1]
    -> BB3
    -> BB12
BB3[2..3]
    -> BB5
    -> BB4
BB4[4..5]
    -> BB6
BB5[6..6]
    -> BB6
BB6[7..8]
    -> BB7
    -> BB12
BB7[9..14]
    -> BB8
    -> BB12
BB8[15..16]
    -> BB9
    -> BB12
BB9[17..17]
    -> BB10
    -> BB12
BB10[18..18]
    -> BB11
    -> BB12
BB11[19..20]
    -> BB12
BB12[-1..-2]
Instructions:
BB0
BB1
0   v2 = load_metadata: <Primordial,Lcom/squareup/okhttp/internal/spdy/SpdyConnection>, <Primordial,Ljava/lang/Class>(line 49)
BB2
1   v4 = invokevirtual < Application, Ljava/lang/Class, desiredAssertionStatus()Z > v2 @2 exception:v3(line 49)
BB3
3   conditional branch(ne) v4,v5:#0          (line 49)
BB4
5   goto                                     (line 49)
BB5
BB6
           v7 = phi  v6:#1,v5:#0
7   putstatic v7 < Application, Lcom/squareup/okhttp/internal/spdy/SpdyConnection, $assertionsDisabled, <Primordial,Z> >(line 49)
8   v8 = new <Application,Ljava/util/concurrent/ThreadPoolExecutor>@16(line 84)
BB7
13   v11 = getstatic < Application, Ljava/util/concurrent/TimeUnit, SECONDS, <Application,Ljava/util/concurrent/TimeUnit> >(line 84)
14   v12 = new <Application,Ljava/util/concurrent/SynchronousQueue>@29(line 85)
BB8
16   invokespecial < Application, Ljava/util/concurrent/SynchronousQueue, <init>()V > v12 @33 exception:v13(line 85)
BB9
17   v15 = invokestatic < Application, Ljava/util/concurrent/Executors, defaultThreadFactory()Ljava/util/concurrent/ThreadFactory; > @36 exception:v14(line 85)
BB10
18   invokespecial < Application, Ljava/util/concurrent/ThreadPoolExecutor, <init>(IIJLjava/util/concurrent/TimeUnit;Ljava/util/concurrent/BlockingQueue;Ljava/util/concurrent/ThreadFactory;)V > v8,v5:#0,v9:#2147483647,v10:#60,v11,v12,v15 @39 exception:v16(line 84)
BB11
19   putstatic v8 < Application, Lcom/squareup/okhttp/internal/spdy/SpdyConnection, executor, <Application,Ljava/util/concurrent/ExecutorService> >(line 83)
20   return                                  (line 83)
BB12

**CGNode:** Node: < Application, Lcom/squareup/okhttp/internal/spdy/SpdyConnection, newStream(Ljava/util/List;ZZ)Lcom/squareup/okhttp/internal/spdy/SpdyStream; > Context: JavaTypeContext<point: <Application,Lcom/squareup/okhttp/internal/spdy/SpdyConnection>>
**IR:** < Application, Lcom/squareup/okhttp/internal/spdy/SpdyConnection, newStream(Ljava/util/List;ZZ)Lcom/squareup/okhttp/internal/spdy/SpdyStream; >
CFG:
BB0[-1..-2]
    -> BB1
BB1[0..2]
    -> BB3
    -> BB2
BB2[3..4]
    -> BB4
BB3[5..5]
    -> BB4
BB4[6..8]
    -> BB6
    -> BB5
BB5[9..10]
    -> BB7
BB6[11..11]
    -> BB7
BB7[12..21]
    -> BB8
    -> BB38
BB8[22..24]
    -> BB9
    -> BB38
BB9[25..28]
    -> BB10
    -> BB35
BB10[29..30]
    -> BB11
    -> BB29
BB11[31..32]
    -> BB15
    -> BB12
BB12[33..33]
    -> BB13
    -> BB29
BB13[34..36]
    -> BB14
    -> BB29
BB14[37..37]
    -> BB29
BB15[38..39]
    -> BB16
    -> BB29
BB16[40..43]
    -> BB17
    -> BB29
BB17[44..46]
    -> BB18
    -> BB29
BB18[47..47]
    -> BB19
    -> BB29
BB19[48..56]
    -> BB20
    -> BB29
BB20[57..57]
    -> BB21
    -> BB29
BB21[58..60]
    -> BB22
    -> BB29
BB22[61..62]
    -> BB27
    -> BB23
BB23[63..64]
    -> BB24
    -> BB29
BB24[65..66]
    -> BB25
    -> BB29
BB25[67..68]
    -> BB26
    -> BB29
BB26[69..72]
    -> BB27
    -> BB29
BB27[73..74]
    -> BB28
    -> BB29
BB28[75..75]
    -> BB31
BB29[76..77]
    -> BB30
    -> BB29
BB30[78..78]
    -> BB35
BB31[79..80]
    -> BB32
    -> BB35
BB32[81..87]
    -> BB33
    -> BB35
BB33[88..89]
    -> BB34
    -> BB35
BB34[90..90]
    -> BB37
BB35[91..92]
    -> BB36
    -> BB35
BB36[93..93]
    -> BB38
BB37[94..95]
    -> BB38
BB38[-1..-2]
Instructions:
BB0
BB1
2   conditional branch(eq) v3,v6:#0          (line 170)
BB2
4   goto                                     (line 170)
BB3
BB4
           v8 = phi  v6:#0,v7:#1
8   conditional branch(eq) v4,v6:#0          (line 170)
BB5
10   goto                                    (line 170)
BB6
BB7
           v10 = phi  v6:#0,v9:#2
12   v11 = binaryop(or) v8 , v10             (line 170)
21   v12 = getfield < Application, Lcom/squareup/okhttp/internal/spdy/SpdyConnection, spdyWriter, <Application,Lcom/squareup/okhttp/internal/spdy/SpdyWriter> > v1(line 177)
BB8
24   monitorenter v12                        (line 177)
BB9
28   monitorenter v1                         (line 178)
BB10
30   v13 = getfield < Application, Lcom/squareup/okhttp/internal/spdy/SpdyConnection, shutdown, <Primordial,Z> > v1(line 179)
BB11
32   conditional branch(eq) v13,v6:#0        (line 179)
BB12
33   v30 = new <Application,Ljava/io/IOException>@50(line 180)
BB13
36   invokespecial < Application, Ljava/io/IOException, <init>(Ljava/lang/String;)V > v30,v31:#shutdown @56 exception:v32(line 180)
BB14
37   throw v30                               (line 180)
BB15
39   v14 = getfield < Application, Lcom/squareup/okhttp/internal/spdy/SpdyConnection, nextStreamId, <Primordial,I> > v1(line 182)
BB16
43   v15 = getfield < Application, Lcom/squareup/okhttp/internal/spdy/SpdyConnection, nextStreamId, <Primordial,I> > v1(line 183)
BB17
45   v16 = binaryop(add) v15 , v9:#2         (line 183)
46   putfield v1 = v16 < Application, Lcom/squareup/okhttp/internal/spdy/SpdyConnection, nextStreamId, <Primordial,I> >(line 183)
BB18
47   v17 = new <Application,Lcom/squareup/okhttp/internal/spdy/SpdyStream>@76(line 184)
BB19
56   v18 = getfield < Application, Lcom/squareup/okhttp/internal/spdy/SpdyConnection, settings, <Application,Lcom/squareup/okhttp/internal/spdy/Settings> > v1(line 184)
BB20
57   invokespecial < Application, Lcom/squareup/okhttp/internal/spdy/SpdyStream, <init>(ILcom/squareup/okhttp/internal/spdy/SpdyConnection;IIILjava/util/List;Lcom/squareup/okhttp/internal/spdy/Settings;)V > v17,v14,v1,v11,v6:#0,v6:#0,v2,v18 @94 exception:v19(line 184)
BB21
60   v21 = invokevirtual < Application, Lcom/squareup/okhttp/internal/spdy/SpdyStream, isOpen()Z > v17 @101 exception:v20(line 185)
BB22
62   conditional branch(eq) v21,v6:#0        (line 185)
BB23
64   v22 = getfield < Application, Lcom/squareup/okhttp/internal/spdy/SpdyConnection, streams, <Application,Ljava/util/Map> > v1(line 186)
BB24
66   v24 = invokestatic < Application, Ljava/lang/Integer, valueOf(I)Ljava/lang/Integer; > v14 @113 exception:v23(line 186)
BB25
68   v26 = invokeinterface < Application, Ljava/util/Map, put(Ljava/lang/Object;Ljava/lang/Object;)Ljava/lang/Object; > v22,v24,v17 @118 exception:v25(line 186)
BB26
72   invokespecial < Application, Lcom/squareup/okhttp/internal/spdy/SpdyConnection, setIdle(Z)V > v1,v6:#0 @126 exception:v27(line 187)
BB27
74   monitorexit v1                          (line 178)
BB28
75   goto                                    (line 178)
BB29<Handler>
           v33 = getCaughtException 
77   monitorexit v1                          (line 178)
BB30
78   throw v33                               (line 178)
BB31
80   v28 = getfield < Application, Lcom/squareup/okhttp/internal/spdy/SpdyConnection, spdyWriter, <Application,Lcom/squareup/okhttp/internal/spdy/SpdyWriter> > v1(line 191)
BB32
87   invokevirtual < Application, Lcom/squareup/okhttp/internal/spdy/SpdyWriter, synStream(IIIIILjava/util/List;)V > v28,v11,v14,v6:#0,v6:#0,v6:#0,v2 @154 exception:v29(line 191)
BB33
89   monitorexit v12                         (line 177)
BB34
90   goto                                    (line 177)
BB35<Handler>
           v34 = getCaughtException 
92   monitorexit v12                         (line 177)
BB36
93   throw v34                               (line 177)
BB37
95   return v17                              (line 194)
BB38

**CGNode:** Node: < Application, Lcom/squareup/okhttp/internal/DiskLruCache, renameTo(Ljava/io/File;Ljava/io/File;Z)V > Context: JavaTypeContext<point: <Primordial,Ljava/io/File>>
**IR:** < Application, Lcom/squareup/okhttp/internal/DiskLruCache, renameTo(Ljava/io/File;Ljava/io/File;Z)V >
CFG:
BB0[-1..-2]
    -> BB1
BB1[0..2]
    -> BB3
    -> BB2
BB2[3..4]
    -> BB3
    -> BB9
BB3[5..7]
    -> BB4
    -> BB9
BB4[8..9]
    -> BB8
    -> BB5
BB5[10..10]
    -> BB6
    -> BB9
BB6[11..12]
    -> BB7
    -> BB9
BB7[13..13]
    -> BB9
BB8[14..14]
    -> BB9
BB9[-1..-2]
Instructions:
BB0
BB1
2   conditional branch(eq) v3,v5:#0          (line 392)
BB2
4   invokestatic < Application, Lcom/squareup/okhttp/internal/DiskLruCache, deleteIfExists(Ljava/io/File;)V > v2 @5 exception:v6(line 393)
BB3
7   v8 = invokevirtual < Application, Ljava/io/File, renameTo(Ljava/io/File;)Z > v1,v2 @10 exception:v7(line 395)
BB4
9   conditional branch(ne) v8,v5:#0          (line 395)
BB5
10   v9 = new <Application,Ljava/io/IOException>@16(line 396)
BB6
12   invokespecial < Application, Ljava/io/IOException, <init>()V > v9 @20 exception:v10(line 396)
BB7
13   throw v9                                (line 396)
BB8
14   return                                  (line 398)
BB9

**CGNode:** Node: < Application, Lcom/squareup/okhttp/internal/DiskLruCache, <init>(Ljava/io/File;IIJ)V > Context: JavaTypeContext<point: <Application,Lcom/squareup/okhttp/internal/DiskLruCache>>
**IR:** < Application, Lcom/squareup/okhttp/internal/DiskLruCache, <init>(Ljava/io/File;IIJ)V >
CFG:
BB0[-1..-2]
    -> BB1
BB1[0..1]
    -> BB2
    -> BB29
BB2[2..4]
    -> BB3
    -> BB29
BB3[5..6]
    -> BB4
    -> BB29
BB4[7..11]
    -> BB5
    -> BB29
BB5[12..12]
    -> BB6
    -> BB29
BB6[13..15]
    -> BB7
    -> BB29
BB7[16..17]
    -> BB8
    -> BB29
BB8[18..23]
    -> BB9
    -> BB29
BB9[24..25]
    -> BB10
    -> BB29
BB10[26..26]
    -> BB11
    -> BB29
BB11[27..27]
    -> BB12
    -> BB29
BB12[28..29]
    -> BB13
    -> BB29
BB13[30..32]
    -> BB14
    -> BB29
BB14[33..33]
    -> BB15
    -> BB29
BB15[34..36]
    -> BB16
    -> BB29
BB16[37..39]
    -> BB17
    -> BB29
BB17[40..41]
    -> BB18
    -> BB29
BB18[42..45]
    -> BB19
    -> BB29
BB19[46..46]
    -> BB20
    -> BB29
BB20[47..48]
    -> BB21
    -> BB29
BB21[49..52]
    -> BB22
    -> BB29
BB22[53..53]
    -> BB23
    -> BB29
BB23[54..55]
    -> BB24
    -> BB29
BB24[56..59]
    -> BB25
    -> BB29
BB25[60..60]
    -> BB26
    -> BB29
BB26[61..63]
    -> BB27
    -> BB29
BB27[64..66]
    -> BB28
    -> BB29
BB28[67..67]
    -> BB29
BB29[-1..-2]
Instructions:
BB0
BB1
1   invokespecial < Application, Ljava/lang/Object, <init>()V > v1 @1 exception:v7(line 182)
BB2
4   putfield v1 = v8:#0 < Application, Lcom/squareup/okhttp/internal/DiskLruCache, size, <Primordial,J> >(line 150)
BB3
6   v9 = new <Application,Ljava/util/LinkedHashMap>@10(line 153)
BB4
11   invokespecial < Application, Ljava/util/LinkedHashMap, <init>(IFZ)V > v9,v10:#0,v11:#0.75,v12:#1 @18 exception:v13(line 153)
BB5
12   putfield v1 = v9 < Application, Lcom/squareup/okhttp/internal/DiskLruCache, lruEntries, <Application,Ljava/util/LinkedHashMap> >(line 153)
BB6
15   putfield v1 = v8:#0 < Application, Lcom/squareup/okhttp/internal/DiskLruCache, nextSequenceNumber, <Primordial,J> >(line 161)
BB7
17   v14 = new <Application,Ljava/util/concurrent/ThreadPoolExecutor>@30(line 164)
BB8
22   v16 = getstatic < Application, Ljava/util/concurrent/TimeUnit, SECONDS, <Application,Ljava/util/concurrent/TimeUnit> >(line 165)
23   v17 = new <Application,Ljava/util/concurrent/LinkedBlockingQueue>@42(line 165)
BB9
25   invokespecial < Application, Ljava/util/concurrent/LinkedBlockingQueue, <init>()V > v17 @46 exception:v18(line 165)
BB10
26   invokespecial < Application, Ljava/util/concurrent/ThreadPoolExecutor, <init>(IIJLjava/util/concurrent/TimeUnit;Ljava/util/concurrent/BlockingQueue;)V > v14,v10:#0,v12:#1,v15:#60,v16,v17 @49 exception:v19(line 165)
BB11
27   putfield v1 = v14 < Application, Lcom/squareup/okhttp/internal/DiskLruCache, executorService, <Application,Ljava/util/concurrent/ThreadPoolExecutor> >(line 165)
BB12
29   v20 = new <Application,Lcom/squareup/okhttp/internal/DiskLruCache$1>@56(line 166)
BB13
32   invokespecial < Application, Lcom/squareup/okhttp/internal/DiskLruCache$1, <init>(Lcom/squareup/okhttp/internal/DiskLruCache;)V > v20,v1 @61 exception:v21(line 166)
BB14
33   putfield v1 = v20 < Application, Lcom/squareup/okhttp/internal/DiskLruCache, cleanupCallable, <Application,Ljava/util/concurrent/Callable> >(line 166)
BB15
36   putfield v1 = v2 < Application, Lcom/squareup/okhttp/internal/DiskLruCache, directory, <Application,Ljava/io/File> >(line 183)
BB16
39   putfield v1 = v3 < Application, Lcom/squareup/okhttp/internal/DiskLruCache, appVersion, <Primordial,I> >(line 184)
BB17
41   v22 = new <Application,Ljava/io/File>@78(line 185)
BB18
45   invokespecial < Application, Ljava/io/File, <init>(Ljava/io/File;Ljava/lang/String;)V > v22,v2,v23:#journal @85 exception:v24(line 185)
BB19
46   putfield v1 = v22 < Application, Lcom/squareup/okhttp/internal/DiskLruCache, journalFile, <Application,Ljava/io/File> >(line 185)
BB20
48   v25 = new <Application,Ljava/io/File>@92(line 186)
BB21
52   invokespecial < Application, Ljava/io/File, <init>(Ljava/io/File;Ljava/lang/String;)V > v25,v2,v26:#journal.tmp @99 exception:v27(line 186)
BB22
53   putfield v1 = v25 < Application, Lcom/squareup/okhttp/internal/DiskLruCache, journalFileTmp, <Application,Ljava/io/File> >(line 186)
BB23
55   v28 = new <Application,Ljava/io/File>@106(line 187)
BB24
59   invokespecial < Application, Ljava/io/File, <init>(Ljava/io/File;Ljava/lang/String;)V > v28,v2,v29:#journal.bkp @113 exception:v30(line 187)
BB25
60   putfield v1 = v28 < Application, Lcom/squareup/okhttp/internal/DiskLruCache, journalFileBkp, <Application,Ljava/io/File> >(line 187)
BB26
63   putfield v1 = v4 < Application, Lcom/squareup/okhttp/internal/DiskLruCache, valueCount, <Primordial,I> >(line 188)
BB27
66   putfield v1 = v5 < Application, Lcom/squareup/okhttp/internal/DiskLruCache, maxSize, <Primordial,J> >(line 189)
BB28
67   return                                  (line 190)
BB29

**CGNode:** Node: < Application, Lcom/squareup/okhttp/internal/DiskLruCache, readJournal()V > Context: JavaTypeContext<point: <Application,Lcom/squareup/okhttp/internal/DiskLruCache>>
**IR:** < Application, Lcom/squareup/okhttp/internal/DiskLruCache, readJournal()V >
CFG:
BB0[-1..-2]
    -> BB1
BB1[0..0]
    -> BB2
    -> BB51
BB2[1..2]
    -> BB3
    -> BB51
BB3[3..5]
    -> BB4
    -> BB51
BB4[6..6]
    -> BB5
    -> BB51
BB5[7..8]
    -> BB6
    -> BB51
BB6[9..11]
    -> BB7
    -> BB47
BB7[12..14]
    -> BB8
    -> BB47
BB8[15..17]
    -> BB9
    -> BB47
BB9[18..20]
    -> BB10
    -> BB47
BB10[21..23]
    -> BB11
    -> BB47
BB11[24..27]
    -> BB12
    -> BB47
BB12[28..29]
    -> BB25
    -> BB13
BB13[30..32]
    -> BB14
    -> BB47
BB14[33..34]
    -> BB25
    -> BB15
BB15[35..36]
    -> BB16
    -> BB47
BB16[37..37]
    -> BB17
    -> BB47
BB17[38..39]
    -> BB18
    -> BB47
BB18[40..41]
    -> BB25
    -> BB19
BB19[42..43]
    -> BB20
    -> BB47
BB20[44..44]
    -> BB21
    -> BB47
BB21[45..46]
    -> BB22
    -> BB47
BB22[47..48]
    -> BB25
    -> BB23
BB23[49..51]
    -> BB24
    -> BB47
BB24[52..53]
    -> BB39
    -> BB25
BB25[54..54]
    -> BB26
    -> BB47
BB26[55..56]
    -> BB27
    -> BB47
BB27[57..59]
    -> BB28
    -> BB47
BB28[60..61]
    -> BB29
    -> BB47
BB29[62..63]
    -> BB30
    -> BB47
BB30[64..65]
    -> BB31
    -> BB47
BB31[66..67]
    -> BB32
    -> BB47
BB32[68..69]
    -> BB33
    -> BB47
BB33[70..71]
    -> BB34
    -> BB47
BB34[72..73]
    -> BB35
    -> BB47
BB35[74..75]
    -> BB36
    -> BB47
BB36[76..76]
    -> BB37
    -> BB47
BB37[77..77]
    -> BB38
    -> BB47
BB38[78..78]
    -> BB47
BB39[79..80]
    -> BB40
BB40[81..83]
    -> BB41
    -> BB43
    -> BB47
BB41[84..84]
    -> BB42
    -> BB43
    -> BB47
BB42[85..89]
    -> BB40
BB43[90..94]
    -> BB44
    -> BB47
BB44[95..95]
    -> BB45
    -> BB47
BB45[96..97]
    -> BB46
    -> BB47
BB46[98..98]
    -> BB49
BB47[99..101]
    -> BB48
    -> BB51
BB48[102..103]
    -> BB51
BB49[104..105]
    -> BB50
    -> BB51
BB50[106..106]
    -> BB51
BB51[-1..-2]
Instructions:
BB0
BB1
0   v3 = new <Application,Lcom/squareup/okhttp/internal/StrictLineReader>@0(line 247)
BB2
2   v4 = new <Application,Ljava/io/FileInputStream>@4(line 247)
BB3
5   v5 = getfield < Application, Lcom/squareup/okhttp/internal/DiskLruCache, journalFile, <Application,Ljava/io/File> > v1(line 247)
BB4
6   invokespecial < Application, Ljava/io/FileInputStream, <init>(Ljava/io/File;)V > v4,v5 @12 exception:v6(line 247)
BB5
7   v7 = getstatic < Application, Lcom/squareup/okhttp/internal/Util, US_ASCII, <Application,Ljava/nio/charset/Charset> >(line 248)
8   invokespecial < Application, Lcom/squareup/okhttp/internal/StrictLineReader, <init>(Ljava/io/InputStream;Ljava/nio/charset/Charset;)V > v3,v4,v7 @18 exception:v8(line 247)
BB6
11   v10 = invokevirtual < Application, Lcom/squareup/okhttp/internal/StrictLineReader, readLine()Ljava/lang/String; > v3 @23 exception:v9(line 250)
BB7
14   v12 = invokevirtual < Application, Lcom/squareup/okhttp/internal/StrictLineReader, readLine()Ljava/lang/String; > v3 @28 exception:v11(line 251)
BB8
17   v14 = invokevirtual < Application, Lcom/squareup/okhttp/internal/StrictLineReader, readLine()Ljava/lang/String; > v3 @33 exception:v13(line 252)
BB9
20   v16 = invokevirtual < Application, Lcom/squareup/okhttp/internal/StrictLineReader, readLine()Ljava/lang/String; > v3 @39 exception:v15(line 253)
BB10
23   v18 = invokevirtual < Application, Lcom/squareup/okhttp/internal/StrictLineReader, readLine()Ljava/lang/String; > v3 @45 exception:v17(line 254)
BB11
27   v21 = invokevirtual < Application, Ljava/lang/String, equals(Ljava/lang/Object;)Z > v19:#libcore.io.DiskLruCache,v10 @53 exception:v20(line 255)
BB12
29   conditional branch(eq) v21,v22:#0       (line 255)
BB13
32   v25 = invokevirtual < Application, Ljava/lang/String, equals(Ljava/lang/Object;)Z > v23:#1,v12 @62 exception:v24(line 256)
BB14
34   conditional branch(eq) v25,v22:#0       (line 256)
BB15
36   v26 = getfield < Application, Lcom/squareup/okhttp/internal/DiskLruCache, appVersion, <Primordial,I> > v1(line 257)
BB16
37   v28 = invokestatic < Application, Ljava/lang/Integer, toString(I)Ljava/lang/String; > v26 @72 exception:v27(line 257)
BB17
39   v30 = invokevirtual < Application, Ljava/lang/String, equals(Ljava/lang/Object;)Z > v28,v14 @77 exception:v29(line 257)
BB18
41   conditional branch(eq) v30,v22:#0       (line 257)
BB19
43   v31 = getfield < Application, Lcom/squareup/okhttp/internal/DiskLruCache, valueCount, <Primordial,I> > v1(line 258)
BB20
44   v33 = invokestatic < Application, Ljava/lang/Integer, toString(I)Ljava/lang/String; > v31 @87 exception:v32(line 258)
BB21
46   v35 = invokevirtual < Application, Ljava/lang/String, equals(Ljava/lang/Object;)Z > v33,v16 @92 exception:v34(line 258)
BB22
48   conditional branch(eq) v35,v22:#0       (line 258)
BB23
51   v38 = invokevirtual < Application, Ljava/lang/String, equals(Ljava/lang/Object;)Z > v36:#,v18 @103 exception:v37(line 259)
BB24
53   conditional branch(ne) v38,v22:#0       (line 259)
BB25
54   v51 = new <Application,Ljava/io/IOException>@109(line 260)
BB26
56   v52 = new <Application,Ljava/lang/StringBuilder>@113(line 260)
BB27
59   invokespecial < Application, Ljava/lang/StringBuilder, <init>(Ljava/lang/String;)V > v52,v53:#unexpected journal header: [ @120 exception:v54(line 260)
BB28
61   v56 = invokevirtual < Application, Ljava/lang/StringBuilder, append(Ljava/lang/String;)Ljava/lang/StringBuilder; > v52,v10 @124 exception:v55(line 261)
BB29
63   v59 = invokevirtual < Application, Ljava/lang/StringBuilder, append(Ljava/lang/String;)Ljava/lang/StringBuilder; > v56,v57:#,  @130 exception:v58(line 261)
BB30
65   v61 = invokevirtual < Application, Ljava/lang/StringBuilder, append(Ljava/lang/String;)Ljava/lang/StringBuilder; > v59,v12 @134 exception:v60(line 261)
BB31
67   v63 = invokevirtual < Application, Ljava/lang/StringBuilder, append(Ljava/lang/String;)Ljava/lang/StringBuilder; > v61,v57:#,  @140 exception:v62(line 261)
BB32
69   v65 = invokevirtual < Application, Ljava/lang/StringBuilder, append(Ljava/lang/String;)Ljava/lang/StringBuilder; > v63,v16 @145 exception:v64(line 261)
BB33
71   v67 = invokevirtual < Application, Ljava/lang/StringBuilder, append(Ljava/lang/String;)Ljava/lang/StringBuilder; > v65,v57:#,  @151 exception:v66(line 261)
BB34
73   v69 = invokevirtual < Application, Ljava/lang/StringBuilder, append(Ljava/lang/String;)Ljava/lang/StringBuilder; > v67,v18 @156 exception:v68(line 261)
BB35
75   v72 = invokevirtual < Application, Ljava/lang/StringBuilder, append(Ljava/lang/String;)Ljava/lang/StringBuilder; > v69,v70:#] @162 exception:v71(line 261)
BB36
76   v74 = invokevirtual < Application, Ljava/lang/StringBuilder, toString()Ljava/lang/String; > v72 @165 exception:v73(line 261)
BB37
77   invokespecial < Application, Ljava/io/IOException, <init>(Ljava/lang/String;)V > v51,v74 @168 exception:v75(line 260)
BB38
78   throw v51                               (line 260)
BB39
BB40
           v44 = phi  v43,v22:#0
83   v40 = invokevirtual < Application, Lcom/squareup/okhttp/internal/StrictLineReader, readLine()Ljava/lang/String; > v3 @177 exception:v39(line 267)
BB41
84   invokespecial < Application, Lcom/squareup/okhttp/internal/DiskLruCache, readJournalLine(Ljava/lang/String;)V > v1,v40 @180 exception:v41(line 267)
BB42
87   v43 = binaryop(add) v44 , v42:#1        (line 268)
89   goto                                    (line 268)
BB43<Handler>
           v45 = getCaughtException 
94   v46 = getfield < Application, Lcom/squareup/okhttp/internal/DiskLruCache, lruEntries, <Application,Ljava/util/LinkedHashMap> > v1(line 273)
BB44
95   v48 = invokevirtual < Application, Ljava/util/LinkedHashMap, size()I > v46 @198 exception:v47(line 273)
BB45
96   v49 = binaryop(sub) v44 , v48           (line 273)
97   putfield v1 = v49 < Application, Lcom/squareup/okhttp/internal/DiskLruCache, redundantOpCount, <Primordial,I> >(line 273)
BB46
98   goto                                    (line 273)
BB47<Handler>
           v76 = getCaughtException 
101   invokestatic < Application, Lcom/squareup/okhttp/internal/Util, closeQuietly(Ljava/io/Closeable;)V > v3 @211 exception:v77(line 275)
BB48
103   throw v76                              (line 276)
BB49
105   invokestatic < Application, Lcom/squareup/okhttp/internal/Util, closeQuietly(Ljava/io/Closeable;)V > v3 @218 exception:v50(line 275)
BB50
106   return                                 (line 277)
BB51

**CGNode:** Node: < Application, Lcom/squareup/okhttp/internal/DiskLruCache, processJournal()V > Context: JavaTypeContext<point: <Application,Lcom/squareup/okhttp/internal/DiskLruCache>>
**IR:** < Application, Lcom/squareup/okhttp/internal/DiskLruCache, processJournal()V >
CFG:
BB0[-1..-2]
    -> BB1
BB1[0..1]
    -> BB2
    -> BB33
BB2[2..2]
    -> BB3
    -> BB33
BB3[3..4]
    -> BB4
    -> BB33
BB4[5..5]
    -> BB5
    -> BB33
BB5[6..6]
    -> BB6
    -> BB33
BB6[7..8]
    -> BB30
BB7[9..10]
    -> BB8
    -> BB33
BB8[11..11]
    -> BB9
    -> BB33
BB9[12..14]
    -> BB10
    -> BB33
BB10[15..16]
    -> BB20
    -> BB11
BB11[17..19]
    -> BB17
BB12[20..22]
    -> BB13
    -> BB33
BB13[23..24]
    -> BB14
    -> BB33
BB14[25..26]
    -> BB15
    -> BB33
BB15[27..28]
    -> BB16
    -> BB33
BB16[29..32]
    -> BB17
BB17[33..35]
    -> BB18
    -> BB33
BB18[36..36]
    -> BB12
    -> BB19
BB19[37..37]
    -> BB30
BB20[38..40]
    -> BB21
    -> BB33
BB21[41..43]
    -> BB27
BB22[44..46]
    -> BB23
    -> BB33
BB23[47..47]
    -> BB24
    -> BB33
BB24[48..50]
    -> BB25
    -> BB33
BB25[51..51]
    -> BB26
    -> BB33
BB26[52..55]
    -> BB27
BB27[56..58]
    -> BB28
    -> BB33
BB28[59..59]
    -> BB22
    -> BB29
BB29[60..61]
    -> BB30
    -> BB33
BB30[62..63]
    -> BB31
    -> BB33
BB31[64..65]
    -> BB7
    -> BB32
BB32[66..66]
    -> BB33
BB33[-1..-2]
Instructions:
BB0
BB1
1   v3 = getfield < Application, Lcom/squareup/okhttp/internal/DiskLruCache, journalFileTmp, <Application,Ljava/io/File> > v1(line 323)
BB2
2   invokestatic < Application, Lcom/squareup/okhttp/internal/DiskLruCache, deleteIfExists(Ljava/io/File;)V > v3 @4 exception:v4(line 323)
BB3
4   v5 = getfield < Application, Lcom/squareup/okhttp/internal/DiskLruCache, lruEntries, <Application,Ljava/util/LinkedHashMap> > v1(line 324)
BB4
5   v7 = invokevirtual < Application, Ljava/util/LinkedHashMap, values()Ljava/util/Collection; > v5 @11 exception:v6(line 324)
BB5
6   v9 = invokeinterface < Application, Ljava/util/Collection, iterator()Ljava/util/Iterator; > v7 @14 exception:v8(line 324)
BB6
8   goto                                     (line 324)
BB7
10   v14 = invokeinterface < Application, Ljava/util/Iterator, next()Ljava/lang/Object; > v9 @24 exception:v13(line 325)
BB8
11   v15 = checkcast <Application,Lcom/squareup/okhttp/internal/DiskLruCache$Entry>v14(line 325)
BB9
14   v17 = invokestatic < Application, Lcom/squareup/okhttp/internal/DiskLruCache$Entry, access$1(Lcom/squareup/okhttp/internal/DiskLruCache$Entry;)Lcom/squareup/okhttp/internal/DiskLruCache$Editor; > v15 @34 exception:v16(line 326)
BB10
16   conditional branch(ne) v17,v18:#null    (line 326)
BB11
19   goto                                    (line 327)
BB12
22   v20 = getfield < Application, Lcom/squareup/okhttp/internal/DiskLruCache, size, <Primordial,J> > v1(line 328)
BB13
24   v22 = invokestatic < Application, Lcom/squareup/okhttp/internal/DiskLruCache$Entry, access$7(Lcom/squareup/okhttp/internal/DiskLruCache$Entry;)[J > v15 @51 exception:v21(line 328)
BB14
26   v23 = arrayload v22[v27]                (line 328)
BB15
27   v24 = binaryop(add) v20 , v23           (line 328)
28   putfield v1 = v24 < Application, Lcom/squareup/okhttp/internal/DiskLruCache, size, <Primordial,J> >(line 328)
BB16
31   v26 = binaryop(add) v27 , v25:#1        (line 327)
BB17
           v27 = phi  v12:#0,v26
35   v19 = getfield < Application, Lcom/squareup/okhttp/internal/DiskLruCache, valueCount, <Primordial,I> > v1(line 327)
BB18
36   conditional branch(lt) v27,v19          (line 327)
BB19
37   goto                                    (line 327)
BB20
40   invokestatic < Application, Lcom/squareup/okhttp/internal/DiskLruCache$Entry, access$5(Lcom/squareup/okhttp/internal/DiskLruCache$Entry;Lcom/squareup/okhttp/internal/DiskLruCache$Editor;)V > v15,v18:#null @76 exception:v28(line 331)
BB21
43   goto                                    (line 332)
BB22
46   v31 = invokevirtual < Application, Lcom/squareup/okhttp/internal/DiskLruCache$Entry, getCleanFile(I)Ljava/io/File; > v15,v37 @86 exception:v30(line 333)
BB23
47   invokestatic < Application, Lcom/squareup/okhttp/internal/DiskLruCache, deleteIfExists(Ljava/io/File;)V > v31 @89 exception:v32(line 333)
BB24
50   v34 = invokevirtual < Application, Lcom/squareup/okhttp/internal/DiskLruCache$Entry, getDirtyFile(I)Ljava/io/File; > v15,v37 @94 exception:v33(line 334)
BB25
51   invokestatic < Application, Lcom/squareup/okhttp/internal/DiskLruCache, deleteIfExists(Ljava/io/File;)V > v34 @97 exception:v35(line 334)
BB26
54   v36 = binaryop(add) v37 , v25:#1        (line 332)
BB27
           v37 = phi  v12:#0,v36
58   v29 = getfield < Application, Lcom/squareup/okhttp/internal/DiskLruCache, valueCount, <Primordial,I> > v1(line 332)
BB28
59   conditional branch(lt) v37,v29          (line 332)
BB29
61   invokeinterface < Application, Ljava/util/Iterator, remove()V > v9 @112 exception:v38(line 336)
BB30
63   v11 = invokeinterface < Application, Ljava/util/Iterator, hasNext()Z > v9 @118 exception:v10(line 324)
BB31
65   conditional branch(ne) v11,v12:#0       (line 324)
BB32
66   return                                  (line 339)
BB33

**CGNode:** Node: < Application, Lcom/squareup/okhttp/internal/Util, <clinit>()V > Context: Everywhere
**IR:** < Application, Lcom/squareup/okhttp/internal/Util, <clinit>()V >
CFG:
BB0[-1..-2]
    -> BB1
BB1[0..1]
    -> BB2
    -> BB9
BB2[2..4]
    -> BB3
    -> BB9
BB3[5..7]
    -> BB4
    -> BB9
BB4[8..10]
    -> BB5
    -> BB9
BB5[11..13]
    -> BB6
    -> BB9
BB6[14..15]
    -> BB7
    -> BB9
BB7[16..17]
    -> BB8
    -> BB9
BB8[18..19]
    -> BB9
BB9[-1..-2]
Instructions:
BB0
BB1
1   v3 = new <Primordial,[B>@1v2:#0          (line 36)
BB2
2   putstatic v3 < Application, Lcom/squareup/okhttp/internal/Util, EMPTY_BYTE_ARRAY, <Primordial,[B> >(line 36)
4   v4 = new <Application,[Ljava/lang/String>@7v2:#0 (line 37)
BB3
5   putstatic v4 < Application, Lcom/squareup/okhttp/internal/Util, EMPTY_STRING_ARRAY, <Application,[Ljava/lang/String> >(line 37)
7   v7 = invokestatic < Application, Ljava/nio/charset/Charset, forName(Ljava/lang/String;)Ljava/nio/charset/Charset; > v5:#ISO-8859-1 @15 exception:v6(line 40)
BB4
8   putstatic v7 < Application, Lcom/squareup/okhttp/internal/Util, ISO_8859_1, <Application,Ljava/nio/charset/Charset> >(line 40)
10   v10 = invokestatic < Application, Ljava/nio/charset/Charset, forName(Ljava/lang/String;)Ljava/nio/charset/Charset; > v8:#US-ASCII @23 exception:v9(line 43)
BB5
11   putstatic v10 < Application, Lcom/squareup/okhttp/internal/Util, US_ASCII, <Application,Ljava/nio/charset/Charset> >(line 43)
13   v13 = invokestatic < Application, Ljava/nio/charset/Charset, forName(Ljava/lang/String;)Ljava/nio/charset/Charset; > v11:#UTF-8 @31 exception:v12(line 46)
BB6
14   putstatic v13 < Application, Lcom/squareup/okhttp/internal/Util, UTF_8, <Application,Ljava/nio/charset/Charset> >(line 46)
15   v14 = new <Application,Ljava/util/concurrent/atomic/AtomicReference>@37(line 47)
BB7
17   invokespecial < Application, Ljava/util/concurrent/atomic/AtomicReference, <init>()V > v14 @41 exception:v15(line 47)
BB8
18   putstatic v14 < Application, Lcom/squareup/okhttp/internal/Util, skipBuffer, <Application,Ljava/util/concurrent/atomic/AtomicReference> >(line 47)
19   return                                  (line 35)
BB9

**CGNode:** Node: < Application, Lcom/squareup/okhttp/internal/Platform, get()Lcom/squareup/okhttp/internal/Platform; > Context: JavaTypeContext<point: <Primordial,Ljava/io/File>>
**IR:** < Application, Lcom/squareup/okhttp/internal/Platform, get()Lcom/squareup/okhttp/internal/Platform; >
CFG:
BB0[-1..-2]
    -> BB1
BB1[0..1]
    -> BB2
BB2[-1..-2]
Instructions:
BB0
BB1
0   v2 = getstatic < Application, Lcom/squareup/okhttp/internal/Platform, PLATFORM, <Application,Lcom/squareup/okhttp/internal/Platform> >(line 55)
1   return v2                                (line 55)
BB2

**CGNode:** Node: < Application, Lcom/squareup/okhttp/internal/Platform, <clinit>()V > Context: Everywhere
**IR:** < Application, Lcom/squareup/okhttp/internal/Platform, <clinit>()V >
CFG:
BB0[-1..-2]
    -> BB1
BB1[0..0]
    -> BB2
    -> BB3
BB2[1..2]
    -> BB3
BB3[-1..-2]
Instructions:
BB0
BB1
0   v3 = invokestatic < Application, Lcom/squareup/okhttp/internal/Platform, findPlatform()Lcom/squareup/okhttp/internal/Platform; > @0 exception:v2(line 50)
BB2
1   putstatic v3 < Application, Lcom/squareup/okhttp/internal/Platform, PLATFORM, <Application,Lcom/squareup/okhttp/internal/Platform> >(line 50)
2   return                                   (line 49)
BB3

**CGNode:** Node: < Application, Lcom/squareup/okhttp/internal/DiskLruCache, delete()V > Context: JavaTypeContext<point: <Application,Lcom/squareup/okhttp/internal/DiskLruCache>>
**IR:** < Application, Lcom/squareup/okhttp/internal/DiskLruCache, delete()V >
CFG:
BB0[-1..-2]
    -> BB1
BB1[0..1]
    -> BB2
    -> BB5
BB2[2..3]
    -> BB3
    -> BB5
BB3[4..4]
    -> BB4
    -> BB5
BB4[5..5]
    -> BB5
BB5[-1..-2]
Instructions:
BB0
BB1
1   invokevirtual < Application, Lcom/squareup/okhttp/internal/DiskLruCache, close()V > v1 @1 exception:v3(line 662)
BB2
3   v4 = getfield < Application, Lcom/squareup/okhttp/internal/DiskLruCache, directory, <Application,Ljava/io/File> > v1(line 663)
BB3
4   invokestatic < Application, Lcom/squareup/okhttp/internal/Util, deleteContents(Ljava/io/File;)V > v4 @8 exception:v5(line 663)
BB4
5   return                                   (line 664)
BB5

**CGNode:** Node: < Application, Lcom/squareup/okhttp/internal/DiskLruCache, rebuildJournal()V > Context: JavaTypeContext<point: <Application,Lcom/squareup/okhttp/internal/DiskLruCache>>
**IR:** < Application, Lcom/squareup/okhttp/internal/DiskLruCache, rebuildJournal()V >
CFG:
BB0[-1..-2]
    -> BB1
BB1[0..1]
    -> BB2
    -> BB76
BB2[2..3]
    -> BB5
    -> BB3
BB3[4..5]
    -> BB4
    -> BB76
BB4[6..6]
    -> BB5
    -> BB76
BB5[7..7]
    -> BB6
    -> BB76
BB6[8..9]
    -> BB7
    -> BB76
BB7[10..11]
    -> BB8
    -> BB76
BB8[12..14]
    -> BB9
    -> BB76
BB9[15..15]
    -> BB10
    -> BB76
BB10[16..17]
    -> BB11
    -> BB76
BB11[18..18]
    -> BB12
    -> BB76
BB12[19..22]
    -> BB13
    -> BB53
BB13[23..25]
    -> BB14
    -> BB53
BB14[26..28]
    -> BB15
    -> BB53
BB15[29..31]
    -> BB16
    -> BB53
BB16[32..34]
    -> BB17
    -> BB53
BB17[35..35]
    -> BB18
    -> BB53
BB18[36..36]
    -> BB19
    -> BB53
BB19[37..39]
    -> BB20
    -> BB53
BB20[40..42]
    -> BB21
    -> BB53
BB21[43..43]
    -> BB22
    -> BB53
BB22[44..44]
    -> BB23
    -> BB53
BB23[45..47]
    -> BB24
    -> BB53
BB24[48..50]
    -> BB25
    -> BB53
BB25[51..52]
    -> BB26
    -> BB53
BB26[53..53]
    -> BB27
    -> BB53
BB27[54..54]
    -> BB28
    -> BB53
BB28[55..56]
    -> BB50
BB29[57..58]
    -> BB30
    -> BB53
BB30[59..59]
    -> BB31
    -> BB53
BB31[60..62]
    -> BB32
    -> BB53
BB32[63..64]
    -> BB41
    -> BB33
BB33[65..66]
    -> BB34
    -> BB53
BB34[67..69]
    -> BB35
    -> BB53
BB35[70..71]
    -> BB36
    -> BB53
BB36[72..72]
    -> BB37
    -> BB53
BB37[73..74]
    -> BB38
    -> BB53
BB38[75..75]
    -> BB39
    -> BB53
BB39[76..76]
    -> BB40
    -> BB53
BB40[77..77]
    -> BB50
BB41[78..79]
    -> BB42
    -> BB53
BB42[80..82]
    -> BB43
    -> BB53
BB43[83..84]
    -> BB44
    -> BB53
BB44[85..85]
    -> BB45
    -> BB53
BB45[86..87]
    -> BB46
    -> BB53
BB46[88..88]
    -> BB47
    -> BB53
BB47[89..90]
    -> BB48
    -> BB53
BB48[91..91]
    -> BB49
    -> BB53
BB49[92..92]
    -> BB50
    -> BB53
BB50[93..94]
    -> BB51
    -> BB53
BB51[95..96]
    -> BB29
    -> BB52
BB52[97..97]
    -> BB55
BB53[98..100]
    -> BB54
    -> BB76
BB54[101..102]
    -> BB76
BB55[103..104]
    -> BB56
    -> BB76
BB56[105..106]
    -> BB57
    -> BB76
BB57[107..107]
    -> BB58
    -> BB76
BB58[108..109]
    -> BB62
    -> BB59
BB59[110..111]
    -> BB60
    -> BB76
BB60[112..113]
    -> BB61
    -> BB76
BB61[114..115]
    -> BB62
    -> BB76
BB62[116..117]
    -> BB63
    -> BB76
BB63[118..119]
    -> BB64
    -> BB76
BB64[120..121]
    -> BB65
    -> BB76
BB65[122..123]
    -> BB66
    -> BB76
BB66[124..124]
    -> BB67
    -> BB76
BB67[125..127]
    -> BB68
    -> BB76
BB68[128..129]
    -> BB69
    -> BB76
BB69[130..131]
    -> BB70
    -> BB76
BB70[132..134]
    -> BB71
    -> BB76
BB71[135..136]
    -> BB72
    -> BB76
BB72[137..138]
    -> BB73
    -> BB76
BB73[139..139]
    -> BB74
    -> BB76
BB74[140..140]
    -> BB75
    -> BB76
BB75[141..141]
    -> BB76
BB76[-1..-2]
Instructions:
BB0
BB1
1   v3 = getfield < Application, Lcom/squareup/okhttp/internal/DiskLruCache, journalWriter, <Application,Ljava/io/Writer> > v1(line 346)
BB2
3   conditional branch(eq) v3,v4:#null       (line 346)
BB3
5   v5 = getfield < Application, Lcom/squareup/okhttp/internal/DiskLruCache, journalWriter, <Application,Ljava/io/Writer> > v1(line 347)
BB4
6   invokevirtual < Application, Ljava/io/Writer, close()V > v5 @11 exception:v6(line 347)
BB5
7   v7 = new <Application,Ljava/io/BufferedWriter>@14(line 350)
BB6
9   v8 = new <Application,Ljava/io/OutputStreamWriter>@18(line 350)
BB7
11   v9 = new <Application,Ljava/io/FileOutputStream>@22(line 351)
BB8
14   v10 = getfield < Application, Lcom/squareup/okhttp/internal/DiskLruCache, journalFileTmp, <Application,Ljava/io/File> > v1(line 351)
BB9
15   invokespecial < Application, Ljava/io/FileOutputStream, <init>(Ljava/io/File;)V > v9,v10 @30 exception:v11(line 351)
BB10
16   v12 = getstatic < Application, Lcom/squareup/okhttp/internal/Util, US_ASCII, <Application,Ljava/nio/charset/Charset> >(line 351)
17   invokespecial < Application, Ljava/io/OutputStreamWriter, <init>(Ljava/io/OutputStream;Ljava/nio/charset/Charset;)V > v8,v9,v12 @36 exception:v13(line 351)
BB11
18   invokespecial < Application, Ljava/io/BufferedWriter, <init>(Ljava/io/Writer;)V > v7,v8 @39 exception:v14(line 350)
BB12
22   invokevirtual < Application, Ljava/io/Writer, write(Ljava/lang/String;)V > v7,v15:#libcore.io.DiskLruCache @46 exception:v16(line 353)
BB13
25   invokevirtual < Application, Ljava/io/Writer, write(Ljava/lang/String;)V > v7,v17:#
 @53 exception:v18(line 354)
BB14
28   invokevirtual < Application, Ljava/io/Writer, write(Ljava/lang/String;)V > v7,v19:#1 @59 exception:v20(line 355)
BB15
31   invokevirtual < Application, Ljava/io/Writer, write(Ljava/lang/String;)V > v7,v17:#
 @66 exception:v21(line 356)
BB16
34   v22 = getfield < Application, Lcom/squareup/okhttp/internal/DiskLruCache, appVersion, <Primordial,I> > v1(line 357)
BB17
35   v24 = invokestatic < Application, Ljava/lang/Integer, toString(I)Ljava/lang/String; > v22 @74 exception:v23(line 357)
BB18
36   invokevirtual < Application, Ljava/io/Writer, write(Ljava/lang/String;)V > v7,v24 @77 exception:v25(line 357)
BB19
39   invokevirtual < Application, Ljava/io/Writer, write(Ljava/lang/String;)V > v7,v17:#
 @84 exception:v26(line 358)
BB20
42   v27 = getfield < Application, Lcom/squareup/okhttp/internal/DiskLruCache, valueCount, <Primordial,I> > v1(line 359)
BB21
43   v29 = invokestatic < Application, Ljava/lang/Integer, toString(I)Ljava/lang/String; > v27 @92 exception:v28(line 359)
BB22
44   invokevirtual < Application, Ljava/io/Writer, write(Ljava/lang/String;)V > v7,v29 @95 exception:v30(line 359)
BB23
47   invokevirtual < Application, Ljava/io/Writer, write(Ljava/lang/String;)V > v7,v17:#
 @102 exception:v31(line 360)
BB24
50   invokevirtual < Application, Ljava/io/Writer, write(Ljava/lang/String;)V > v7,v17:#
 @109 exception:v32(line 361)
BB25
52   v33 = getfield < Application, Lcom/squareup/okhttp/internal/DiskLruCache, lruEntries, <Application,Ljava/util/LinkedHashMap> > v1(line 363)
BB26
53   v35 = invokevirtual < Application, Ljava/util/LinkedHashMap, values()Ljava/util/Collection; > v33 @116 exception:v34(line 363)
BB27
54   v37 = invokeinterface < Application, Ljava/util/Collection, iterator()Ljava/util/Iterator; > v35 @119 exception:v36(line 363)
BB28
56   goto                                    (line 363)
BB29
58   v42 = invokeinterface < Application, Ljava/util/Iterator, next()Ljava/lang/Object; > v37 @129 exception:v41(line 363)
BB30
59   v43 = checkcast <Application,Lcom/squareup/okhttp/internal/DiskLruCache$Entry>v42(line 363)
BB31
62   v45 = invokestatic < Application, Lcom/squareup/okhttp/internal/DiskLruCache$Entry, access$1(Lcom/squareup/okhttp/internal/DiskLruCache$Entry;)Lcom/squareup/okhttp/internal/DiskLruCache$Editor; > v43 @139 exception:v44(line 364)
BB32
64   conditional branch(eq) v45,v4:#null     (line 364)
BB33
66   v46 = new <Application,Ljava/lang/StringBuilder>@146(line 365)
BB34
69   invokespecial < Application, Ljava/lang/StringBuilder, <init>(Ljava/lang/String;)V > v46,v47:#DIRTY  @153 exception:v48(line 365)
BB35
71   v50 = invokestatic < Application, Lcom/squareup/okhttp/internal/DiskLruCache$Entry, access$2(Lcom/squareup/okhttp/internal/DiskLruCache$Entry;)Ljava/lang/String; > v43 @157 exception:v49(line 365)
BB36
72   v52 = invokevirtual < Application, Ljava/lang/StringBuilder, append(Ljava/lang/String;)Ljava/lang/StringBuilder; > v46,v50 @160 exception:v51(line 365)
BB37
74   v55 = invokevirtual < Application, Ljava/lang/StringBuilder, append(C)Ljava/lang/StringBuilder; > v52,v53:#10 @165 exception:v54(line 365)
BB38
75   v57 = invokevirtual < Application, Ljava/lang/StringBuilder, toString()Ljava/lang/String; > v55 @168 exception:v56(line 365)
BB39
76   invokevirtual < Application, Ljava/io/Writer, write(Ljava/lang/String;)V > v7,v57 @171 exception:v58(line 365)
BB40
77   goto                                    (line 365)
BB41
79   v59 = new <Application,Ljava/lang/StringBuilder>@178(line 367)
BB42
82   invokespecial < Application, Ljava/lang/StringBuilder, <init>(Ljava/lang/String;)V > v59,v60:#CLEAN  @185 exception:v61(line 367)
BB43
84   v63 = invokestatic < Application, Lcom/squareup/okhttp/internal/DiskLruCache$Entry, access$2(Lcom/squareup/okhttp/internal/DiskLruCache$Entry;)Ljava/lang/String; > v43 @189 exception:v62(line 367)
BB44
85   v65 = invokevirtual < Application, Ljava/lang/StringBuilder, append(Ljava/lang/String;)Ljava/lang/StringBuilder; > v59,v63 @192 exception:v64(line 367)
BB45
87   v67 = invokevirtual < Application, Lcom/squareup/okhttp/internal/DiskLruCache$Entry, getLengths()Ljava/lang/String; > v43 @196 exception:v66(line 367)
BB46
88   v69 = invokevirtual < Application, Ljava/lang/StringBuilder, append(Ljava/lang/String;)Ljava/lang/StringBuilder; > v65,v67 @199 exception:v68(line 367)
BB47
90   v71 = invokevirtual < Application, Ljava/lang/StringBuilder, append(C)Ljava/lang/StringBuilder; > v69,v53:#10 @204 exception:v70(line 367)
BB48
91   v73 = invokevirtual < Application, Ljava/lang/StringBuilder, toString()Ljava/lang/String; > v71 @207 exception:v72(line 367)
BB49
92   invokevirtual < Application, Ljava/io/Writer, write(Ljava/lang/String;)V > v7,v73 @210 exception:v74(line 367)
BB50
94   v39 = invokeinterface < Application, Ljava/util/Iterator, hasNext()Z > v37 @214 exception:v38(line 363)
BB51
96   conditional branch(ne) v39,v40:#0       (line 363)
BB52
97   goto                                    (line 363)
BB53<Handler>
           v97 = getCaughtException 
100   invokevirtual < Application, Ljava/io/Writer, close()V > v7 @228 exception:v98(line 371)
BB54
102   throw v97                              (line 372)
BB55
104   invokevirtual < Application, Ljava/io/Writer, close()V > v7 @235 exception:v75(line 371)
BB56
106   v76 = getfield < Application, Lcom/squareup/okhttp/internal/DiskLruCache, journalFile, <Application,Ljava/io/File> > v1(line 374)
BB57
107   v78 = invokevirtual < Application, Ljava/io/File, exists()Z > v76 @242 exception:v77(line 374)
BB58
109   conditional branch(eq) v78,v40:#0      (line 374)
BB59
111   v79 = getfield < Application, Lcom/squareup/okhttp/internal/DiskLruCache, journalFile, <Application,Ljava/io/File> > v1(line 375)
BB60
113   v80 = getfield < Application, Lcom/squareup/okhttp/internal/DiskLruCache, journalFileBkp, <Application,Ljava/io/File> > v1(line 375)
BB61
115   invokestatic < Application, Lcom/squareup/okhttp/internal/DiskLruCache, renameTo(Ljava/io/File;Ljava/io/File;Z)V > v79,v80,v81:#1 @257 exception:v82(line 375)
BB62
117   v83 = getfield < Application, Lcom/squareup/okhttp/internal/DiskLruCache, journalFileTmp, <Application,Ljava/io/File> > v1(line 377)
BB63
119   v84 = getfield < Application, Lcom/squareup/okhttp/internal/DiskLruCache, journalFile, <Application,Ljava/io/File> > v1(line 377)
BB64
121   invokestatic < Application, Lcom/squareup/okhttp/internal/DiskLruCache, renameTo(Ljava/io/File;Ljava/io/File;Z)V > v83,v84,v40:#0 @269 exception:v85(line 377)
BB65
123   v86 = getfield < Application, Lcom/squareup/okhttp/internal/DiskLruCache, journalFileBkp, <Application,Ljava/io/File> > v1(line 378)
BB66
124   v88 = invokevirtual < Application, Ljava/io/File, delete()Z > v86 @276 exception:v87(line 378)
BB67
127   v89 = new <Application,Ljava/io/BufferedWriter>@281(line 380)
BB68
129   v90 = new <Application,Ljava/io/OutputStreamWriter>@285(line 380)
BB69
131   v91 = new <Application,Ljava/io/FileOutputStream>@289(line 381)
BB70
134   v92 = getfield < Application, Lcom/squareup/okhttp/internal/DiskLruCache, journalFile, <Application,Ljava/io/File> > v1(line 381)
BB71
136   invokespecial < Application, Ljava/io/FileOutputStream, <init>(Ljava/io/File;Z)V > v91,v92,v81:#1 @298 exception:v93(line 381)
BB72
137   v94 = getstatic < Application, Lcom/squareup/okhttp/internal/Util, US_ASCII, <Application,Ljava/nio/charset/Charset> >(line 381)
138   invokespecial < Application, Ljava/io/OutputStreamWriter, <init>(Ljava/io/OutputStream;Ljava/nio/charset/Charset;)V > v90,v91,v94 @304 exception:v95(line 381)
BB73
139   invokespecial < Application, Ljava/io/BufferedWriter, <init>(Ljava/io/Writer;)V > v89,v90 @307 exception:v96(line 381)
BB74
140   putfield v1 = v89 < Application, Lcom/squareup/okhttp/internal/DiskLruCache, journalWriter, <Application,Ljava/io/Writer> >(line 380)
BB75
141   return                                 (line 382)
BB76

**CGNode:** Node: < Application, Lcom/squareup/okhttp/internal/DiskLruCache$2, <init>()V > Context: JavaTypeContext<point: <Application,Lcom/squareup/okhttp/internal/DiskLruCache$2>>
**IR:** < Application, Lcom/squareup/okhttp/internal/DiskLruCache$2, <init>()V >
CFG:
BB0[-1..-2]
    -> BB1
BB1[0..1]
    -> BB2
    -> BB3
BB2[2..2]
    -> BB3
BB3[-1..-2]
Instructions:
BB0
BB1
1   invokespecial < Application, Ljava/io/OutputStream, <init>()V > v1 @1 exception:v3(line 731)
BB2
2   return                                   (line 1)
BB3

**CGNode:** Node: < Application, Lcom/squareup/okhttp/internal/spdy/SpdyStream, <clinit>()V > Context: Everywhere
**IR:** < Application, Lcom/squareup/okhttp/internal/spdy/SpdyStream, <clinit>()V >
CFG:
BB0[-1..-2]
    -> BB1
BB1[0..0]
    -> BB2
    -> BB19
BB2[1..1]
    -> BB3
    -> BB19
BB3[2..3]
    -> BB5
    -> BB4
BB4[4..5]
    -> BB6
BB5[6..6]
    -> BB6
BB6[7..9]
    -> BB7
    -> BB19
BB7[10..13]
    -> BB8
    -> BB19
BB8[14..17]
    -> BB9
    -> BB19
BB9[18..21]
    -> BB10
    -> BB19
BB10[22..25]
    -> BB11
    -> BB19
BB11[26..29]
    -> BB12
    -> BB19
BB12[30..33]
    -> BB13
    -> BB19
BB13[34..37]
    -> BB14
    -> BB19
BB14[38..41]
    -> BB15
    -> BB19
BB15[42..45]
    -> BB16
    -> BB19
BB16[46..49]
    -> BB17
    -> BB19
BB17[50..53]
    -> BB18
    -> BB19
BB18[54..55]
    -> BB19
BB19[-1..-2]
Instructions:
BB0
BB1
0   v2 = load_metadata: <Primordial,Lcom/squareup/okhttp/internal/spdy/SpdyStream>, <Primordial,Ljava/lang/Class>(line 33)
BB2
1   v4 = invokevirtual < Application, Ljava/lang/Class, desiredAssertionStatus()Z > v2 @2 exception:v3(line 33)
BB3
3   conditional branch(ne) v4,v5:#0          (line 33)
BB4
5   goto                                     (line 33)
BB5
BB6
           v7 = phi  v6:#1,v5:#0
7   putstatic v7 < Application, Lcom/squareup/okhttp/internal/spdy/SpdyStream, $assertionsDisabled, <Primordial,Z> >(line 33)
9   v9 = new <Application,[Ljava/lang/String>@18v8:#12 (line 40)
BB7
13   arraystore v9[v6:#1] = v10:#PROTOCOL_ERROR(line 42)
BB8
17   arraystore v9[v11:#2] = v12:#INVALID_STREAM(line 43)
BB9
21   arraystore v9[v13:#3] = v14:#REFUSED_STREAM(line 44)
BB10
25   arraystore v9[v15:#4] = v16:#UNSUPPORTED_VERSION(line 45)
BB11
29   arraystore v9[v17:#5] = v18:#CANCEL     (line 46)
BB12
33   arraystore v9[v19:#6] = v20:#INTERNAL_ERROR(line 47)
BB13
37   arraystore v9[v21:#7] = v22:#FLOW_CONTROL_ERROR(line 48)
BB14
41   arraystore v9[v23:#8] = v24:#STREAM_IN_USE(line 49)
BB15
45   arraystore v9[v25:#9] = v26:#STREAM_ALREADY_CLOSED(line 50)
BB16
49   arraystore v9[v27:#10] = v28:#INVALID_CREDENTIALS(line 51)
BB17
53   arraystore v9[v29:#11] = v30:#FRAME_TOO_LARGE(line 52)
BB18
54   putstatic v9 < Application, Lcom/squareup/okhttp/internal/spdy/SpdyStream, STATUS_CODE_NAMES, <Application,[Ljava/lang/String> >(line 40)
55   return                                  (line 40)
BB19

**CGNode:** Node: < Application, Lcom/squareup/okhttp/internal/spdy/SpdyStream, <init>(ILcom/squareup/okhttp/internal/spdy/SpdyConnection;IIILjava/util/List;Lcom/squareup/okhttp/internal/spdy/Settings;)V > Context: JavaTypeContext<point: <Application,Lcom/squareup/okhttp/internal/spdy/SpdyStream>>
**IR:** < Application, Lcom/squareup/okhttp/internal/spdy/SpdyStream, <init>(ILcom/squareup/okhttp/internal/spdy/SpdyConnection;IIILjava/util/List;Lcom/squareup/okhttp/internal/spdy/Settings;)V >
CFG:
BB0[-1..-2]
    -> BB1
BB1[0..1]
    -> BB2
    -> BB48
BB2[2..4]
    -> BB3
    -> BB48
BB3[5..6]
    -> BB4
    -> BB48
BB4[7..10]
    -> BB5
    -> BB48
BB5[11..11]
    -> BB6
    -> BB48
BB6[12..13]
    -> BB7
    -> BB48
BB7[14..17]
    -> BB8
    -> BB48
BB8[18..18]
    -> BB9
    -> BB48
BB9[19..21]
    -> BB10
    -> BB48
BB10[22..24]
    -> BB14
    -> BB11
BB11[25..25]
    -> BB12
    -> BB48
BB12[26..28]
    -> BB13
    -> BB48
BB13[29..29]
    -> BB48
BB14[30..32]
    -> BB18
    -> BB15
BB15[33..33]
    -> BB16
    -> BB48
BB16[34..36]
    -> BB17
    -> BB48
BB17[37..37]
    -> BB48
BB18[38..40]
    -> BB19
    -> BB48
BB19[41..43]
    -> BB20
    -> BB48
BB20[44..46]
    -> BB21
    -> BB48
BB21[47..49]
    -> BB22
    -> BB48
BB22[50..52]
    -> BB23
    -> BB48
BB23[53..54]
    -> BB24
    -> BB48
BB24[55..56]
    -> BB36
    -> BB25
BB25[57..58]
    -> BB26
    -> BB48
BB26[59..63]
    -> BB28
    -> BB27
BB27[64..65]
    -> BB29
BB28[66..66]
    -> BB29
BB29[67..67]
    -> BB30
    -> BB48
BB30[68..69]
    -> BB31
    -> BB48
BB31[70..74]
    -> BB33
    -> BB32
BB32[75..76]
    -> BB34
BB33[77..77]
    -> BB34
BB34[78..78]
    -> BB35
    -> BB48
BB35[79..79]
    -> BB46
BB36[80..81]
    -> BB37
    -> BB48
BB37[82..86]
    -> BB39
    -> BB38
BB38[87..88]
    -> BB40
BB39[89..89]
    -> BB40
BB40[90..90]
    -> BB41
    -> BB48
BB41[91..92]
    -> BB42
    -> BB48
BB42[93..97]
    -> BB44
    -> BB43
BB43[98..99]
    -> BB45
BB44[100..100]
    -> BB45
BB45[101..101]
    -> BB46
    -> BB48
BB46[102..104]
    -> BB47
    -> BB48
BB47[105..105]
    -> BB48
BB48[-1..-2]
Instructions:
BB0
BB1
1   invokespecial < Application, Ljava/lang/Object, <init>()V > v1 @1 exception:v10(line 98)
BB2
4   putfield v1 = v11:#0 < Application, Lcom/squareup/okhttp/internal/spdy/SpdyStream, readTimeoutMillis, <Primordial,J> >(line 79)
BB3
6   v12 = new <Application,Lcom/squareup/okhttp/internal/spdy/SpdyStream$SpdyDataInputStream>@10(line 88)
BB4
10   invokespecial < Application, Lcom/squareup/okhttp/internal/spdy/SpdyStream$SpdyDataInputStream, <init>(Lcom/squareup/okhttp/internal/spdy/SpdyStream;Lcom/squareup/okhttp/internal/spdy/SpdyStream$SpdyDataInputStream;)V > v12,v1,v13:#null @16 exception:v14(line 88)
BB5
11   putfield v1 = v12 < Application, Lcom/squareup/okhttp/internal/spdy/SpdyStream, in, <Application,Lcom/squareup/okhttp/internal/spdy/SpdyStream$SpdyDataInputStream> >(line 88)
BB6
13   v15 = new <Application,Lcom/squareup/okhttp/internal/spdy/SpdyStream$SpdyDataOutputStream>@23(line 89)
BB7
17   invokespecial < Application, Lcom/squareup/okhttp/internal/spdy/SpdyStream$SpdyDataOutputStream, <init>(Lcom/squareup/okhttp/internal/spdy/SpdyStream;Lcom/squareup/okhttp/internal/spdy/SpdyStream$SpdyDataOutputStream;)V > v15,v1,v13:#null @29 exception:v16(line 89)
BB8
18   putfield v1 = v15 < Application, Lcom/squareup/okhttp/internal/spdy/SpdyStream, out, <Application,Lcom/squareup/okhttp/internal/spdy/SpdyStream$SpdyDataOutputStream> >(line 89)
BB9
21   putfield v1 = v17:#-1 < Application, Lcom/squareup/okhttp/internal/spdy/SpdyStream, rstStatusCode, <Primordial,I> >(line 96)
BB10
24   conditional branch(ne) v3,v13:#null     (line 100)
BB11
25   v43 = new <Application,Ljava/lang/NullPointerException>@44(line 100)
BB12
28   invokespecial < Application, Ljava/lang/NullPointerException, <init>(Ljava/lang/String;)V > v43,v44:#connection == null @50 exception:v45(line 100)
BB13
29   throw v43                               (line 100)
BB14
32   conditional branch(ne) v7,v13:#null     (line 101)
BB15
33   v40 = new <Application,Ljava/lang/NullPointerException>@59(line 101)
BB16
36   invokespecial < Application, Ljava/lang/NullPointerException, <init>(Ljava/lang/String;)V > v40,v41:#requestHeaders == null @65 exception:v42(line 101)
BB17
37   throw v40                               (line 101)
BB18
40   putfield v1 = v2 < Application, Lcom/squareup/okhttp/internal/spdy/SpdyStream, id, <Primordial,I> >(line 102)
BB19
43   putfield v1 = v3 < Application, Lcom/squareup/okhttp/internal/spdy/SpdyStream, connection, <Application,Lcom/squareup/okhttp/internal/spdy/SpdyConnection> >(line 103)
BB20
46   putfield v1 = v5 < Application, Lcom/squareup/okhttp/internal/spdy/SpdyStream, priority, <Primordial,I> >(line 104)
BB21
49   putfield v1 = v6 < Application, Lcom/squareup/okhttp/internal/spdy/SpdyStream, slot, <Primordial,I> >(line 105)
BB22
52   putfield v1 = v7 < Application, Lcom/squareup/okhttp/internal/spdy/SpdyStream, requestHeaders, <Application,Ljava/util/List> >(line 106)
BB23
54   v19 = invokevirtual < Application, Lcom/squareup/okhttp/internal/spdy/SpdyStream, isLocallyInitiated()Z > v1 @98 exception:v18(line 108)
BB24
56   conditional branch(eq) v19,v20:#0       (line 108)
BB25
58   v31 = getfield < Application, Lcom/squareup/okhttp/internal/spdy/SpdyStream, in, <Application,Lcom/squareup/okhttp/internal/spdy/SpdyStream$SpdyDataInputStream> > v1(line 110)
BB26
61   v32 = binaryop(and) v4 , v27:#2         (line 110)
63   conditional branch(eq) v32,v20:#0       (line 110)
BB27
65   goto                                    (line 110)
BB28
BB29
           v33 = phi  v22:#1,v20:#0
67   invokestatic < Application, Lcom/squareup/okhttp/internal/spdy/SpdyStream$SpdyDataInputStream, access$1(Lcom/squareup/okhttp/internal/spdy/SpdyStream$SpdyDataInputStream;Z)V > v31,v33 @119 exception:v34(line 110)
BB30
69   v35 = getfield < Application, Lcom/squareup/okhttp/internal/spdy/SpdyStream, out, <Application,Lcom/squareup/okhttp/internal/spdy/SpdyStream$SpdyDataOutputStream> > v1(line 111)
BB31
72   v36 = binaryop(and) v4 , v22:#1         (line 111)
74   conditional branch(eq) v36,v20:#0       (line 111)
BB32
76   goto                                    (line 111)
BB33
BB34
           v37 = phi  v22:#1,v20:#0
78   invokestatic < Application, Lcom/squareup/okhttp/internal/spdy/SpdyStream$SpdyDataOutputStream, access$1(Lcom/squareup/okhttp/internal/spdy/SpdyStream$SpdyDataOutputStream;Z)V > v35,v37 @137 exception:v38(line 111)
BB35
79   goto                                    (line 111)
BB36
81   v21 = getfield < Application, Lcom/squareup/okhttp/internal/spdy/SpdyStream, in, <Application,Lcom/squareup/okhttp/internal/spdy/SpdyStream$SpdyDataInputStream> > v1(line 114)
BB37
84   v23 = binaryop(and) v4 , v22:#1         (line 114)
86   conditional branch(eq) v23,v20:#0       (line 114)
BB38
88   goto                                    (line 114)
BB39
BB40
           v24 = phi  v22:#1,v20:#0
90   invokestatic < Application, Lcom/squareup/okhttp/internal/spdy/SpdyStream$SpdyDataInputStream, access$1(Lcom/squareup/okhttp/internal/spdy/SpdyStream$SpdyDataInputStream;Z)V > v21,v24 @158 exception:v25(line 114)
BB41
92   v26 = getfield < Application, Lcom/squareup/okhttp/internal/spdy/SpdyStream, out, <Application,Lcom/squareup/okhttp/internal/spdy/SpdyStream$SpdyDataOutputStream> > v1(line 115)
BB42
95   v28 = binaryop(and) v4 , v27:#2         (line 115)
97   conditional branch(eq) v28,v20:#0       (line 115)
BB43
99   goto                                    (line 115)
BB44
BB45
           v29 = phi  v22:#1,v20:#0
101   invokestatic < Application, Lcom/squareup/okhttp/internal/spdy/SpdyStream$SpdyDataOutputStream, access$1(Lcom/squareup/okhttp/internal/spdy/SpdyStream$SpdyDataOutputStream;Z)V > v26,v29 @176 exception:v30(line 115)
BB46
104   invokespecial < Application, Lcom/squareup/okhttp/internal/spdy/SpdyStream, setSettings(Lcom/squareup/okhttp/internal/spdy/Settings;)V > v1,v8 @182 exception:v39(line 118)
BB47
105   return                                 (line 119)
BB48

**CGNode:** Node: < Application, Lcom/squareup/okhttp/internal/spdy/SpdyStream, isOpen()Z > Context: JavaTypeContext<point: <Application,Lcom/squareup/okhttp/internal/spdy/SpdyStream>>
**IR:** < Application, Lcom/squareup/okhttp/internal/spdy/SpdyStream, isOpen()Z >
CFG:
BB0[-1..-2]
    -> BB1
BB1[0..1]
    -> BB2
    -> BB20
BB2[2..3]
    -> BB4
    -> BB3
BB3[4..5]
    -> BB20
BB4[6..7]
    -> BB5
    -> BB20
BB5[8..8]
    -> BB6
    -> BB20
BB6[9..10]
    -> BB10
    -> BB7
BB7[11..12]
    -> BB8
    -> BB20
BB8[13..13]
    -> BB9
    -> BB20
BB9[14..15]
    -> BB19
    -> BB10
BB10[16..17]
    -> BB11
    -> BB20
BB11[18..18]
    -> BB12
    -> BB20
BB12[19..20]
    -> BB16
    -> BB13
BB13[21..22]
    -> BB14
    -> BB20
BB14[23..23]
    -> BB15
    -> BB20
BB15[24..25]
    -> BB19
    -> BB16
BB16[26..27]
    -> BB17
    -> BB20
BB17[28..29]
    -> BB19
    -> BB18
BB18[30..31]
    -> BB20
BB19[32..33]
    -> BB20
BB20[-1..-2]
Instructions:
BB0
BB1
1   v3 = getfield < Application, Lcom/squareup/okhttp/internal/spdy/SpdyStream, rstStatusCode, <Primordial,I> > v1(line 132)
BB2
3   conditional branch(eq) v3,v4:#-1         (line 132)
BB3
5   return v8:#0                             (line 133)
BB4
7   v5 = getfield < Application, Lcom/squareup/okhttp/internal/spdy/SpdyStream, in, <Application,Lcom/squareup/okhttp/internal/spdy/SpdyStream$SpdyDataInputStream> > v1(line 135)
BB5
8   v7 = invokestatic < Application, Lcom/squareup/okhttp/internal/spdy/SpdyStream$SpdyDataInputStream, access$2(Lcom/squareup/okhttp/internal/spdy/SpdyStream$SpdyDataInputStream;)Z > v5 @14 exception:v6(line 135)
BB6
10   conditional branch(ne) v7,v8:#0         (line 135)
BB7
12   v9 = getfield < Application, Lcom/squareup/okhttp/internal/spdy/SpdyStream, in, <Application,Lcom/squareup/okhttp/internal/spdy/SpdyStream$SpdyDataInputStream> > v1(line 135)
BB8
13   v11 = invokestatic < Application, Lcom/squareup/okhttp/internal/spdy/SpdyStream$SpdyDataInputStream, access$3(Lcom/squareup/okhttp/internal/spdy/SpdyStream$SpdyDataInputStream;)Z > v9 @24 exception:v10(line 135)
BB9
15   conditional branch(eq) v11,v8:#0        (line 135)
BB10
17   v12 = getfield < Application, Lcom/squareup/okhttp/internal/spdy/SpdyStream, out, <Application,Lcom/squareup/okhttp/internal/spdy/SpdyStream$SpdyDataOutputStream> > v1(line 135)
BB11
18   v14 = invokestatic < Application, Lcom/squareup/okhttp/internal/spdy/SpdyStream$SpdyDataOutputStream, access$2(Lcom/squareup/okhttp/internal/spdy/SpdyStream$SpdyDataOutputStream;)Z > v12 @34 exception:v13(line 135)
BB12
20   conditional branch(ne) v14,v8:#0        (line 135)
BB13
22   v15 = getfield < Application, Lcom/squareup/okhttp/internal/spdy/SpdyStream, out, <Application,Lcom/squareup/okhttp/internal/spdy/SpdyStream$SpdyDataOutputStream> > v1(line 135)
BB14
23   v17 = invokestatic < Application, Lcom/squareup/okhttp/internal/spdy/SpdyStream$SpdyDataOutputStream, access$3(Lcom/squareup/okhttp/internal/spdy/SpdyStream$SpdyDataOutputStream;)Z > v15 @44 exception:v16(line 135)
BB15
25   conditional branch(eq) v17,v8:#0        (line 135)
BB16
27   v18 = getfield < Application, Lcom/squareup/okhttp/internal/spdy/SpdyStream, responseHeaders, <Application,Ljava/util/List> > v1(line 135)
BB17
29   conditional branch(eq) v18,v19:#null    (line 135)
BB18
31   return v8:#0                            (line 136)
BB19
33   return v20:#1                           (line 138)
BB20

**CGNode:** Node: < Application, Lcom/squareup/okhttp/internal/spdy/SpdyConnection, setIdle(Z)V > Context: JavaTypeContext<point: <Application,Lcom/squareup/okhttp/internal/spdy/SpdyConnection>>
**IR:** < Application, Lcom/squareup/okhttp/internal/spdy/SpdyConnection, setIdle(Z)V >
CFG:
BB0[-1..-2]
    -> BB1
BB1[0..3]
    -> BB4
    -> BB2
BB2[4..4]
    -> BB3
    -> BB7
BB3[5..5]
    -> BB5
BB4[6..6]
    -> BB5
BB5[7..7]
    -> BB6
    -> BB7
BB6[8..8]
    -> BB7
BB7[-1..-2]
Instructions:
BB0
BB1
3   conditional branch(eq) v2,v4:#0          (line 146)
BB2
4   v7 = invokestatic < Application, Ljava/lang/System, nanoTime()J > @5 exception:v6(line 146)
BB3
5   goto                                     (line 146)
BB4
BB5
           v8 = phi  v7,v5:#0
7   putfield v1 = v8 < Application, Lcom/squareup/okhttp/internal/spdy/SpdyConnection, idleStartTimeNs, <Primordial,J> >(line 146)
BB6
8   return                                   (line 147)
BB7

**CGNode:** Node: < Application, Lcom/squareup/okhttp/internal/DiskLruCache, deleteIfExists(Ljava/io/File;)V > Context: JavaTypeContext<point: <Primordial,Ljava/io/File>>
**IR:** < Application, Lcom/squareup/okhttp/internal/DiskLruCache, deleteIfExists(Ljava/io/File;)V >
CFG:
BB0[-1..-2]
    -> BB1
BB1[0..1]
    -> BB2
    -> BB9
BB2[2..3]
    -> BB8
    -> BB3
BB3[4..5]
    -> BB4
    -> BB9
BB4[6..7]
    -> BB8
    -> BB5
BB5[8..8]
    -> BB6
    -> BB9
BB6[9..10]
    -> BB7
    -> BB9
BB7[11..11]
    -> BB9
BB8[12..12]
    -> BB9
BB9[-1..-2]
Instructions:
BB0
BB1
1   v4 = invokevirtual < Application, Ljava/io/File, exists()Z > v1 @1 exception:v3(line 385)
BB2
3   conditional branch(eq) v4,v5:#0          (line 385)
BB3
5   v7 = invokevirtual < Application, Ljava/io/File, delete()Z > v1 @8 exception:v6(line 385)
BB4
7   conditional branch(ne) v7,v5:#0          (line 385)
BB5
8   v8 = new <Application,Ljava/io/IOException>@14(line 386)
BB6
10   invokespecial < Application, Ljava/io/IOException, <init>()V > v8 @18 exception:v9(line 386)
BB7
11   throw v8                                (line 386)
BB8
12   return                                  (line 388)
BB9

**CGNode:** Node: < Application, Lcom/squareup/okhttp/internal/DiskLruCache$1, <init>(Lcom/squareup/okhttp/internal/DiskLruCache;)V > Context: JavaTypeContext<point: <Application,Lcom/squareup/okhttp/internal/DiskLruCache$1>>
**IR:** < Application, Lcom/squareup/okhttp/internal/DiskLruCache$1, <init>(Lcom/squareup/okhttp/internal/DiskLruCache;)V >
CFG:
BB0[-1..-2]
    -> BB1
BB1[0..2]
    -> BB2
    -> BB4
BB2[3..4]
    -> BB3
    -> BB4
BB3[5..5]
    -> BB4
BB4[-1..-2]
Instructions:
BB0
BB1
2   putfield v1 = v2 < Application, Lcom/squareup/okhttp/internal/DiskLruCache$1, this$0, <Application,Lcom/squareup/okhttp/internal/DiskLruCache> >(line 1)
BB2
4   invokespecial < Application, Ljava/lang/Object, <init>()V > v1 @6 exception:v4(line 166)
BB3
5   return                                   (line 166)
BB4

**CGNode:** Node: < Application, Lcom/squareup/okhttp/internal/StrictLineReader, <init>(Ljava/io/InputStream;Ljava/nio/charset/Charset;)V > Context: JavaTypeContext<point: <Application,Lcom/squareup/okhttp/internal/StrictLineReader>>
**IR:** < Application, Lcom/squareup/okhttp/internal/StrictLineReader, <init>(Ljava/io/InputStream;Ljava/nio/charset/Charset;)V >
CFG:
BB0[-1..-2]
    -> BB1
BB1[0..4]
    -> BB2
    -> BB3
BB2[5..5]
    -> BB3
BB3[-1..-2]
Instructions:
BB0
BB1
4   invokespecial < Application, Lcom/squareup/okhttp/internal/StrictLineReader, <init>(Ljava/io/InputStream;ILjava/nio/charset/Charset;)V > v1,v2,v5:#8192,v3 @6 exception:v6(line 72)
BB2
5   return                                   (line 73)
BB3

**CGNode:** Node: < Application, Lcom/squareup/okhttp/internal/StrictLineReader, readLine()Ljava/lang/String; > Context: JavaTypeContext<point: <Application,Lcom/squareup/okhttp/internal/StrictLineReader>>
**IR:** < Application, Lcom/squareup/okhttp/internal/StrictLineReader, readLine()Ljava/lang/String; >
CFG:
BB0[-1..-2]
    -> BB1
BB1[0..1]
    -> BB2
    -> BB70
BB2[2..4]
    -> BB3
    -> BB70
BB3[5..6]
    -> BB4
    -> BB68
BB4[7..8]
    -> BB8
    -> BB5
BB5[9..9]
    -> BB6
    -> BB68
BB6[10..12]
    -> BB7
    -> BB68
BB7[13..13]
    -> BB68
BB8[14..15]
    -> BB9
    -> BB68
BB9[16..17]
    -> BB10
    -> BB68
BB10[18..18]
    -> BB12
    -> BB11
BB11[19..20]
    -> BB12
    -> BB68
BB12[21..22]
    -> BB13
    -> BB68
BB13[23..24]
    -> BB35
BB14[25..26]
    -> BB15
    -> BB68
BB15[27..28]
    -> BB16
    -> BB68
BB16[29..30]
    -> BB34
    -> BB17
BB17[31..33]
    -> BB18
    -> BB68
BB18[34..34]
    -> BB23
    -> BB19
BB19[35..36]
    -> BB20
    -> BB68
BB20[37..40]
    -> BB21
    -> BB68
BB21[41..42]
    -> BB23
    -> BB22
BB22[43..46]
    -> BB24
BB23[47..47]
    -> BB24
BB24[48..49]
    -> BB25
    -> BB68
BB25[50..52]
    -> BB26
    -> BB68
BB26[53..54]
    -> BB27
    -> BB68
BB27[55..57]
    -> BB28
    -> BB68
BB28[58..60]
    -> BB29
    -> BB68
BB29[61..61]
    -> BB30
    -> BB68
BB30[62..62]
    -> BB31
    -> BB68
BB31[63..68]
    -> BB32
    -> BB68
BB32[69..71]
    -> BB33
    -> BB68
BB33[72..72]
    -> BB70
BB34[73..76]
    -> BB35
BB35[77..79]
    -> BB36
    -> BB68
BB36[80..80]
    -> BB14
    -> BB37
BB37[81..81]
    -> BB38
    -> BB68
BB38[82..85]
    -> BB39
    -> BB68
BB39[86..87]
    -> BB40
    -> BB68
BB40[88..91]
    -> BB41
    -> BB68
BB41[92..92]
    -> BB42
BB42[93..95]
    -> BB43
    -> BB68
BB43[96..97]
    -> BB44
    -> BB68
BB44[98..99]
    -> BB45
    -> BB68
BB45[100..101]
    -> BB46
    -> BB68
BB46[102..103]
    -> BB47
    -> BB68
BB47[104..106]
    -> BB48
    -> BB68
BB48[107..108]
    -> BB49
    -> BB68
BB49[109..110]
    -> BB50
    -> BB68
BB50[111..112]
    -> BB65
BB51[113..114]
    -> BB52
    -> BB68
BB52[115..116]
    -> BB53
    -> BB68
BB53[117..118]
    -> BB64
    -> BB54
BB54[119..121]
    -> BB55
    -> BB68
BB55[122..122]
    -> BB60
    -> BB56
BB56[123..125]
    -> BB57
    -> BB68
BB57[126..127]
    -> BB58
    -> BB68
BB58[128..130]
    -> BB59
    -> BB68
BB59[131..132]
    -> BB60
    -> BB68
BB60[133..137]
    -> BB61
    -> BB68
BB61[138..139]
    -> BB62
    -> BB68
BB62[140..141]
    -> BB63
    -> BB68
BB63[142..142]
    -> BB70
BB64[143..146]
    -> BB65
BB65[147..149]
    -> BB66
    -> BB68
BB66[150..150]
    -> BB51
    -> BB67
BB67[151..151]
    -> BB42
BB68[152..153]
    -> BB69
    -> BB68
BB69[154..154]
    -> BB70
BB70[-1..-2]
Instructions:
BB0
BB1
1   v3 = getfield < Application, Lcom/squareup/okhttp/internal/StrictLineReader, in, <Application,Ljava/io/InputStream> > v1(line 126)
BB2
4   monitorenter v3                          (line 126)
BB3
6   v4 = getfield < Application, Lcom/squareup/okhttp/internal/StrictLineReader, buf, <Primordial,[B> > v1(line 127)
BB4
8   conditional branch(ne) v4,v5:#null       (line 127)
BB5
9   v64 = new <Application,Ljava/io/IOException>@14(line 128)
BB6
12   invokespecial < Application, Ljava/io/IOException, <init>(Ljava/lang/String;)V > v64,v65:#LineReader is closed @20 exception:v66(line 128)
BB7
13   throw v64                               (line 128)
BB8
15   v6 = getfield < Application, Lcom/squareup/okhttp/internal/StrictLineReader, pos, <Primordial,I> > v1(line 134)
BB9
17   v7 = getfield < Application, Lcom/squareup/okhttp/internal/StrictLineReader, end, <Primordial,I> > v1(line 134)
BB10
18   conditional branch(lt) v6,v7            (line 134)
BB11
20   invokespecial < Application, Lcom/squareup/okhttp/internal/StrictLineReader, fillBuf()V > v1 @36 exception:v8(line 135)
BB12
22   v9 = getfield < Application, Lcom/squareup/okhttp/internal/StrictLineReader, pos, <Primordial,I> > v1(line 138)
BB13
24   goto                                    (line 138)
BB14
26   v11 = getfield < Application, Lcom/squareup/okhttp/internal/StrictLineReader, buf, <Primordial,[B> > v1(line 139)
BB15
28   v12 = arrayload v11[v16]                (line 139)
BB16
30   conditional branch(ne) v12,v13:#10      (line 139)
BB17
33   v47 = getfield < Application, Lcom/squareup/okhttp/internal/StrictLineReader, pos, <Primordial,I> > v1(line 140)
BB18
34   conditional branch(eq) v16,v47          (line 140)
BB19
36   v48 = getfield < Application, Lcom/squareup/okhttp/internal/StrictLineReader, buf, <Primordial,[B> > v1(line 140)
BB20
39   v49 = binaryop(sub) v16 , v14:#1        (line 140)
40   v50 = arrayload v48[v49]                (line 140)
BB21
42   conditional branch(ne) v50,v51:#13      (line 140)
BB22
45   v52 = binaryop(sub) v16 , v14:#1        (line 140)
46   goto                                    (line 140)
BB23
BB24
           v53 = phi  v52,v16
49   v54 = new <Application,Ljava/lang/String>@87(line 141)
BB25
52   v55 = getfield < Application, Lcom/squareup/okhttp/internal/StrictLineReader, buf, <Primordial,[B> > v1(line 141)
BB26
54   v56 = getfield < Application, Lcom/squareup/okhttp/internal/StrictLineReader, pos, <Primordial,I> > v1(line 141)
BB27
57   v57 = getfield < Application, Lcom/squareup/okhttp/internal/StrictLineReader, pos, <Primordial,I> > v1(line 141)
BB28
58   v58 = binaryop(sub) v53 , v57           (line 141)
60   v59 = getfield < Application, Lcom/squareup/okhttp/internal/StrictLineReader, charset, <Application,Ljava/nio/charset/Charset> > v1(line 141)
BB29
61   v61 = invokevirtual < Application, Ljava/nio/charset/Charset, name()Ljava/lang/String; > v59 @109 exception:v60(line 141)
BB30
62   invokespecial < Application, Ljava/lang/String, <init>([BIILjava/lang/String;)V > v54,v55,v56,v58,v61 @112 exception:v62(line 141)
BB31
67   v63 = binaryop(add) v16 , v14:#1        (line 142)
68   putfield v1 = v63 < Application, Lcom/squareup/okhttp/internal/StrictLineReader, pos, <Primordial,I> >(line 142)
BB32
71   monitorexit v3                          (line 143)
BB33
72   return v54                              (line 143)
BB34
75   v15 = binaryop(add) v16 , v14:#1        (line 138)
BB35
           v16 = phi  v9,v15
79   v10 = getfield < Application, Lcom/squareup/okhttp/internal/StrictLineReader, end, <Primordial,I> > v1(line 138)
BB36
80   conditional branch(ne) v16,v10          (line 138)
BB37
81   v17 = new <Application,Lcom/squareup/okhttp/internal/StrictLineReader$1>@140(line 148)
BB38
85   v18 = getfield < Application, Lcom/squareup/okhttp/internal/StrictLineReader, end, <Primordial,I> > v1(line 148)
BB39
87   v19 = getfield < Application, Lcom/squareup/okhttp/internal/StrictLineReader, pos, <Primordial,I> > v1(line 148)
BB40
88   v20 = binaryop(sub) v18 , v19           (line 148)
90   v22 = binaryop(add) v20 , v21:#80       (line 148)
91   invokespecial < Application, Lcom/squareup/okhttp/internal/StrictLineReader$1, <init>(Lcom/squareup/okhttp/internal/StrictLineReader;I)V > v17,v1,v22 @157 exception:v23(line 148)
BB41
BB42
95   v24 = getfield < Application, Lcom/squareup/okhttp/internal/StrictLineReader, buf, <Primordial,[B> > v1(line 161)
BB43
97   v25 = getfield < Application, Lcom/squareup/okhttp/internal/StrictLineReader, pos, <Primordial,I> > v1(line 161)
BB44
99   v26 = getfield < Application, Lcom/squareup/okhttp/internal/StrictLineReader, end, <Primordial,I> > v1(line 161)
BB45
101   v27 = getfield < Application, Lcom/squareup/okhttp/internal/StrictLineReader, pos, <Primordial,I> > v1(line 161)
BB46
102   v28 = binaryop(sub) v26 , v27          (line 161)
103   invokevirtual < Application, Ljava/io/ByteArrayOutputStream, write([BII)V > v17,v24,v25,v28 @179 exception:v29(line 161)
BB47
106   putfield v1 = v30:#-1 < Application, Lcom/squareup/okhttp/internal/StrictLineReader, end, <Primordial,I> >(line 163)
BB48
108   invokespecial < Application, Lcom/squareup/okhttp/internal/StrictLineReader, fillBuf()V > v1 @188 exception:v31(line 164)
BB49
110   v32 = getfield < Application, Lcom/squareup/okhttp/internal/StrictLineReader, pos, <Primordial,I> > v1(line 166)
BB50
112   goto                                   (line 166)
BB51
114   v34 = getfield < Application, Lcom/squareup/okhttp/internal/StrictLineReader, buf, <Primordial,[B> > v1(line 167)
BB52
116   v35 = arrayload v34[v37]               (line 167)
BB53
118   conditional branch(ne) v35,v13:#10     (line 167)
BB54
121   v38 = getfield < Application, Lcom/squareup/okhttp/internal/StrictLineReader, pos, <Primordial,I> > v1(line 168)
BB55
122   conditional branch(eq) v37,v38         (line 168)
BB56
125   v39 = getfield < Application, Lcom/squareup/okhttp/internal/StrictLineReader, buf, <Primordial,[B> > v1(line 169)
BB57
127   v40 = getfield < Application, Lcom/squareup/okhttp/internal/StrictLineReader, pos, <Primordial,I> > v1(line 169)
BB58
130   v41 = getfield < Application, Lcom/squareup/okhttp/internal/StrictLineReader, pos, <Primordial,I> > v1(line 169)
BB59
131   v42 = binaryop(sub) v37 , v41          (line 169)
132   invokevirtual < Application, Ljava/io/ByteArrayOutputStream, write([BII)V > v17,v39,v40,v42 @233 exception:v43(line 169)
BB60
136   v44 = binaryop(add) v37 , v14:#1       (line 171)
137   putfield v1 = v44 < Application, Lcom/squareup/okhttp/internal/StrictLineReader, pos, <Primordial,I> >(line 171)
BB61
139   v46 = invokevirtual < Application, Ljava/io/ByteArrayOutputStream, toString()Ljava/lang/String; > v17 @244 exception:v45(line 172)
BB62
141   monitorexit v3                         (line 172)
BB63
142   return v46                             (line 172)
BB64
145   v36 = binaryop(add) v37 , v14:#1       (line 166)
BB65
           v37 = phi  v32,v36
149   v33 = getfield < Application, Lcom/squareup/okhttp/internal/StrictLineReader, end, <Primordial,I> > v1(line 166)
BB66
150   conditional branch(ne) v37,v33         (line 166)
BB67
151   goto                                   (line 160)
BB68<Handler>
           v67 = getCaughtException 
153   monitorexit v3                         (line 126)
BB69
154   throw v67                              (line 126)
BB70

**CGNode:** Node: < Application, Lcom/squareup/okhttp/internal/DiskLruCache, readJournalLine(Ljava/lang/String;)V > Context: JavaTypeContext<point: <Application,Lcom/squareup/okhttp/internal/DiskLruCache>>
**IR:** < Application, Lcom/squareup/okhttp/internal/DiskLruCache, readJournalLine(Ljava/lang/String;)V >
CFG:
BB0[-1..-2]
    -> BB1
BB1[0..2]
    -> BB2
    -> BB64
BB2[3..6]
    -> BB10
    -> BB3
BB3[7..7]
    -> BB4
    -> BB64
BB4[8..9]
    -> BB5
    -> BB64
BB5[10..12]
    -> BB6
    -> BB64
BB6[13..14]
    -> BB7
    -> BB64
BB7[15..15]
    -> BB8
    -> BB64
BB8[16..16]
    -> BB9
    -> BB64
BB9[17..17]
    -> BB64
BB10[18..25]
    -> BB11
    -> BB64
BB11[26..29]
    -> BB20
    -> BB12
BB12[30..32]
    -> BB13
    -> BB64
BB13[33..36]
    -> BB14
    -> BB64
BB14[37..37]
    -> BB22
    -> BB15
BB15[38..40]
    -> BB16
    -> BB64
BB16[41..42]
    -> BB22
    -> BB17
BB17[43..44]
    -> BB18
    -> BB64
BB18[45..46]
    -> BB19
    -> BB64
BB19[47..48]
    -> BB64
BB20[49..52]
    -> BB21
    -> BB64
BB21[53..53]
    -> BB22
BB22[54..55]
    -> BB23
    -> BB64
BB23[56..57]
    -> BB24
    -> BB64
BB24[58..58]
    -> BB25
    -> BB64
BB25[59..62]
    -> BB31
    -> BB26
BB26[63..63]
    -> BB27
    -> BB64
BB27[64..68]
    -> BB28
    -> BB64
BB28[69..71]
    -> BB29
    -> BB64
BB29[72..74]
    -> BB30
    -> BB64
BB30[75..75]
    -> BB31
BB31[76..78]
    -> BB42
    -> BB32
BB32[79..81]
    -> BB33
    -> BB64
BB33[82..82]
    -> BB42
    -> BB34
BB34[83..85]
    -> BB35
    -> BB64
BB35[86..87]
    -> BB42
    -> BB36
BB36[88..92]
    -> BB37
    -> BB64
BB37[93..94]
    -> BB38
    -> BB64
BB38[95..98]
    -> BB39
    -> BB64
BB39[99..101]
    -> BB40
    -> BB64
BB40[102..104]
    -> BB41
    -> BB64
BB41[105..105]
    -> BB63
BB42[106..108]
    -> BB51
    -> BB43
BB43[109..111]
    -> BB44
    -> BB64
BB44[112..112]
    -> BB51
    -> BB45
BB45[113..115]
    -> BB46
    -> BB64
BB46[116..117]
    -> BB51
    -> BB47
BB47[118..119]
    -> BB48
    -> BB64
BB48[120..124]
    -> BB49
    -> BB64
BB49[125..125]
    -> BB50
    -> BB64
BB50[126..126]
    -> BB63
BB51[127..129]
    -> BB56
    -> BB52
BB52[130..132]
    -> BB53
    -> BB64
BB53[133..133]
    -> BB56
    -> BB54
BB54[134..136]
    -> BB55
    -> BB64
BB55[137..138]
    -> BB63
    -> BB56
BB56[139..139]
    -> BB57
    -> BB64
BB57[140..141]
    -> BB58
    -> BB64
BB58[142..144]
    -> BB59
    -> BB64
BB59[145..146]
    -> BB60
    -> BB64
BB60[147..147]
    -> BB61
    -> BB64
BB61[148..148]
    -> BB62
    -> BB64
BB62[149..149]
    -> BB64
BB63[150..150]
    -> BB64
BB64[-1..-2]
Instructions:
BB0
BB1
2   v6 = invokevirtual < Application, Ljava/lang/String, indexOf(I)I > v2,v4:#32 @3 exception:v5(line 280)
BB2
6   conditional branch(ne) v6,v7:#-1         (line 281)
BB3
7   v73 = new <Application,Ljava/io/IOException>@12(line 282)
BB4
9   v74 = new <Application,Ljava/lang/StringBuilder>@16(line 282)
BB5
12   invokespecial < Application, Ljava/lang/StringBuilder, <init>(Ljava/lang/String;)V > v74,v51:#unexpected journal line:  @23 exception:v75(line 282)
BB6
14   v77 = invokevirtual < Application, Ljava/lang/StringBuilder, append(Ljava/lang/String;)Ljava/lang/StringBuilder; > v74,v2 @27 exception:v76(line 282)
BB7
15   v79 = invokevirtual < Application, Ljava/lang/StringBuilder, toString()Ljava/lang/String; > v77 @30 exception:v78(line 282)
BB8
16   invokespecial < Application, Ljava/io/IOException, <init>(Ljava/lang/String;)V > v73,v79 @33 exception:v80(line 282)
BB9
17   throw v73                               (line 282)
BB10
20   v9 = binaryop(add) v6 , v8:#1           (line 285)
25   v11 = invokevirtual < Application, Ljava/lang/String, indexOf(II)I > v2,v4:#32,v9 @45 exception:v10(line 286)
BB11
29   conditional branch(ne) v11,v7:#-1       (line 288)
BB12
32   v15 = invokevirtual < Application, Ljava/lang/String, substring(I)Ljava/lang/String; > v2,v9 @58 exception:v14(line 289)
BB13
36   v18 = invokevirtual < Application, Ljava/lang/String, length()I > v16:#REMOVE @66 exception:v17(line 290)
BB14
37   conditional branch(ne) v6,v18           (line 290)
BB15
40   v20 = invokevirtual < Application, Ljava/lang/String, startsWith(Ljava/lang/String;)Z > v2,v16:#REMOVE @75 exception:v19(line 290)
BB16
42   conditional branch(eq) v20,v21:#0       (line 290)
BB17
44   v70 = getfield < Application, Lcom/squareup/okhttp/internal/DiskLruCache, lruEntries, <Application,Ljava/util/LinkedHashMap> > v1(line 291)
BB18
46   v72 = invokevirtual < Application, Ljava/util/LinkedHashMap, remove(Ljava/lang/Object;)Ljava/lang/Object; > v70,v15 @87 exception:v71(line 291)
BB19
48   return                                  (line 292)
BB20
52   v13 = invokevirtual < Application, Ljava/lang/String, substring(II)Ljava/lang/String; > v2,v9,v11 @96 exception:v12(line 295)
BB21
BB22
           v22 = phi  v15,v15,v13
55   v23 = getfield < Application, Lcom/squareup/okhttp/internal/DiskLruCache, lruEntries, <Application,Ljava/util/LinkedHashMap> > v1(line 298)
BB23
57   v25 = invokevirtual < Application, Ljava/util/LinkedHashMap, get(Ljava/lang/Object;)Ljava/lang/Object; > v23,v22 @107 exception:v24(line 298)
BB24
58   v26 = checkcast <Application,Lcom/squareup/okhttp/internal/DiskLruCache$Entry>v25(line 298)
BB25
62   conditional branch(ne) v26,v27:#null    (line 299)
BB26
63   v28 = new <Application,Lcom/squareup/okhttp/internal/DiskLruCache$Entry>@120(line 300)
BB27
68   invokespecial < Application, Lcom/squareup/okhttp/internal/DiskLruCache$Entry, <init>(Lcom/squareup/okhttp/internal/DiskLruCache;Ljava/lang/String;Lcom/squareup/okhttp/internal/DiskLruCache$Entry;)V > v28,v1,v22,v27:#null @128 exception:v29(line 300)
BB28
71   v30 = getfield < Application, Lcom/squareup/okhttp/internal/DiskLruCache, lruEntries, <Application,Ljava/util/LinkedHashMap> > v1(line 301)
BB29
74   v32 = invokevirtual < Application, Ljava/util/LinkedHashMap, put(Ljava/lang/Object;Ljava/lang/Object;)Ljava/lang/Object; > v30,v22,v28 @141 exception:v31(line 301)
BB30
BB31
           v33 = phi  v26,v28
78   conditional branch(eq) v11,v7:#-1       (line 304)
BB32
81   v36 = invokevirtual < Application, Ljava/lang/String, length()I > v34:#CLEAN @154 exception:v35(line 304)
BB33
82   conditional branch(ne) v6,v36           (line 304)
BB34
85   v38 = invokevirtual < Application, Ljava/lang/String, startsWith(Ljava/lang/String;)Z > v2,v34:#CLEAN @163 exception:v37(line 304)
BB35
87   conditional branch(eq) v38,v21:#0       (line 304)
BB36
91   v61 = binaryop(add) v11 , v8:#1         (line 305)
92   v63 = invokevirtual < Application, Ljava/lang/String, substring(I)Ljava/lang/String; > v2,v61 @174 exception:v62(line 305)
BB37
94   v66 = invokevirtual < Application, Ljava/lang/String, split(Ljava/lang/String;)[Ljava/lang/String; > v63,v64:#  @180 exception:v65(line 305)
BB38
98   invokestatic < Application, Lcom/squareup/okhttp/internal/DiskLruCache$Entry, access$4(Lcom/squareup/okhttp/internal/DiskLruCache$Entry;Z)V > v33,v8:#1 @188 exception:v67(line 306)
BB39
101   invokestatic < Application, Lcom/squareup/okhttp/internal/DiskLruCache$Entry, access$5(Lcom/squareup/okhttp/internal/DiskLruCache$Entry;Lcom/squareup/okhttp/internal/DiskLruCache$Editor;)V > v33,v27:#null @194 exception:v68(line 307)
BB40
104   invokestatic < Application, Lcom/squareup/okhttp/internal/DiskLruCache$Entry, access$6(Lcom/squareup/okhttp/internal/DiskLruCache$Entry;[Ljava/lang/String;)V > v33,v66 @201 exception:v69(line 308)
BB41
105   goto                                   (line 308)
BB42
108   conditional branch(ne) v11,v7:#-1      (line 309)
BB43
111   v41 = invokevirtual < Application, Ljava/lang/String, length()I > v39:#DIRTY @216 exception:v40(line 309)
BB44
112   conditional branch(ne) v6,v41          (line 309)
BB45
115   v43 = invokevirtual < Application, Ljava/lang/String, startsWith(Ljava/lang/String;)Z > v2,v39:#DIRTY @225 exception:v42(line 309)
BB46
117   conditional branch(eq) v43,v21:#0      (line 309)
BB47
119   v58 = new <Application,Lcom/squareup/okhttp/internal/DiskLruCache$Editor>@233(line 310)
BB48
124   invokespecial < Application, Lcom/squareup/okhttp/internal/DiskLruCache$Editor, <init>(Lcom/squareup/okhttp/internal/DiskLruCache;Lcom/squareup/okhttp/internal/DiskLruCache$Entry;Lcom/squareup/okhttp/internal/DiskLruCache$Editor;)V > v58,v1,v33,v27:#null @241 exception:v59(line 310)
BB49
125   invokestatic < Application, Lcom/squareup/okhttp/internal/DiskLruCache$Entry, access$5(Lcom/squareup/okhttp/internal/DiskLruCache$Entry;Lcom/squareup/okhttp/internal/DiskLruCache$Editor;)V > v33,v58 @244 exception:v60(line 310)
BB50
126   goto                                   (line 310)
BB51
129   conditional branch(ne) v11,v7:#-1      (line 311)
BB52
132   v46 = invokevirtual < Application, Ljava/lang/String, length()I > v44:#READ @259 exception:v45(line 311)
BB53
133   conditional branch(ne) v6,v46          (line 311)
BB54
136   v48 = invokevirtual < Application, Ljava/lang/String, startsWith(Ljava/lang/String;)Z > v2,v44:#READ @268 exception:v47(line 311)
BB55
138   conditional branch(ne) v48,v21:#0      (line 311)
BB56
139   v49 = new <Application,Ljava/io/IOException>@274(line 314)
BB57
141   v50 = new <Application,Ljava/lang/StringBuilder>@278(line 314)
BB58
144   invokespecial < Application, Ljava/lang/StringBuilder, <init>(Ljava/lang/String;)V > v50,v51:#unexpected journal line:  @285 exception:v52(line 314)
BB59
146   v54 = invokevirtual < Application, Ljava/lang/StringBuilder, append(Ljava/lang/String;)Ljava/lang/StringBuilder; > v50,v2 @289 exception:v53(line 314)
BB60
147   v56 = invokevirtual < Application, Ljava/lang/StringBuilder, toString()Ljava/lang/String; > v54 @292 exception:v55(line 314)
BB61
148   invokespecial < Application, Ljava/io/IOException, <init>(Ljava/lang/String;)V > v49,v56 @295 exception:v57(line 314)
BB62
149   throw v49                              (line 314)
BB63
150   return                                 (line 316)
BB64

**CGNode:** Node: < Application, Lcom/squareup/okhttp/internal/Util, closeQuietly(Ljava/io/Closeable;)V > Context: JavaTypeContext<point: <Application,Lcom/squareup/okhttp/internal/StrictLineReader>>
**IR:** < Application, Lcom/squareup/okhttp/internal/Util, closeQuietly(Ljava/io/Closeable;)V >
CFG:
BB0[-1..-2]
    -> BB1
BB1[0..2]
    -> BB6
    -> BB2
BB2[3..4]
    -> BB3
    -> BB4
    -> BB5
    -> BB7
BB3[5..5]
    -> BB6
BB4[6..8]
    -> BB7
BB5[9..9]
    -> BB6
BB6[10..10]
    -> BB7
BB7[-1..-2]
Instructions:
BB0
BB1
2   conditional branch(eq) v1,v3:#null       (line 104)
BB2
4   invokeinterface < Application, Ljava/io/Closeable, close()V > v1 @5 exception:v4(line 106)
BB3
5   goto                                     (line 106)
BB4<Handler>
           v6 = getCaughtException 
8   throw v6                                 (line 108)
BB5<Handler>
           v5 = getCaughtException 
BB6
10   return                                  (line 112)
BB7

**CGNode:** Node: < Application, Lcom/squareup/okhttp/internal/DiskLruCache$Entry, access$1(Lcom/squareup/okhttp/internal/DiskLruCache$Entry;)Lcom/squareup/okhttp/internal/DiskLruCache$Editor; > Context: JavaTypeContext<point: <Application,Lcom/squareup/okhttp/internal/DiskLruCache>>
**IR:** < Application, Lcom/squareup/okhttp/internal/DiskLruCache$Entry, access$1(Lcom/squareup/okhttp/internal/DiskLruCache$Entry;)Lcom/squareup/okhttp/internal/DiskLruCache$Editor; >
CFG:
BB0[-1..-2]
    -> BB1
BB1[0..1]
    -> BB2
    -> BB3
BB2[2..2]
    -> BB3
BB3[-1..-2]
Instructions:
BB0
BB1
1   v3 = getfield < Application, Lcom/squareup/okhttp/internal/DiskLruCache$Entry, currentEditor, <Application,Lcom/squareup/okhttp/internal/DiskLruCache$Editor> > v1(line 907)
BB2
2   return v3                                (line 907)
BB3

**CGNode:** Node: < Application, Lcom/squareup/okhttp/internal/DiskLruCache$Entry, access$7(Lcom/squareup/okhttp/internal/DiskLruCache$Entry;)[J > Context: JavaTypeContext<point: <Application,Lcom/squareup/okhttp/internal/DiskLruCache>>
**IR:** < Application, Lcom/squareup/okhttp/internal/DiskLruCache$Entry, access$7(Lcom/squareup/okhttp/internal/DiskLruCache$Entry;)[J >
CFG:
BB0[-1..-2]
    -> BB1
BB1[0..1]
    -> BB2
    -> BB3
BB2[2..2]
    -> BB3
BB3[-1..-2]
Instructions:
BB0
BB1
1   v3 = getfield < Application, Lcom/squareup/okhttp/internal/DiskLruCache$Entry, lengths, <Primordial,[J> > v1(line 901)
BB2
2   return v3                                (line 901)
BB3

**CGNode:** Node: < Application, Lcom/squareup/okhttp/internal/DiskLruCache$Entry, access$5(Lcom/squareup/okhttp/internal/DiskLruCache$Entry;Lcom/squareup/okhttp/internal/DiskLruCache$Editor;)V > Context: JavaTypeContext<point: <Application,Lcom/squareup/okhttp/internal/DiskLruCache>>
**IR:** < Application, Lcom/squareup/okhttp/internal/DiskLruCache$Entry, access$5(Lcom/squareup/okhttp/internal/DiskLruCache$Entry;Lcom/squareup/okhttp/internal/DiskLruCache$Editor;)V >
CFG:
BB0[-1..-2]
    -> BB1
BB1[0..2]
    -> BB2
    -> BB3
BB2[3..3]
    -> BB3
BB3[-1..-2]
Instructions:
BB0
BB1
2   putfield v1 = v2 < Application, Lcom/squareup/okhttp/internal/DiskLruCache$Entry, currentEditor, <Application,Lcom/squareup/okhttp/internal/DiskLruCache$Editor> >(line 907)
BB2
3   return                                   (line 907)
BB3

**CGNode:** Node: < Application, Lcom/squareup/okhttp/internal/DiskLruCache, deleteIfExists(Ljava/io/File;)V > Context: JavaTypeContext<point: <Application,Lcom/squareup/okhttp/internal/DiskLruCache>>
**IR:** < Application, Lcom/squareup/okhttp/internal/DiskLruCache, deleteIfExists(Ljava/io/File;)V >
CFG:
BB0[-1..-2]
    -> BB1
BB1[0..1]
    -> BB2
    -> BB9
BB2[2..3]
    -> BB8
    -> BB3
BB3[4..5]
    -> BB4
    -> BB9
BB4[6..7]
    -> BB8
    -> BB5
BB5[8..8]
    -> BB6
    -> BB9
BB6[9..10]
    -> BB7
    -> BB9
BB7[11..11]
    -> BB9
BB8[12..12]
    -> BB9
BB9[-1..-2]
Instructions:
BB0
BB1
1   v4 = invokevirtual < Application, Ljava/io/File, exists()Z > v1 @1 exception:v3(line 385)
BB2
3   conditional branch(eq) v4,v5:#0          (line 385)
BB3
5   v7 = invokevirtual < Application, Ljava/io/File, delete()Z > v1 @8 exception:v6(line 385)
BB4
7   conditional branch(ne) v7,v5:#0          (line 385)
BB5
8   v8 = new <Application,Ljava/io/IOException>@14(line 386)
BB6
10   invokespecial < Application, Ljava/io/IOException, <init>()V > v8 @18 exception:v9(line 386)
BB7
11   throw v8                                (line 386)
BB8
12   return                                  (line 388)
BB9

**CGNode:** Node: < Application, Lcom/squareup/okhttp/internal/Platform, findPlatform()Lcom/squareup/okhttp/internal/Platform; > Context: Everywhere
**IR:** < Application, Lcom/squareup/okhttp/internal/Platform, findPlatform()Lcom/squareup/okhttp/internal/Platform; >
CFG:
BB0[-1..-2]
    -> BB1
BB1[0..1]
    -> BB2
    -> BB21
    -> BB60
BB2[2..6]
    -> BB3
    -> BB60
BB3[7..10]
    -> BB4
    -> BB60
BB4[11..11]
    -> BB5
    -> BB22
    -> BB60
BB5[12..16]
    -> BB6
    -> BB60
BB6[17..19]
    -> BB7
    -> BB21
BB7[20..20]
    -> BB8
    -> BB60
BB8[21..21]
    -> BB9
    -> BB22
    -> BB60
BB9[22..26]
    -> BB10
    -> BB60
BB10[27..29]
    -> BB11
    -> BB21
BB11[30..30]
    -> BB12
    -> BB60
BB12[31..31]
    -> BB13
    -> BB18
    -> BB60
BB13[32..36]
    -> BB14
    -> BB60
BB14[37..37]
    -> BB15
    -> BB18
    -> BB60
BB15[38..39]
    -> BB16
    -> BB60
BB16[40..47]
    -> BB17
    -> BB60
BB17[48..48]
    -> BB60
BB18[49..50]
    -> BB19
    -> BB60
BB19[51..57]
    -> BB20
    -> BB60
BB20[58..58]
    -> BB60
BB21[59..60]
    -> BB23
BB22[61..61]
    -> BB23
BB23[62..65]
    -> BB24
    -> BB54
    -> BB60
BB24[66..67]
    -> BB25
    -> BB60
BB25[68..70]
    -> BB26
    -> BB60
BB26[71..71]
    -> BB27
    -> BB60
BB27[72..73]
    -> BB28
    -> BB60
BB28[74..74]
    -> BB29
    -> BB60
BB29[75..75]
    -> BB30
    -> BB54
    -> BB60
BB30[76..77]
    -> BB31
    -> BB60
BB31[78..80]
    -> BB32
    -> BB60
BB32[81..81]
    -> BB33
    -> BB60
BB33[82..83]
    -> BB34
    -> BB60
BB34[84..84]
    -> BB35
    -> BB60
BB35[85..85]
    -> BB36
    -> BB54
    -> BB60
BB36[86..87]
    -> BB37
    -> BB60
BB37[88..90]
    -> BB38
    -> BB60
BB38[91..91]
    -> BB39
    -> BB60
BB39[92..93]
    -> BB40
    -> BB60
BB40[94..94]
    -> BB41
    -> BB60
BB41[95..95]
    -> BB42
    -> BB54
    -> BB60
BB42[96..100]
    -> BB43
    -> BB60
BB43[101..103]
    -> BB44
    -> BB54
BB44[104..104]
    -> BB45
    -> BB60
BB45[105..108]
    -> BB46
    -> BB60
BB46[109..109]
    -> BB47
    -> BB57
    -> BB60
BB47[110..114]
    -> BB48
    -> BB60
BB48[115..117]
    -> BB49
    -> BB54
BB49[118..118]
    -> BB50
    -> BB60
BB50[119..119]
    -> BB51
    -> BB57
    -> BB60
BB51[120..121]
    -> BB52
    -> BB60
BB52[122..127]
    -> BB53
    -> BB60
BB53[128..128]
    -> BB60
BB54[129..130]
    -> BB55
    -> BB60
BB55[131..132]
    -> BB56
    -> BB60
BB56[133..133]
    -> BB60
BB57[134..135]
    -> BB58
    -> BB60
BB58[136..137]
    -> BB59
    -> BB60
BB59[138..138]
    -> BB60
BB60[-1..-2]
Instructions:
BB0
BB1
1   v4 = invokestatic < Application, Ljava/lang/Class, forName(Ljava/lang/String;)Ljava/lang/Class; > v2:#org.apache.harmony.xnet.provider.jsse.OpenSSLSocketImpl @2 exception:v3(line 133)
BB2
6   v7 = new <Application,[Ljava/lang/Class>@10v6:#1 (line 134)
BB3
9   v9 = getstatic < Application, Ljava/lang/Boolean, TYPE, <Application,Ljava/lang/Class> >(line 134)
10   arraystore v7[v8:#0] = v9               (line 134)
BB4
11   v11 = invokevirtual < Application, Ljava/lang/Class, getMethod(Ljava/lang/String;[Ljava/lang/Class;)Ljava/lang/reflect/Method; > v4,v5:#setUseSessionTickets,v7 @19 exception:v10(line 134)
BB5
16   v13 = new <Application,[Ljava/lang/Class>@27v6:#1 (line 135)
BB6
19   v14 = load_metadata: <Primordial,Ljava/lang/String>, <Primordial,Ljava/lang/Class>(line 135)
BB7
20   arraystore v13[v8:#0] = v14             (line 135)
BB8
21   v16 = invokevirtual < Application, Ljava/lang/Class, getMethod(Ljava/lang/String;[Ljava/lang/Class;)Ljava/lang/reflect/Method; > v4,v12:#setHostname,v13 @35 exception:v15(line 135)
BB9
26   v19 = new <Application,[Ljava/lang/Class>@43v6:#1 (line 139)
BB10
29   v20 = load_metadata: <Primordial,[B>, <Primordial,Ljava/lang/Class>(line 139)
BB11
30   arraystore v19[v8:#0] = v20             (line 139)
BB12
31   v79 = invokevirtual < Application, Ljava/lang/Class, getMethod(Ljava/lang/String;[Ljava/lang/Class;)Ljava/lang/reflect/Method; > v4,v18:#setNpnProtocols,v19 @51 exception:v78(line 139)
BB13
36   v81 = new <Application,[Ljava/lang/Class>@59v8:#0 (line 140)
BB14
37   v83 = invokevirtual < Application, Ljava/lang/Class, getMethod(Ljava/lang/String;[Ljava/lang/Class;)Ljava/lang/reflect/Method; > v4,v80:#getNpnSelectedProtocol,v81 @62 exception:v82(line 140)
BB15
39   v88 = new <Application,Lcom/squareup/okhttp/internal/Platform$Android41>@67(line 141)
BB16
47   invokespecial < Application, Lcom/squareup/okhttp/internal/Platform$Android41, <init>(Ljava/lang/Class;Ljava/lang/reflect/Method;Ljava/lang/reflect/Method;Ljava/lang/reflect/Method;Ljava/lang/reflect/Method;Lcom/squareup/okhttp/internal/Platform$Android41;)V > v88,v4,v11,v16,v79,v83,v86:#null @78 exception:v89(line 141)
BB17
48   return v88                              (line 141)
BB18<Handler>
           v84 = getCaughtException 
50   v85 = new <Application,Lcom/squareup/okhttp/internal/Platform$Android23>@83(line 144)
BB19
57   invokespecial < Application, Lcom/squareup/okhttp/internal/Platform$Android23, <init>(Ljava/lang/Class;Ljava/lang/reflect/Method;Ljava/lang/reflect/Method;Lcom/squareup/okhttp/internal/Platform$Android23;Lcom/squareup/okhttp/internal/Platform$Android23;)V > v85,v4,v11,v16,v86:#null,v86:#null @92 exception:v87(line 144)
BB20
58   return v85                              (line 144)
BB21<Handler>
           v21 = getCaughtException 
60   goto                                    (line 146)
BB22<Handler>
           v17 = getCaughtException 
BB23
65   v25 = invokestatic < Application, Ljava/lang/Class, forName(Ljava/lang/String;)Ljava/lang/Class; > v23:#org.eclipse.jetty.npn.NextProtoNego @105 exception:v24(line 155)
BB24
67   v26 = new <Application,Ljava/lang/StringBuilder>@110(line 156)
BB25
70   v28 = invokestatic < Application, Ljava/lang/String, valueOf(Ljava/lang/Object;)Ljava/lang/String; > v23:#org.eclipse.jetty.npn.NextProtoNego @115 exception:v27(line 156)
BB26
71   invokespecial < Application, Ljava/lang/StringBuilder, <init>(Ljava/lang/String;)V > v26,v28 @118 exception:v29(line 156)
BB27
73   v32 = invokevirtual < Application, Ljava/lang/StringBuilder, append(Ljava/lang/String;)Ljava/lang/StringBuilder; > v26,v30:#$Provider @123 exception:v31(line 156)
BB28
74   v34 = invokevirtual < Application, Ljava/lang/StringBuilder, toString()Ljava/lang/String; > v32 @126 exception:v33(line 156)
BB29
75   v36 = invokestatic < Application, Ljava/lang/Class, forName(Ljava/lang/String;)Ljava/lang/Class; > v34 @129 exception:v35(line 156)
BB30
77   v37 = new <Application,Ljava/lang/StringBuilder>@134(line 157)
BB31
80   v39 = invokestatic < Application, Ljava/lang/String, valueOf(Ljava/lang/Object;)Ljava/lang/String; > v23:#org.eclipse.jetty.npn.NextProtoNego @139 exception:v38(line 157)
BB32
81   invokespecial < Application, Ljava/lang/StringBuilder, <init>(Ljava/lang/String;)V > v37,v39 @142 exception:v40(line 157)
BB33
83   v43 = invokevirtual < Application, Ljava/lang/StringBuilder, append(Ljava/lang/String;)Ljava/lang/StringBuilder; > v37,v41:#$ClientProvider @147 exception:v42(line 157)
BB34
84   v45 = invokevirtual < Application, Ljava/lang/StringBuilder, toString()Ljava/lang/String; > v43 @150 exception:v44(line 157)
BB35
85   v47 = invokestatic < Application, Ljava/lang/Class, forName(Ljava/lang/String;)Ljava/lang/Class; > v45 @153 exception:v46(line 157)
BB36
87   v48 = new <Application,Ljava/lang/StringBuilder>@158(line 158)
BB37
90   v50 = invokestatic < Application, Ljava/lang/String, valueOf(Ljava/lang/Object;)Ljava/lang/String; > v23:#org.eclipse.jetty.npn.NextProtoNego @163 exception:v49(line 158)
BB38
91   invokespecial < Application, Ljava/lang/StringBuilder, <init>(Ljava/lang/String;)V > v48,v50 @166 exception:v51(line 158)
BB39
93   v54 = invokevirtual < Application, Ljava/lang/StringBuilder, append(Ljava/lang/String;)Ljava/lang/StringBuilder; > v48,v52:#$ServerProvider @171 exception:v53(line 158)
BB40
94   v56 = invokevirtual < Application, Ljava/lang/StringBuilder, toString()Ljava/lang/String; > v54 @174 exception:v55(line 158)
BB41
95   v58 = invokestatic < Application, Ljava/lang/Class, forName(Ljava/lang/String;)Ljava/lang/Class; > v56 @177 exception:v57(line 158)
BB42
100   v61 = new <Application,[Ljava/lang/Class>@187v60:#2 (line 159)
BB43
103   v62 = load_metadata: <Primordial,Ljavax/net/ssl/SSLSocket>, <Primordial,Ljava/lang/Class>(line 159)
BB44
104   arraystore v61[v8:#0] = v62            (line 159)
BB45
108   arraystore v61[v6:#1] = v36            (line 159)
BB46
109   v64 = invokevirtual < Application, Ljava/lang/Class, getMethod(Ljava/lang/String;[Ljava/lang/Class;)Ljava/lang/reflect/Method; > v25,v59:#put,v61 @200 exception:v63(line 159)
BB47
114   v66 = new <Application,[Ljava/lang/Class>@210v6:#1 (line 160)
BB48
117   v67 = load_metadata: <Primordial,Ljavax/net/ssl/SSLSocket>, <Primordial,Ljava/lang/Class>(line 160)
BB49
118   arraystore v66[v8:#0] = v67            (line 160)
BB50
119   v72 = invokevirtual < Application, Ljava/lang/Class, getMethod(Ljava/lang/String;[Ljava/lang/Class;)Ljava/lang/reflect/Method; > v25,v65:#get,v66 @218 exception:v71(line 160)
BB51
121   v76 = new <Application,Lcom/squareup/okhttp/internal/Platform$JdkWithJettyNpnPlatform>@223(line 161)
BB52
127   invokespecial < Application, Lcom/squareup/okhttp/internal/Platform$JdkWithJettyNpnPlatform, <init>(Ljava/lang/reflect/Method;Ljava/lang/reflect/Method;Ljava/lang/Class;Ljava/lang/Class;)V > v76,v64,v72,v47,v58 @235 exception:v77(line 161)
BB53
128   return v76                             (line 161)
BB54<Handler>
           v68 = getCaughtException 
130   v69 = new <Application,Lcom/squareup/okhttp/internal/Platform>@240(line 164)
BB55
132   invokespecial < Application, Lcom/squareup/okhttp/internal/Platform, <init>()V > v69 @244 exception:v70(line 164)
BB56
133   return v69                             (line 164)
BB57<Handler>
           v73 = getCaughtException 
135   v74 = new <Application,Lcom/squareup/okhttp/internal/Platform>@249(line 166)
BB58
137   invokespecial < Application, Lcom/squareup/okhttp/internal/Platform, <init>()V > v74 @253 exception:v75(line 166)
BB59
138   return v74                             (line 166)
BB60

**CGNode:** Node: < Application, Lcom/squareup/okhttp/internal/DiskLruCache, close()V > Context: JavaTypeContext<point: <Application,Lcom/squareup/okhttp/internal/DiskLruCache>>
**IR:** < Application, Lcom/squareup/okhttp/internal/DiskLruCache, close()V >
CFG:
BB0[-1..-2]
    -> BB1
BB1[0..1]
    -> BB2
    -> BB23
BB2[2..3]
    -> BB4
    -> BB3
BB3[4..4]
    -> BB23
BB4[5..5]
    -> BB5
    -> BB23
BB5[6..8]
    -> BB6
    -> BB23
BB6[9..9]
    -> BB7
    -> BB23
BB7[10..10]
    -> BB8
    -> BB23
BB8[11..11]
    -> BB9
    -> BB23
BB9[12..13]
    -> BB16
BB10[14..15]
    -> BB11
    -> BB23
BB11[16..16]
    -> BB12
    -> BB23
BB12[17..19]
    -> BB13
    -> BB23
BB13[20..21]
    -> BB16
    -> BB14
BB14[22..23]
    -> BB15
    -> BB23
BB15[24..24]
    -> BB16
    -> BB23
BB16[25..26]
    -> BB17
    -> BB23
BB17[27..28]
    -> BB10
    -> BB18
BB18[29..30]
    -> BB19
    -> BB23
BB19[31..32]
    -> BB20
    -> BB23
BB20[33..33]
    -> BB21
    -> BB23
BB21[34..36]
    -> BB22
    -> BB23
BB22[37..37]
    -> BB23
BB23[-1..-2]
Instructions:
BB0
BB1
1   v3 = getfield < Application, Lcom/squareup/okhttp/internal/DiskLruCache, journalWriter, <Application,Ljava/io/Writer> > v1(line 636)
BB2
3   conditional branch(ne) v3,v4:#null       (line 636)
BB3
4   return                                   (line 637)
BB4
5   v5 = new <Application,Ljava/util/ArrayList>@8(line 639)
BB5
8   v6 = getfield < Application, Lcom/squareup/okhttp/internal/DiskLruCache, lruEntries, <Application,Ljava/util/LinkedHashMap> > v1(line 639)
BB6
9   v8 = invokevirtual < Application, Ljava/util/LinkedHashMap, values()Ljava/util/Collection; > v6 @16 exception:v7(line 639)
BB7
10   invokespecial < Application, Ljava/util/ArrayList, <init>(Ljava/util/Collection;)V > v5,v8 @19 exception:v9(line 639)
BB8
11   v11 = invokevirtual < Application, Ljava/util/ArrayList, iterator()Ljava/util/Iterator; > v5 @22 exception:v10(line 639)
BB9
13   goto                                    (line 639)
BB10
15   v16 = invokeinterface < Application, Ljava/util/Iterator, next()Ljava/lang/Object; > v11 @30 exception:v15(line 639)
BB11
16   v17 = checkcast <Application,Lcom/squareup/okhttp/internal/DiskLruCache$Entry>v16(line 639)
BB12
19   v19 = invokestatic < Application, Lcom/squareup/okhttp/internal/DiskLruCache$Entry, access$1(Lcom/squareup/okhttp/internal/DiskLruCache$Entry;)Lcom/squareup/okhttp/internal/DiskLruCache$Editor; > v17 @40 exception:v18(line 640)
BB13
21   conditional branch(eq) v19,v4:#null     (line 640)
BB14
23   v21 = invokestatic < Application, Lcom/squareup/okhttp/internal/DiskLruCache$Entry, access$1(Lcom/squareup/okhttp/internal/DiskLruCache$Entry;)Lcom/squareup/okhttp/internal/DiskLruCache$Editor; > v17 @47 exception:v20(line 641)
BB15
24   invokevirtual < Application, Lcom/squareup/okhttp/internal/DiskLruCache$Editor, abort()V > v21 @50 exception:v22(line 641)
BB16
26   v13 = invokeinterface < Application, Ljava/util/Iterator, hasNext()Z > v11 @54 exception:v12(line 639)
BB17
28   conditional branch(ne) v13,v14:#0       (line 639)
BB18
30   invokespecial < Application, Lcom/squareup/okhttp/internal/DiskLruCache, trimToSize()V > v1 @63 exception:v23(line 644)
BB19
32   v24 = getfield < Application, Lcom/squareup/okhttp/internal/DiskLruCache, journalWriter, <Application,Ljava/io/Writer> > v1(line 645)
BB20
33   invokevirtual < Application, Ljava/io/Writer, close()V > v24 @70 exception:v25(line 645)
BB21
36   putfield v1 = v4:#null < Application, Lcom/squareup/okhttp/internal/DiskLruCache, journalWriter, <Application,Ljava/io/Writer> >(line 646)
BB22
37   return                                  (line 647)
BB23

**CGNode:** Node: < Application, Lcom/squareup/okhttp/internal/Util, deleteContents(Ljava/io/File;)V > Context: JavaTypeContext<point: <Primordial,Ljava/io/File>>
**IR:** < Application, Lcom/squareup/okhttp/internal/Util, deleteContents(Ljava/io/File;)V >
CFG:
BB0[-1..-2]
    -> BB1
BB1[0..1]
    -> BB2
    -> BB28
BB2[2..5]
    -> BB10
    -> BB3
BB3[6..6]
    -> BB4
    -> BB28
BB4[7..8]
    -> BB5
    -> BB28
BB5[9..11]
    -> BB6
    -> BB28
BB6[12..13]
    -> BB7
    -> BB28
BB7[14..14]
    -> BB8
    -> BB28
BB8[15..15]
    -> BB9
    -> BB28
BB9[16..16]
    -> BB28
BB10[17..20]
    -> BB11
    -> BB28
BB11[21..24]
    -> BB26
BB12[25..27]
    -> BB13
    -> BB28
BB13[28..30]
    -> BB14
    -> BB28
BB14[31..32]
    -> BB16
    -> BB15
BB15[33..34]
    -> BB16
    -> BB28
BB16[35..36]
    -> BB17
    -> BB28
BB17[37..38]
    -> BB25
    -> BB18
BB18[39..39]
    -> BB19
    -> BB28
BB19[40..41]
    -> BB20
    -> BB28
BB20[42..44]
    -> BB21
    -> BB28
BB21[45..46]
    -> BB22
    -> BB28
BB22[47..47]
    -> BB23
    -> BB28
BB23[48..48]
    -> BB24
    -> BB28
BB24[49..49]
    -> BB28
BB25[50..53]
    -> BB26
BB26[54..56]
    -> BB12
    -> BB27
BB27[57..57]
    -> BB28
BB28[-1..-2]
Instructions:
BB0
BB1
1   v4 = invokevirtual < Application, Ljava/io/File, listFiles()[Ljava/io/File; > v1 @1 exception:v3(line 155)
BB2
5   conditional branch(ne) v4,v5:#null       (line 156)
BB3
6   v26 = new <Application,Ljava/lang/IllegalArgumentException>@9(line 157)
BB4
8   v27 = new <Application,Ljava/lang/StringBuilder>@13(line 157)
BB5
11   invokespecial < Application, Ljava/lang/StringBuilder, <init>(Ljava/lang/String;)V > v27,v28:#not a directory:  @19 exception:v29(line 157)
BB6
13   v31 = invokevirtual < Application, Ljava/lang/StringBuilder, append(Ljava/lang/Object;)Ljava/lang/StringBuilder; > v27,v1 @23 exception:v30(line 157)
BB7
14   v33 = invokevirtual < Application, Ljava/lang/StringBuilder, toString()Ljava/lang/String; > v31 @26 exception:v32(line 157)
BB8
15   invokespecial < Application, Ljava/lang/IllegalArgumentException, <init>(Ljava/lang/String;)V > v26,v33 @29 exception:v34(line 157)
BB9
16   throw v26                               (line 157)
BB10
20   v6 = arraylength v4                     (line 159)
BB11
24   goto                                    (line 159)
BB12
27   v8 = arrayload v4[v16]                  (line 159)
BB13
30   v10 = invokevirtual < Application, Ljava/io/File, isDirectory()Z > v8 @51 exception:v9(line 160)
BB14
32   conditional branch(eq) v10,v7:#0        (line 160)
BB15
34   invokestatic < Application, Lcom/squareup/okhttp/internal/Util, deleteContents(Ljava/io/File;)V > v8 @58 exception:v11(line 161)
BB16
36   v13 = invokevirtual < Application, Ljava/io/File, delete()Z > v8 @62 exception:v12(line 163)
BB17
38   conditional branch(ne) v13,v7:#0        (line 163)
BB18
39   v17 = new <Application,Ljava/io/IOException>@68(line 164)
BB19
41   v18 = new <Application,Ljava/lang/StringBuilder>@72(line 164)
BB20
44   invokespecial < Application, Ljava/lang/StringBuilder, <init>(Ljava/lang/String;)V > v18,v19:#failed to delete file:  @78 exception:v20(line 164)
BB21
46   v22 = invokevirtual < Application, Ljava/lang/StringBuilder, append(Ljava/lang/Object;)Ljava/lang/StringBuilder; > v18,v8 @82 exception:v21(line 164)
BB22
47   v24 = invokevirtual < Application, Ljava/lang/StringBuilder, toString()Ljava/lang/String; > v22 @85 exception:v23(line 164)
BB23
48   invokespecial < Application, Ljava/io/IOException, <init>(Ljava/lang/String;)V > v17,v24 @88 exception:v25(line 164)
BB24
49   throw v17                               (line 164)
BB25
52   v15 = binaryop(add) v16 , v14:#1        (line 159)
BB26
           v16 = phi  v7:#0,v15
56   conditional branch(lt) v16,v6           (line 159)
BB27
57   return                                  (line 167)
BB28

**CGNode:** Node: < Application, Lcom/squareup/okhttp/internal/DiskLruCache$Entry, access$2(Lcom/squareup/okhttp/internal/DiskLruCache$Entry;)Ljava/lang/String; > Context: JavaTypeContext<point: <Application,Lcom/squareup/okhttp/internal/DiskLruCache>>
**IR:** < Application, Lcom/squareup/okhttp/internal/DiskLruCache$Entry, access$2(Lcom/squareup/okhttp/internal/DiskLruCache$Entry;)Ljava/lang/String; >
CFG:
BB0[-1..-2]
    -> BB1
BB1[0..1]
    -> BB2
    -> BB3
BB2[2..2]
    -> BB3
BB3[-1..-2]
Instructions:
BB0
BB1
1   v3 = getfield < Application, Lcom/squareup/okhttp/internal/DiskLruCache$Entry, key, <Application,Ljava/lang/String> > v1(line 898)
BB2
2   return v3                                (line 898)
BB3

**CGNode:** Node: < Application, Lcom/squareup/okhttp/internal/spdy/SpdyStream$SpdyDataInputStream, <clinit>()V > Context: Everywhere
**IR:** < Application, Lcom/squareup/okhttp/internal/spdy/SpdyStream$SpdyDataInputStream, <clinit>()V >
CFG:
BB0[-1..-2]
    -> BB1
BB1[0..0]
    -> BB2
    -> BB7
BB2[1..1]
    -> BB3
    -> BB7
BB3[2..3]
    -> BB5
    -> BB4
BB4[4..5]
    -> BB6
BB5[6..6]
    -> BB6
BB6[7..8]
    -> BB7
BB7[-1..-2]
Instructions:
BB0
BB1
0   v2 = load_metadata: <Primordial,Lcom/squareup/okhttp/internal/spdy/SpdyStream>, <Primordial,Ljava/lang/Class>(line 385)
BB2
1   v4 = invokevirtual < Application, Ljava/lang/Class, desiredAssertionStatus()Z > v2 @2 exception:v3(line 385)
BB3
3   conditional branch(ne) v4,v5:#0          (line 385)
BB4
5   goto                                     (line 385)
BB5
BB6
           v7 = phi  v6:#1,v5:#0
7   putstatic v7 < Application, Lcom/squareup/okhttp/internal/spdy/SpdyStream$SpdyDataInputStream, $assertionsDisabled, <Primordial,Z> >(line 385)
8   return                                   (line 385)
BB7

**CGNode:** Node: < Application, Lcom/squareup/okhttp/internal/spdy/SpdyStream$SpdyDataInputStream, <init>(Lcom/squareup/okhttp/internal/spdy/SpdyStream;Lcom/squareup/okhttp/internal/spdy/SpdyStream$SpdyDataInputStream;)V > Context: JavaTypeContext<point: <Application,Lcom/squareup/okhttp/internal/spdy/SpdyStream$SpdyDataInputStream>>
**IR:** < Application, Lcom/squareup/okhttp/internal/spdy/SpdyStream$SpdyDataInputStream, <init>(Lcom/squareup/okhttp/internal/spdy/SpdyStream;Lcom/squareup/okhttp/internal/spdy/SpdyStream$SpdyDataInputStream;)V >
CFG:
BB0[-1..-2]
    -> BB1
BB1[0..2]
    -> BB2
    -> BB3
BB2[3..3]
    -> BB3
BB3[-1..-2]
Instructions:
BB0
BB1
2   invokespecial < Application, Lcom/squareup/okhttp/internal/spdy/SpdyStream$SpdyDataInputStream, <init>(Lcom/squareup/okhttp/internal/spdy/SpdyStream;)V > v1,v2 @2 exception:v5(line 385)
BB2
3   return                                   (line 385)
BB3

**CGNode:** Node: < Application, Lcom/squareup/okhttp/internal/spdy/SpdyStream$SpdyDataOutputStream, <clinit>()V > Context: Everywhere
**IR:** < Application, Lcom/squareup/okhttp/internal/spdy/SpdyStream$SpdyDataOutputStream, <clinit>()V >
CFG:
BB0[-1..-2]
    -> BB1
BB1[0..0]
    -> BB2
    -> BB7
BB2[1..1]
    -> BB3
    -> BB7
BB3[2..3]
    -> BB5
    -> BB4
BB4[4..5]
    -> BB6
BB5[6..6]
    -> BB6
BB6[7..8]
    -> BB7
BB7[-1..-2]
Instructions:
BB0
BB1
0   v2 = load_metadata: <Primordial,Lcom/squareup/okhttp/internal/spdy/SpdyStream>, <Primordial,Ljava/lang/Class>(line 615)
BB2
1   v4 = invokevirtual < Application, Ljava/lang/Class, desiredAssertionStatus()Z > v2 @2 exception:v3(line 615)
BB3
3   conditional branch(ne) v4,v5:#0          (line 615)
BB4
5   goto                                     (line 615)
BB5
BB6
           v7 = phi  v6:#1,v5:#0
7   putstatic v7 < Application, Lcom/squareup/okhttp/internal/spdy/SpdyStream$SpdyDataOutputStream, $assertionsDisabled, <Primordial,Z> >(line 615)
8   return                                   (line 615)
BB7

**CGNode:** Node: < Application, Lcom/squareup/okhttp/internal/spdy/SpdyStream$SpdyDataOutputStream, <init>(Lcom/squareup/okhttp/internal/spdy/SpdyStream;Lcom/squareup/okhttp/internal/spdy/SpdyStream$SpdyDataOutputStream;)V > Context: JavaTypeContext<point: <Application,Lcom/squareup/okhttp/internal/spdy/SpdyStream$SpdyDataOutputStream>>
**IR:** < Application, Lcom/squareup/okhttp/internal/spdy/SpdyStream$SpdyDataOutputStream, <init>(Lcom/squareup/okhttp/internal/spdy/SpdyStream;Lcom/squareup/okhttp/internal/spdy/SpdyStream$SpdyDataOutputStream;)V >
CFG:
BB0[-1..-2]
    -> BB1
BB1[0..2]
    -> BB2
    -> BB3
BB2[3..3]
    -> BB3
BB3[-1..-2]
Instructions:
BB0
BB1
2   invokespecial < Application, Lcom/squareup/okhttp/internal/spdy/SpdyStream$SpdyDataOutputStream, <init>(Lcom/squareup/okhttp/internal/spdy/SpdyStream;)V > v1,v2 @2 exception:v5(line 615)
BB2
3   return                                   (line 615)
BB3

**CGNode:** Node: < Application, Lcom/squareup/okhttp/internal/spdy/SpdyStream, isLocallyInitiated()Z > Context: JavaTypeContext<point: <Application,Lcom/squareup/okhttp/internal/spdy/SpdyStream>>
**IR:** < Application, Lcom/squareup/okhttp/internal/spdy/SpdyStream, isLocallyInitiated()Z >
CFG:
BB0[-1..-2]
    -> BB1
BB1[0..1]
    -> BB2
    -> BB11
BB2[2..3]
    -> BB3
    -> BB11
BB3[4..5]
    -> BB5
    -> BB4
BB4[6..7]
    -> BB6
BB5[8..8]
    -> BB6
BB6[9..11]
    -> BB7
    -> BB11
BB7[12..12]
    -> BB8
    -> BB11
BB8[13..14]
    -> BB10
    -> BB9
BB9[15..16]
    -> BB11
BB10[17..18]
    -> BB11
BB11[-1..-2]
Instructions:
BB0
BB1
1   v3 = getfield < Application, Lcom/squareup/okhttp/internal/spdy/SpdyStream, id, <Primordial,I> > v1(line 143)
BB2
3   v5 = binaryop(rem) v3 , v4:#2            (line 143)
BB3
5   conditional branch(ne) v5,v6:#1          (line 143)
BB4
7   goto                                     (line 143)
BB5
BB6
           v8 = phi  v6:#1,v7:#0
11   v9 = getfield < Application, Lcom/squareup/okhttp/internal/spdy/SpdyStream, connection, <Application,Lcom/squareup/okhttp/internal/spdy/SpdyConnection> > v1(line 144)
BB7
12   v10 = getfield < Application, Lcom/squareup/okhttp/internal/spdy/SpdyConnection, client, <Primordial,Z> > v9(line 144)
BB8
14   conditional branch(ne) v10,v8           (line 144)
BB9
16   return v6:#1                            (line 144)
BB10
18   return v7:#0                            (line 144)
BB11

**CGNode:** Node: < Application, Lcom/squareup/okhttp/internal/spdy/SpdyStream$SpdyDataInputStream, access$1(Lcom/squareup/okhttp/internal/spdy/SpdyStream$SpdyDataInputStream;Z)V > Context: JavaTypeContext<point: <Application,Lcom/squareup/okhttp/internal/spdy/SpdyStream$SpdyDataInputStream>>
**IR:** < Application, Lcom/squareup/okhttp/internal/spdy/SpdyStream$SpdyDataInputStream, access$1(Lcom/squareup/okhttp/internal/spdy/SpdyStream$SpdyDataInputStream;Z)V >
CFG:
BB0[-1..-2]
    -> BB1
BB1[0..2]
    -> BB2
    -> BB3
BB2[3..3]
    -> BB3
BB3[-1..-2]
Instructions:
BB0
BB1
2   putfield v1 = v2 < Application, Lcom/squareup/okhttp/internal/spdy/SpdyStream$SpdyDataInputStream, finished, <Primordial,Z> >(line 413)
BB2
3   return                                   (line 413)
BB3

**CGNode:** Node: < Application, Lcom/squareup/okhttp/internal/spdy/SpdyStream$SpdyDataOutputStream, access$1(Lcom/squareup/okhttp/internal/spdy/SpdyStream$SpdyDataOutputStream;Z)V > Context: JavaTypeContext<point: <Application,Lcom/squareup/okhttp/internal/spdy/SpdyStream$SpdyDataOutputStream>>
**IR:** < Application, Lcom/squareup/okhttp/internal/spdy/SpdyStream$SpdyDataOutputStream, access$1(Lcom/squareup/okhttp/internal/spdy/SpdyStream$SpdyDataOutputStream;Z)V >
CFG:
BB0[-1..-2]
    -> BB1
BB1[0..2]
    -> BB2
    -> BB3
BB2[3..3]
    -> BB3
BB3[-1..-2]
Instructions:
BB0
BB1
2   putfield v1 = v2 < Application, Lcom/squareup/okhttp/internal/spdy/SpdyStream$SpdyDataOutputStream, finished, <Primordial,Z> >(line 626)
BB2
3   return                                   (line 626)
BB3

**CGNode:** Node: < Application, Lcom/squareup/okhttp/internal/spdy/SpdyStream, setSettings(Lcom/squareup/okhttp/internal/spdy/Settings;)V > Context: JavaTypeContext<point: <Application,Lcom/squareup/okhttp/internal/spdy/SpdyStream>>
**IR:** < Application, Lcom/squareup/okhttp/internal/spdy/SpdyStream, setSettings(Lcom/squareup/okhttp/internal/spdy/Settings;)V >
CFG:
BB0[-1..-2]
    -> BB1
BB1[0..2]
    -> BB8
    -> BB2
BB2[3..4]
    -> BB3
    -> BB14
BB3[5..5]
    -> BB4
    -> BB14
BB4[6..7]
    -> BB8
    -> BB5
BB5[8..8]
    -> BB6
    -> BB14
BB6[9..10]
    -> BB7
    -> BB14
BB7[11..11]
    -> BB14
BB8[12..15]
    -> BB11
    -> BB9
BB9[16..18]
    -> BB10
    -> BB14
BB10[19..19]
    -> BB12
BB11[20..20]
    -> BB12
BB12[21..21]
    -> BB13
    -> BB14
BB13[22..22]
    -> BB14
BB14[-1..-2]
Instructions:
BB0
BB1
0   v4 = getstatic < Application, Lcom/squareup/okhttp/internal/spdy/SpdyStream, $assertionsDisabled, <Primordial,Z> >(line 350)
2   conditional branch(ne) v4,v5:#0          (line 350)
BB2
4   v6 = getfield < Application, Lcom/squareup/okhttp/internal/spdy/SpdyStream, connection, <Application,Lcom/squareup/okhttp/internal/spdy/SpdyConnection> > v1(line 350)
BB3
5   v8 = invokestatic < Application, Ljava/lang/Thread, holdsLock(Ljava/lang/Object;)Z > v6 @10 exception:v7(line 350)
BB4
7   conditional branch(ne) v8,v5:#0          (line 350)
BB5
8   v14 = new <Application,Ljava/lang/AssertionError>@16(line 350)
BB6
10   invokespecial < Application, Ljava/lang/AssertionError, <init>()V > v14 @20 exception:v15(line 350)
BB7
11   throw v14                               (line 350)
BB8
15   conditional branch(eq) v2,v9:#null      (line 352)
BB9
18   v12 = invokevirtual < Application, Lcom/squareup/okhttp/internal/spdy/Settings, getInitialWindowSize(I)I > v2,v10:#65536 @33 exception:v11(line 352)
BB10
19   goto                                    (line 352)
BB11
BB12
           v13 = phi  v12,v10:#65536
21   putfield v1 = v13 < Application, Lcom/squareup/okhttp/internal/spdy/SpdyStream, writeWindowSize, <Primordial,I> >(line 351)
BB13
22   return                                  (line 354)
BB14

**CGNode:** Node: < Application, Lcom/squareup/okhttp/internal/spdy/SpdyStream$SpdyDataInputStream, access$2(Lcom/squareup/okhttp/internal/spdy/SpdyStream$SpdyDataInputStream;)Z > Context: JavaTypeContext<point: <Application,Lcom/squareup/okhttp/internal/spdy/SpdyStream$SpdyDataInputStream>>
**IR:** < Application, Lcom/squareup/okhttp/internal/spdy/SpdyStream$SpdyDataInputStream, access$2(Lcom/squareup/okhttp/internal/spdy/SpdyStream$SpdyDataInputStream;)Z >
CFG:
BB0[-1..-2]
    -> BB1
BB1[0..1]
    -> BB2
    -> BB3
BB2[2..2]
    -> BB3
BB3[-1..-2]
Instructions:
BB0
BB1
1   v3 = getfield < Application, Lcom/squareup/okhttp/internal/spdy/SpdyStream$SpdyDataInputStream, finished, <Primordial,Z> > v1(line 413)
BB2
2   return v3                                (line 413)
BB3

**CGNode:** Node: < Application, Lcom/squareup/okhttp/internal/spdy/SpdyStream$SpdyDataInputStream, access$3(Lcom/squareup/okhttp/internal/spdy/SpdyStream$SpdyDataInputStream;)Z > Context: JavaTypeContext<point: <Application,Lcom/squareup/okhttp/internal/spdy/SpdyStream$SpdyDataInputStream>>
**IR:** < Application, Lcom/squareup/okhttp/internal/spdy/SpdyStream$SpdyDataInputStream, access$3(Lcom/squareup/okhttp/internal/spdy/SpdyStream$SpdyDataInputStream;)Z >
CFG:
BB0[-1..-2]
    -> BB1
BB1[0..1]
    -> BB2
    -> BB3
BB2[2..2]
    -> BB3
BB3[-1..-2]
Instructions:
BB0
BB1
1   v3 = getfield < Application, Lcom/squareup/okhttp/internal/spdy/SpdyStream$SpdyDataInputStream, closed, <Primordial,Z> > v1(line 407)
BB2
2   return v3                                (line 407)
BB3

**CGNode:** Node: < Application, Lcom/squareup/okhttp/internal/spdy/SpdyStream$SpdyDataOutputStream, access$2(Lcom/squareup/okhttp/internal/spdy/SpdyStream$SpdyDataOutputStream;)Z > Context: JavaTypeContext<point: <Application,Lcom/squareup/okhttp/internal/spdy/SpdyStream$SpdyDataOutputStream>>
**IR:** < Application, Lcom/squareup/okhttp/internal/spdy/SpdyStream$SpdyDataOutputStream, access$2(Lcom/squareup/okhttp/internal/spdy/SpdyStream$SpdyDataOutputStream;)Z >
CFG:
BB0[-1..-2]
    -> BB1
BB1[0..1]
    -> BB2
    -> BB3
BB2[2..2]
    -> BB3
BB3[-1..-2]
Instructions:
BB0
BB1
1   v3 = getfield < Application, Lcom/squareup/okhttp/internal/spdy/SpdyStream$SpdyDataOutputStream, finished, <Primordial,Z> > v1(line 626)
BB2
2   return v3                                (line 626)
BB3

**CGNode:** Node: < Application, Lcom/squareup/okhttp/internal/spdy/SpdyStream$SpdyDataOutputStream, access$3(Lcom/squareup/okhttp/internal/spdy/SpdyStream$SpdyDataOutputStream;)Z > Context: JavaTypeContext<point: <Application,Lcom/squareup/okhttp/internal/spdy/SpdyStream$SpdyDataOutputStream>>
**IR:** < Application, Lcom/squareup/okhttp/internal/spdy/SpdyStream$SpdyDataOutputStream, access$3(Lcom/squareup/okhttp/internal/spdy/SpdyStream$SpdyDataOutputStream;)Z >
CFG:
BB0[-1..-2]
    -> BB1
BB1[0..1]
    -> BB2
    -> BB3
BB2[2..2]
    -> BB3
BB3[-1..-2]
Instructions:
BB0
BB1
1   v3 = getfield < Application, Lcom/squareup/okhttp/internal/spdy/SpdyStream$SpdyDataOutputStream, closed, <Primordial,Z> > v1(line 620)
BB2
2   return v3                                (line 620)
BB3

**CGNode:** Node: < Application, Lcom/squareup/okhttp/internal/StrictLineReader, <init>(Ljava/io/InputStream;ILjava/nio/charset/Charset;)V > Context: JavaTypeContext<point: <Application,Lcom/squareup/okhttp/internal/StrictLineReader>>
**IR:** < Application, Lcom/squareup/okhttp/internal/StrictLineReader, <init>(Ljava/io/InputStream;ILjava/nio/charset/Charset;)V >
CFG:
BB0[-1..-2]
    -> BB1
BB1[0..1]
    -> BB2
    -> BB21
BB2[2..4]
    -> BB4
    -> BB3
BB3[5..7]
    -> BB7
    -> BB4
BB4[8..8]
    -> BB5
    -> BB21
BB5[9..10]
    -> BB6
    -> BB21
BB6[11..11]
    -> BB21
BB7[12..14]
    -> BB11
    -> BB8
BB8[15..15]
    -> BB9
    -> BB21
BB9[16..18]
    -> BB10
    -> BB21
BB10[19..19]
    -> BB21
BB11[20..22]
    -> BB12
    -> BB21
BB12[23..24]
    -> BB16
    -> BB13
BB13[25..25]
    -> BB14
    -> BB21
BB14[26..28]
    -> BB15
    -> BB21
BB15[29..29]
    -> BB21
BB16[30..32]
    -> BB17
    -> BB21
BB17[33..35]
    -> BB18
    -> BB21
BB18[36..38]
    -> BB19
    -> BB21
BB19[39..39]
    -> BB20
    -> BB21
BB20[40..40]
    -> BB21
BB21[-1..-2]
Instructions:
BB0
BB1
1   invokespecial < Application, Ljava/lang/Object, <init>()V > v1 @1 exception:v6(line 86)
BB2
4   conditional branch(eq) v2,v7:#null       (line 87)
BB3
7   conditional branch(ne) v4,v7:#null       (line 87)
BB4
8   v19 = new <Application,Ljava/lang/NullPointerException>@12(line 88)
BB5
10   invokespecial < Application, Ljava/lang/NullPointerException, <init>()V > v19 @16 exception:v20(line 88)
BB6
11   throw v19                               (line 88)
BB7
14   conditional branch(ge) v3,v8:#0         (line 90)
BB8
15   v16 = new <Application,Ljava/lang/IllegalArgumentException>@24(line 91)
BB9
18   invokespecial < Application, Ljava/lang/IllegalArgumentException, <init>(Ljava/lang/String;)V > v16,v17:#capacity <= 0 @30 exception:v18(line 91)
BB10
19   throw v16                               (line 91)
BB11
21   v9 = getstatic < Application, Lcom/squareup/okhttp/internal/Util, US_ASCII, <Application,Ljava/nio/charset/Charset> >(line 93)
22   v11 = invokevirtual < Application, Ljava/nio/charset/Charset, equals(Ljava/lang/Object;)Z > v4,v9 @38 exception:v10(line 93)
BB12
24   conditional branch(ne) v11,v8:#0        (line 93)
BB13
25   v13 = new <Application,Ljava/lang/IllegalArgumentException>@44(line 94)
BB14
28   invokespecial < Application, Ljava/lang/IllegalArgumentException, <init>(Ljava/lang/String;)V > v13,v14:#Unsupported encoding @50 exception:v15(line 94)
BB15
29   throw v13                               (line 94)
BB16
32   putfield v1 = v2 < Application, Lcom/squareup/okhttp/internal/StrictLineReader, in, <Application,Ljava/io/InputStream> >(line 97)
BB17
35   putfield v1 = v4 < Application, Lcom/squareup/okhttp/internal/StrictLineReader, charset, <Application,Ljava/nio/charset/Charset> >(line 98)
BB18
38   v12 = new <Primordial,[B>@66v3          (line 99)
BB19
39   putfield v1 = v12 < Application, Lcom/squareup/okhttp/internal/StrictLineReader, buf, <Primordial,[B> >(line 99)
BB20
40   return                                  (line 100)
BB21

**CGNode:** Node: < Application, Lcom/squareup/okhttp/internal/StrictLineReader, fillBuf()V > Context: JavaTypeContext<point: <Application,Lcom/squareup/okhttp/internal/StrictLineReader>>
**IR:** < Application, Lcom/squareup/okhttp/internal/StrictLineReader, fillBuf()V >
CFG:
BB0[-1..-2]
    -> BB1
BB1[0..1]
    -> BB2
    -> BB13
BB2[2..3]
    -> BB3
    -> BB13
BB3[4..6]
    -> BB4
    -> BB13
BB4[7..7]
    -> BB5
    -> BB13
BB5[8..8]
    -> BB6
    -> BB13
BB6[9..12]
    -> BB10
    -> BB7
BB7[13..13]
    -> BB8
    -> BB13
BB8[14..15]
    -> BB9
    -> BB13
BB9[16..16]
    -> BB13
BB10[17..19]
    -> BB11
    -> BB13
BB11[20..22]
    -> BB12
    -> BB13
BB12[23..23]
    -> BB13
BB13[-1..-2]
Instructions:
BB0
BB1
1   v3 = getfield < Application, Lcom/squareup/okhttp/internal/StrictLineReader, in, <Application,Ljava/io/InputStream> > v1(line 200)
BB2
3   v4 = getfield < Application, Lcom/squareup/okhttp/internal/StrictLineReader, buf, <Primordial,[B> > v1(line 200)
BB3
6   v6 = getfield < Application, Lcom/squareup/okhttp/internal/StrictLineReader, buf, <Primordial,[B> > v1(line 200)
BB4
7   v7 = arraylength v6                      (line 200)
BB5
8   v9 = invokevirtual < Application, Ljava/io/InputStream, read([BII)I > v3,v4,v5:#0,v7 @14 exception:v8(line 200)
BB6
12   conditional branch(ne) v9,v10:#-1       (line 201)
BB7
13   v11 = new <Application,Ljava/io/EOFException>@23(line 202)
BB8
15   invokespecial < Application, Ljava/io/EOFException, <init>()V > v11 @27 exception:v12(line 202)
BB9
16   throw v11                               (line 202)
BB10
19   putfield v1 = v5:#0 < Application, Lcom/squareup/okhttp/internal/StrictLineReader, pos, <Primordial,I> >(line 204)
BB11
22   putfield v1 = v9 < Application, Lcom/squareup/okhttp/internal/StrictLineReader, end, <Primordial,I> >(line 205)
BB12
23   return                                  (line 206)
BB13

**CGNode:** Node: < Application, Lcom/squareup/okhttp/internal/StrictLineReader$1, <init>(Lcom/squareup/okhttp/internal/StrictLineReader;I)V > Context: JavaTypeContext<point: <Application,Lcom/squareup/okhttp/internal/StrictLineReader$1>>
**IR:** < Application, Lcom/squareup/okhttp/internal/StrictLineReader$1, <init>(Lcom/squareup/okhttp/internal/StrictLineReader;I)V >
CFG:
BB0[-1..-2]
    -> BB1
BB1[0..2]
    -> BB2
    -> BB4
BB2[3..5]
    -> BB3
    -> BB4
BB3[6..6]
    -> BB4
BB4[-1..-2]
Instructions:
BB0
BB1
2   putfield v1 = v2 < Application, Lcom/squareup/okhttp/internal/StrictLineReader$1, this$0, <Application,Lcom/squareup/okhttp/internal/StrictLineReader> >(line 1)
BB2
5   invokespecial < Application, Ljava/io/ByteArrayOutputStream, <init>(I)V > v1,v3 @7 exception:v5(line 148)
BB3
6   return                                   (line 148)
BB4

**CGNode:** Node: < Application, Lcom/squareup/okhttp/internal/StrictLineReader$1, toString()Ljava/lang/String; > Context: JavaTypeContext<point: <Application,Lcom/squareup/okhttp/internal/StrictLineReader$1>>
**IR:** < Application, Lcom/squareup/okhttp/internal/StrictLineReader$1, toString()Ljava/lang/String; >
CFG:
BB0[-1..-2]
    -> BB1
BB1[0..1]
    -> BB2
    -> BB20
BB2[2..3]
    -> BB9
    -> BB3
BB3[4..5]
    -> BB4
    -> BB20
BB4[6..7]
    -> BB5
    -> BB20
BB5[8..10]
    -> BB6
    -> BB20
BB6[11..12]
    -> BB9
    -> BB7
BB7[13..14]
    -> BB8
    -> BB20
BB8[15..17]
    -> BB10
BB9[18..19]
    -> BB10
    -> BB20
BB10[20..21]
    -> BB11
    -> BB20
BB11[22..24]
    -> BB12
    -> BB20
BB12[25..28]
    -> BB13
    -> BB20
BB13[29..29]
    -> BB14
    -> BB20
BB14[30..30]
    -> BB15
    -> BB20
BB15[31..31]
    -> BB16
    -> BB17
    -> BB20
BB16[32..32]
    -> BB20
BB17[33..34]
    -> BB18
    -> BB20
BB18[35..37]
    -> BB19
    -> BB20
BB19[38..38]
    -> BB20
BB20[-1..-2]
Instructions:
BB0
BB1
1   v3 = getfield < Application, Lcom/squareup/okhttp/internal/StrictLineReader$1, count, <Primordial,I> > v1(line 151)
BB2
3   conditional branch(le) v3,v4:#0          (line 151)
BB3
5   v5 = getfield < Application, Lcom/squareup/okhttp/internal/StrictLineReader$1, buf, <Primordial,[B> > v1(line 151)
BB4
7   v6 = getfield < Application, Lcom/squareup/okhttp/internal/StrictLineReader$1, count, <Primordial,I> > v1(line 151)
BB5
9   v8 = binaryop(sub) v6 , v7:#1            (line 151)
10   v9 = arrayload v5[v8]                   (line 151)
BB6
12   conditional branch(ne) v9,v10:#13       (line 151)
BB7
14   v12 = getfield < Application, Lcom/squareup/okhttp/internal/StrictLineReader$1, count, <Primordial,I> > v1(line 151)
BB8
16   v13 = binaryop(sub) v12 , v7:#1         (line 151)
17   goto                                    (line 151)
BB9
19   v11 = getfield < Application, Lcom/squareup/okhttp/internal/StrictLineReader$1, count, <Primordial,I> > v1(line 151)
BB10
           v14 = phi  v13,v11
21   v15 = new <Application,Ljava/lang/String>@37(line 153)
BB11
24   v16 = getfield < Application, Lcom/squareup/okhttp/internal/StrictLineReader$1, buf, <Primordial,[B> > v1(line 153)
BB12
28   v17 = getfield < Application, Lcom/squareup/okhttp/internal/StrictLineReader$1, this$0, <Application,Lcom/squareup/okhttp/internal/StrictLineReader> > v1(line 153)
BB13
29   v19 = invokestatic < Application, Lcom/squareup/okhttp/internal/StrictLineReader, access$0(Lcom/squareup/okhttp/internal/StrictLineReader;)Ljava/nio/charset/Charset; > v17 @51 exception:v18(line 153)
BB14
30   v21 = invokevirtual < Application, Ljava/nio/charset/Charset, name()Ljava/lang/String; > v19 @54 exception:v20(line 153)
BB15
31   invokespecial < Application, Ljava/lang/String, <init>([BIILjava/lang/String;)V > v15,v16,v4:#0,v14,v21 @57 exception:v22(line 153)
BB16
32   return v15                              (line 153)
BB17<Handler>
           v23 = getCaughtException 
34   v24 = new <Application,Ljava/lang/AssertionError>@62(line 155)
BB18
37   invokespecial < Application, Ljava/lang/AssertionError, <init>(Ljava/lang/Object;)V > v24,v23 @67 exception:v25(line 155)
BB19
38   throw v24                               (line 155)
BB20

**CGNode:** Node: < Application, Lcom/squareup/okhttp/internal/DiskLruCache$Entry, <init>(Lcom/squareup/okhttp/internal/DiskLruCache;Ljava/lang/String;Lcom/squareup/okhttp/internal/DiskLruCache$Entry;)V > Context: JavaTypeContext<point: <Application,Lcom/squareup/okhttp/internal/DiskLruCache$Entry>>
**IR:** < Application, Lcom/squareup/okhttp/internal/DiskLruCache$Entry, <init>(Lcom/squareup/okhttp/internal/DiskLruCache;Ljava/lang/String;Lcom/squareup/okhttp/internal/DiskLruCache$Entry;)V >
CFG:
BB0[-1..-2]
    -> BB1
BB1[0..3]
    -> BB2
    -> BB3
BB2[4..4]
    -> BB3
BB3[-1..-2]
Instructions:
BB0
BB1
3   invokespecial < Application, Lcom/squareup/okhttp/internal/DiskLruCache$Entry, <init>(Lcom/squareup/okhttp/internal/DiskLruCache;Ljava/lang/String;)V > v1,v2,v3 @3 exception:v6(line 912)
BB2
4   return                                   (line 912)
BB3

**CGNode:** Node: < Application, Lcom/squareup/okhttp/internal/DiskLruCache$Entry, access$4(Lcom/squareup/okhttp/internal/DiskLruCache$Entry;Z)V > Context: JavaTypeContext<point: <Application,Lcom/squareup/okhttp/internal/DiskLruCache$Entry>>
**IR:** < Application, Lcom/squareup/okhttp/internal/DiskLruCache$Entry, access$4(Lcom/squareup/okhttp/internal/DiskLruCache$Entry;Z)V >
CFG:
BB0[-1..-2]
    -> BB1
BB1[0..2]
    -> BB2
    -> BB3
BB2[3..3]
    -> BB3
BB3[-1..-2]
Instructions:
BB0
BB1
2   putfield v1 = v2 < Application, Lcom/squareup/okhttp/internal/DiskLruCache$Entry, readable, <Primordial,Z> >(line 904)
BB2
3   return                                   (line 904)
BB3

**CGNode:** Node: < Application, Lcom/squareup/okhttp/internal/DiskLruCache$Entry, access$5(Lcom/squareup/okhttp/internal/DiskLruCache$Entry;Lcom/squareup/okhttp/internal/DiskLruCache$Editor;)V > Context: JavaTypeContext<point: <Application,Lcom/squareup/okhttp/internal/DiskLruCache$Entry>>
**IR:** < Application, Lcom/squareup/okhttp/internal/DiskLruCache$Entry, access$5(Lcom/squareup/okhttp/internal/DiskLruCache$Entry;Lcom/squareup/okhttp/internal/DiskLruCache$Editor;)V >
CFG:
BB0[-1..-2]
    -> BB1
BB1[0..2]
    -> BB2
    -> BB3
BB2[3..3]
    -> BB3
BB3[-1..-2]
Instructions:
BB0
BB1
2   putfield v1 = v2 < Application, Lcom/squareup/okhttp/internal/DiskLruCache$Entry, currentEditor, <Application,Lcom/squareup/okhttp/internal/DiskLruCache$Editor> >(line 907)
BB2
3   return                                   (line 907)
BB3

**CGNode:** Node: < Application, Lcom/squareup/okhttp/internal/DiskLruCache$Entry, access$6(Lcom/squareup/okhttp/internal/DiskLruCache$Entry;[Ljava/lang/String;)V > Context: JavaTypeContext<point: <Application,Lcom/squareup/okhttp/internal/DiskLruCache$Entry>>
**IR:** < Application, Lcom/squareup/okhttp/internal/DiskLruCache$Entry, access$6(Lcom/squareup/okhttp/internal/DiskLruCache$Entry;[Ljava/lang/String;)V >
CFG:
BB0[-1..-2]
    -> BB1
BB1[0..2]
    -> BB2
    -> BB3
BB2[3..3]
    -> BB3
BB3[-1..-2]
Instructions:
BB0
BB1
2   invokespecial < Application, Lcom/squareup/okhttp/internal/DiskLruCache$Entry, setLengths([Ljava/lang/String;)V > v1,v2 @2 exception:v4(line 928)
BB2
3   return                                   (line 928)
BB3

**CGNode:** Node: < Application, Lcom/squareup/okhttp/internal/DiskLruCache$Editor, <init>(Lcom/squareup/okhttp/internal/DiskLruCache;Lcom/squareup/okhttp/internal/DiskLruCache$Entry;Lcom/squareup/okhttp/internal/DiskLruCache$Editor;)V > Context: JavaTypeContext<point: <Application,Lcom/squareup/okhttp/internal/DiskLruCache$Editor>>
**IR:** < Application, Lcom/squareup/okhttp/internal/DiskLruCache$Editor, <init>(Lcom/squareup/okhttp/internal/DiskLruCache;Lcom/squareup/okhttp/internal/DiskLruCache$Entry;Lcom/squareup/okhttp/internal/DiskLruCache$Editor;)V >
CFG:
BB0[-1..-2]
    -> BB1
BB1[0..3]
    -> BB2
    -> BB3
BB2[4..4]
    -> BB3
BB3[-1..-2]
Instructions:
BB0
BB1
3   invokespecial < Application, Lcom/squareup/okhttp/internal/DiskLruCache$Editor, <init>(Lcom/squareup/okhttp/internal/DiskLruCache;Lcom/squareup/okhttp/internal/DiskLruCache$Entry;)V > v1,v2,v3 @3 exception:v6(line 747)
BB2
4   return                                   (line 747)
BB3

**CGNode:** Node: < Application, Lcom/squareup/okhttp/internal/StrictLineReader, close()V > Context: JavaTypeContext<point: <Application,Lcom/squareup/okhttp/internal/StrictLineReader>>
**IR:** < Application, Lcom/squareup/okhttp/internal/StrictLineReader, close()V >
CFG:
BB0[-1..-2]
    -> BB1
BB1[0..1]
    -> BB2
    -> BB13
BB2[2..4]
    -> BB3
    -> BB13
BB3[5..6]
    -> BB4
    -> BB10
BB4[7..8]
    -> BB8
    -> BB5
BB5[9..11]
    -> BB6
    -> BB10
BB6[12..13]
    -> BB7
    -> BB10
BB7[14..14]
    -> BB8
    -> BB10
BB8[15..16]
    -> BB9
    -> BB10
BB9[17..17]
    -> BB12
BB10[18..19]
    -> BB11
    -> BB10
BB11[20..20]
    -> BB13
BB12[21..21]
    -> BB13
BB13[-1..-2]
Instructions:
BB0
BB1
1   v3 = getfield < Application, Lcom/squareup/okhttp/internal/StrictLineReader, in, <Application,Ljava/io/InputStream> > v1(line 109)
BB2
4   monitorenter v3                          (line 109)
BB3
6   v4 = getfield < Application, Lcom/squareup/okhttp/internal/StrictLineReader, buf, <Primordial,[B> > v1(line 110)
BB4
8   conditional branch(eq) v4,v5:#null       (line 110)
BB5
11   putfield v1 = v5:#null < Application, Lcom/squareup/okhttp/internal/StrictLineReader, buf, <Primordial,[B> >(line 111)
BB6
13   v6 = getfield < Application, Lcom/squareup/okhttp/internal/StrictLineReader, in, <Application,Ljava/io/InputStream> > v1(line 112)
BB7
14   invokevirtual < Application, Ljava/io/InputStream, close()V > v6 @23 exception:v7(line 112)
BB8
16   monitorexit v3                          (line 109)
BB9
17   goto                                    (line 109)
BB10<Handler>
           v8 = getCaughtException 
19   monitorexit v3                          (line 109)
BB11
20   throw v8                                (line 109)
BB12
21   return                                  (line 115)
BB13

**CGNode:** Node: < Application, Lcom/squareup/okhttp/internal/Platform$Android41, <init>(Ljava/lang/Class;Ljava/lang/reflect/Method;Ljava/lang/reflect/Method;Ljava/lang/reflect/Method;Ljava/lang/reflect/Method;Lcom/squareup/okhttp/internal/Platform$Android41;)V > Context: JavaTypeContext<point: <Application,Lcom/squareup/okhttp/internal/Platform$Android41>>
**IR:** < Application, Lcom/squareup/okhttp/internal/Platform$Android41, <init>(Ljava/lang/Class;Ljava/lang/reflect/Method;Ljava/lang/reflect/Method;Ljava/lang/reflect/Method;Ljava/lang/reflect/Method;Lcom/squareup/okhttp/internal/Platform$Android41;)V >
CFG:
BB0[-1..-2]
    -> BB1
BB1[0..6]
    -> BB2
    -> BB3
BB2[7..7]
    -> BB3
BB3[-1..-2]
Instructions:
BB0
BB1
6   invokespecial < Application, Lcom/squareup/okhttp/internal/Platform$Android41, <init>(Ljava/lang/Class;Ljava/lang/reflect/Method;Ljava/lang/reflect/Method;Ljava/lang/reflect/Method;Ljava/lang/reflect/Method;)V > v1,v2,v3,v4,v5,v6 @8 exception:v9(line 207)
BB2
7   return                                   (line 207)
BB3

**CGNode:** Node: < Application, Lcom/squareup/okhttp/internal/Platform$Android23, <init>(Ljava/lang/Class;Ljava/lang/reflect/Method;Ljava/lang/reflect/Method;Lcom/squareup/okhttp/internal/Platform$Android23;Lcom/squareup/okhttp/internal/Platform$Android23;)V > Context: JavaTypeContext<point: <Application,Lcom/squareup/okhttp/internal/Platform$Android23>>
**IR:** < Application, Lcom/squareup/okhttp/internal/Platform$Android23, <init>(Ljava/lang/Class;Ljava/lang/reflect/Method;Ljava/lang/reflect/Method;Lcom/squareup/okhttp/internal/Platform$Android23;Lcom/squareup/okhttp/internal/Platform$Android23;)V >
CFG:
BB0[-1..-2]
    -> BB1
BB1[0..4]
    -> BB2
    -> BB3
BB2[5..5]
    -> BB3
BB3[-1..-2]
Instructions:
BB0
BB1
4   invokespecial < Application, Lcom/squareup/okhttp/internal/Platform$Android23, <init>(Ljava/lang/Class;Ljava/lang/reflect/Method;Ljava/lang/reflect/Method;)V > v1,v2,v3,v4 @4 exception:v8(line 179)
BB2
5   return                                   (line 179)
BB3

**CGNode:** Node: < Application, Lcom/squareup/okhttp/internal/Platform$JdkWithJettyNpnPlatform, <init>(Ljava/lang/reflect/Method;Ljava/lang/reflect/Method;Ljava/lang/Class;Ljava/lang/Class;)V > Context: JavaTypeContext<point: <Application,Lcom/squareup/okhttp/internal/Platform$JdkWithJettyNpnPlatform>>
**IR:** < Application, Lcom/squareup/okhttp/internal/Platform$JdkWithJettyNpnPlatform, <init>(Ljava/lang/reflect/Method;Ljava/lang/reflect/Method;Ljava/lang/Class;Ljava/lang/Class;)V >
CFG:
BB0[-1..-2]
    -> BB1
BB1[0..1]
    -> BB2
    -> BB7
BB2[2..4]
    -> BB3
    -> BB7
BB3[5..7]
    -> BB4
    -> BB7
BB4[8..10]
    -> BB5
    -> BB7
BB5[11..13]
    -> BB6
    -> BB7
BB6[14..14]
    -> BB7
BB7[-1..-2]
Instructions:
BB0
BB1
1   invokespecial < Application, Lcom/squareup/okhttp/internal/Platform, <init>()V > v1 @1 exception:v7(line 251)
BB2
4   putfield v1 = v2 < Application, Lcom/squareup/okhttp/internal/Platform$JdkWithJettyNpnPlatform, putMethod, <Application,Ljava/lang/reflect/Method> >(line 253)
BB3
7   putfield v1 = v3 < Application, Lcom/squareup/okhttp/internal/Platform$JdkWithJettyNpnPlatform, getMethod, <Application,Ljava/lang/reflect/Method> >(line 254)
BB4
10   putfield v1 = v4 < Application, Lcom/squareup/okhttp/internal/Platform$JdkWithJettyNpnPlatform, clientProviderClass, <Application,Ljava/lang/Class> >(line 255)
BB5
13   putfield v1 = v5 < Application, Lcom/squareup/okhttp/internal/Platform$JdkWithJettyNpnPlatform, serverProviderClass, <Application,Ljava/lang/Class> >(line 256)
BB6
14   return                                  (line 257)
BB7

**CGNode:** Node: < Application, Lcom/squareup/okhttp/internal/Platform, <init>()V > Context: JavaTypeContext<point: <Application,Lcom/squareup/okhttp/internal/Platform>>
**IR:** < Application, Lcom/squareup/okhttp/internal/Platform, <init>()V >
CFG:
BB0[-1..-2]
    -> BB1
BB1[0..1]
    -> BB2
    -> BB3
BB2[2..2]
    -> BB3
BB3[-1..-2]
Instructions:
BB0
BB1
1   invokespecial < Application, Ljava/lang/Object, <init>()V > v1 @1 exception:v3(line 49)
BB2
2   return                                   (line 49)
BB3

**CGNode:** Node: < Application, Lcom/squareup/okhttp/internal/DiskLruCache, trimToSize()V > Context: JavaTypeContext<point: <Application,Lcom/squareup/okhttp/internal/DiskLruCache>>
**IR:** < Application, Lcom/squareup/okhttp/internal/DiskLruCache, trimToSize()V >
CFG:
BB0[-1..-2]
    -> BB1
BB1[0..0]
    -> BB11
BB2[1..2]
    -> BB3
    -> BB15
BB3[3..3]
    -> BB4
    -> BB15
BB4[4..4]
    -> BB5
    -> BB15
BB5[5..5]
    -> BB6
    -> BB15
BB6[6..6]
    -> BB7
    -> BB15
BB7[7..10]
    -> BB8
    -> BB15
BB8[11..11]
    -> BB9
    -> BB15
BB9[12..12]
    -> BB10
    -> BB15
BB10[13..13]
    -> BB11
BB11[14..15]
    -> BB12
    -> BB15
BB12[16..17]
    -> BB13
    -> BB15
BB13[18..20]
    -> BB2
    -> BB14
BB14[21..21]
    -> BB15
BB15[-1..-2]
Instructions:
BB0
BB1
0   goto                                     (line 650)
BB2
2   v7 = getfield < Application, Lcom/squareup/okhttp/internal/DiskLruCache, lruEntries, <Application,Ljava/util/LinkedHashMap> > v1(line 651)
BB3
3   v9 = invokevirtual < Application, Ljava/util/LinkedHashMap, entrySet()Ljava/util/Set; > v7 @7 exception:v8(line 651)
BB4
4   v11 = invokeinterface < Application, Ljava/util/Set, iterator()Ljava/util/Iterator; > v9 @10 exception:v10(line 651)
BB5
5   v13 = invokeinterface < Application, Ljava/util/Iterator, next()Ljava/lang/Object; > v11 @15 exception:v12(line 651)
BB6
6   v14 = checkcast <Application,Ljava/util/Map$Entry>v13(line 651)
BB7
10   v16 = invokeinterface < Application, Ljava/util/Map$Entry, getKey()Ljava/lang/Object; > v14 @26 exception:v15(line 652)
BB8
11   v17 = checkcast <Application,Ljava/lang/String>v16(line 652)
BB9
12   v19 = invokevirtual < Application, Lcom/squareup/okhttp/internal/DiskLruCache, remove(Ljava/lang/String;)Z > v1,v17 @34 exception:v18(line 652)
BB10
BB11
15   v3 = getfield < Application, Lcom/squareup/okhttp/internal/DiskLruCache, size, <Primordial,J> > v1(line 650)
BB12
17   v4 = getfield < Application, Lcom/squareup/okhttp/internal/DiskLruCache, maxSize, <Primordial,J> > v1(line 650)
BB13
18   v5 = compare v3,v4 opcode=cmp           (line 650)
20   conditional branch(gt) v5,v6:#0         (line 650)
BB14
21   return                                  (line 654)
BB15

**CGNode:** Node: < Application, Lcom/squareup/okhttp/internal/spdy/SpdyStream$SpdyDataInputStream, <init>(Lcom/squareup/okhttp/internal/spdy/SpdyStream;)V > Context: JavaTypeContext<point: <Application,Lcom/squareup/okhttp/internal/spdy/SpdyStream$SpdyDataInputStream>>
**IR:** < Application, Lcom/squareup/okhttp/internal/spdy/SpdyStream$SpdyDataInputStream, <init>(Lcom/squareup/okhttp/internal/spdy/SpdyStream;)V >
CFG:
BB0[-1..-2]
    -> BB1
BB1[0..2]
    -> BB2
    -> BB8
BB2[3..4]
    -> BB3
    -> BB8
BB3[5..7]
    -> BB4
    -> BB8
BB4[8..8]
    -> BB5
    -> BB8
BB5[9..11]
    -> BB6
    -> BB8
BB6[12..14]
    -> BB7
    -> BB8
BB7[15..15]
    -> BB8
BB8[-1..-2]
Instructions:
BB0
BB1
2   putfield v1 = v2 < Application, Lcom/squareup/okhttp/internal/spdy/SpdyStream$SpdyDataInputStream, this$0, <Application,Lcom/squareup/okhttp/internal/spdy/SpdyStream> >(line 385)
BB2
4   invokespecial < Application, Ljava/io/InputStream, <init>()V > v1 @6 exception:v4(line 385)
BB3
7   v6 = new <Primordial,[B>@12v5:#65536     (line 398)
BB4
8   putfield v1 = v6 < Application, Lcom/squareup/okhttp/internal/spdy/SpdyStream$SpdyDataInputStream, buffer, <Primordial,[B> >(line 398)
BB5
11   putfield v1 = v7:#-1 < Application, Lcom/squareup/okhttp/internal/spdy/SpdyStream$SpdyDataInputStream, pos, <Primordial,I> >(line 401)
BB6
14   putfield v1 = v8:#0 < Application, Lcom/squareup/okhttp/internal/spdy/SpdyStream$SpdyDataInputStream, unacknowledgedBytes, <Primordial,I> >(line 420)
BB7
15   return                                  (line 420)
BB8

**CGNode:** Node: < Application, Lcom/squareup/okhttp/internal/spdy/SpdyStream$SpdyDataOutputStream, <init>(Lcom/squareup/okhttp/internal/spdy/SpdyStream;)V > Context: JavaTypeContext<point: <Application,Lcom/squareup/okhttp/internal/spdy/SpdyStream$SpdyDataOutputStream>>
**IR:** < Application, Lcom/squareup/okhttp/internal/spdy/SpdyStream$SpdyDataOutputStream, <init>(Lcom/squareup/okhttp/internal/spdy/SpdyStream;)V >
CFG:
BB0[-1..-2]
    -> BB1
BB1[0..2]
    -> BB2
    -> BB8
BB2[3..4]
    -> BB3
    -> BB8
BB3[5..7]
    -> BB4
    -> BB8
BB4[8..8]
    -> BB5
    -> BB8
BB5[9..11]
    -> BB6
    -> BB8
BB6[12..14]
    -> BB7
    -> BB8
BB7[15..15]
    -> BB8
BB8[-1..-2]
Instructions:
BB0
BB1
2   putfield v1 = v2 < Application, Lcom/squareup/okhttp/internal/spdy/SpdyStream$SpdyDataOutputStream, this$0, <Application,Lcom/squareup/okhttp/internal/spdy/SpdyStream> >(line 615)
BB2
4   invokespecial < Application, Ljava/io/OutputStream, <init>()V > v1 @6 exception:v4(line 615)
BB3
7   v6 = new <Primordial,[B>@13v5:#8192      (line 616)
BB4
8   putfield v1 = v6 < Application, Lcom/squareup/okhttp/internal/spdy/SpdyStream$SpdyDataOutputStream, buffer, <Primordial,[B> >(line 616)
BB5
11   putfield v1 = v7:#8 < Application, Lcom/squareup/okhttp/internal/spdy/SpdyStream$SpdyDataOutputStream, pos, <Primordial,I> >(line 617)
BB6
14   putfield v1 = v8:#0 < Application, Lcom/squareup/okhttp/internal/spdy/SpdyStream$SpdyDataOutputStream, unacknowledgedBytes, <Primordial,I> >(line 633)
BB7
15   return                                  (line 633)
BB8

**CGNode:** Node: < Application, Lcom/squareup/okhttp/internal/StrictLineReader, access$0(Lcom/squareup/okhttp/internal/StrictLineReader;)Ljava/nio/charset/Charset; > Context: JavaTypeContext<point: <Application,Lcom/squareup/okhttp/internal/StrictLineReader>>
**IR:** < Application, Lcom/squareup/okhttp/internal/StrictLineReader, access$0(Lcom/squareup/okhttp/internal/StrictLineReader;)Ljava/nio/charset/Charset; >
CFG:
BB0[-1..-2]
    -> BB1
BB1[0..1]
    -> BB2
    -> BB3
BB2[2..2]
    -> BB3
BB3[-1..-2]
Instructions:
BB0
BB1
1   v3 = getfield < Application, Lcom/squareup/okhttp/internal/StrictLineReader, charset, <Application,Ljava/nio/charset/Charset> > v1(line 50)
BB2
2   return v3                                (line 50)
BB3

**CGNode:** Node: < Application, Lcom/squareup/okhttp/internal/DiskLruCache$Entry, <init>(Lcom/squareup/okhttp/internal/DiskLruCache;Ljava/lang/String;)V > Context: JavaTypeContext<point: <Application,Lcom/squareup/okhttp/internal/DiskLruCache$Entry>>
**IR:** < Application, Lcom/squareup/okhttp/internal/DiskLruCache$Entry, <init>(Lcom/squareup/okhttp/internal/DiskLruCache;Ljava/lang/String;)V >
CFG:
BB0[-1..-2]
    -> BB1
BB1[0..2]
    -> BB2
    -> BB8
BB2[3..4]
    -> BB3
    -> BB8
BB3[5..7]
    -> BB4
    -> BB8
BB4[8..10]
    -> BB5
    -> BB8
BB5[11..11]
    -> BB6
    -> BB8
BB6[12..12]
    -> BB7
    -> BB8
BB7[13..13]
    -> BB8
BB8[-1..-2]
Instructions:
BB0
BB1
2   putfield v1 = v2 < Application, Lcom/squareup/okhttp/internal/DiskLruCache$Entry, this$0, <Application,Lcom/squareup/okhttp/internal/DiskLruCache> >(line 915)
BB2
4   invokespecial < Application, Ljava/lang/Object, <init>()V > v1 @6 exception:v5(line 912)
BB3
7   putfield v1 = v3 < Application, Lcom/squareup/okhttp/internal/DiskLruCache$Entry, key, <Application,Ljava/lang/String> >(line 913)
BB4
10   v7 = invokestatic < Application, Lcom/squareup/okhttp/internal/DiskLruCache, access$7(Lcom/squareup/okhttp/internal/DiskLruCache;)I > v2 @16 exception:v6(line 914)
BB5
11   v8 = new <Primordial,[J>@19v7           (line 914)
BB6
12   putfield v1 = v8 < Application, Lcom/squareup/okhttp/internal/DiskLruCache$Entry, lengths, <Primordial,[J> >(line 914)
BB7
13   return                                  (line 914)
BB8

**CGNode:** Node: < Application, Lcom/squareup/okhttp/internal/DiskLruCache$Entry, setLengths([Ljava/lang/String;)V > Context: JavaTypeContext<point: <Application,Lcom/squareup/okhttp/internal/DiskLruCache$Entry>>
**IR:** < Application, Lcom/squareup/okhttp/internal/DiskLruCache$Entry, setLengths([Ljava/lang/String;)V >
CFG:
BB0[-1..-2]
    -> BB1
BB1[0..1]
    -> BB2
    -> BB19
BB2[2..3]
    -> BB3
    -> BB19
BB3[4..4]
    -> BB4
    -> BB19
BB4[5..5]
    -> BB7
    -> BB5
BB5[6..8]
    -> BB6
    -> BB19
BB6[9..9]
    -> BB19
BB7[10..12]
    -> BB13
BB8[13..14]
    -> BB9
    -> BB19
BB9[15..18]
    -> BB10
    -> BB19
BB10[19..19]
    -> BB11
    -> BB16
    -> BB19
BB11[20..20]
    -> BB12
    -> BB19
BB12[21..24]
    -> BB13
BB13[25..27]
    -> BB14
    -> BB19
BB14[28..28]
    -> BB8
    -> BB15
BB15[29..29]
    -> BB18
BB16[30..33]
    -> BB17
    -> BB19
BB17[34..34]
    -> BB19
BB18[35..35]
    -> BB19
BB19[-1..-2]
Instructions:
BB0
BB1
1   v4 = arraylength v2                      (line 929)
BB2
3   v5 = getfield < Application, Lcom/squareup/okhttp/internal/DiskLruCache$Entry, this$0, <Application,Lcom/squareup/okhttp/internal/DiskLruCache> > v1(line 929)
BB3
4   v7 = invokestatic < Application, Lcom/squareup/okhttp/internal/DiskLruCache, access$7(Lcom/squareup/okhttp/internal/DiskLruCache;)I > v5 @6 exception:v6(line 929)
BB4
5   conditional branch(eq) v4,v7             (line 929)
BB5
8   v21 = invokespecial < Application, Lcom/squareup/okhttp/internal/DiskLruCache$Entry, invalidLengths([Ljava/lang/String;)Ljava/io/IOException; > v1,v2 @14 exception:v20(line 930)
BB6
9   throw v21                                (line 930)
BB7
12   goto                                    (line 934)
BB8
14   v10 = getfield < Application, Lcom/squareup/okhttp/internal/DiskLruCache$Entry, lengths, <Primordial,[J> > v1(line 935)
BB9
18   v11 = arrayload v2[v16]                 (line 935)
BB10
19   v13 = invokestatic < Application, Ljava/lang/Long, parseLong(Ljava/lang/String;)J > v11 @31 exception:v12(line 935)
BB11
20   arraystore v10[v16] = v13               (line 935)
BB12
23   v15 = binaryop(add) v16 , v14:#1        (line 934)
BB13
           v16 = phi  v8:#0,v15
27   v9 = arraylength v2                     (line 934)
BB14
28   conditional branch(lt) v16,v9           (line 934)
BB15
29   goto                                    (line 934)
BB16<Handler>
           v17 = getCaughtException 
33   v19 = invokespecial < Application, Lcom/squareup/okhttp/internal/DiskLruCache$Entry, invalidLengths([Ljava/lang/String;)Ljava/io/IOException; > v1,v2 @50 exception:v18(line 938)
BB17
34   throw v19                               (line 938)
BB18
35   return                                  (line 940)
BB19

**CGNode:** Node: < Application, Lcom/squareup/okhttp/internal/DiskLruCache$Editor, <init>(Lcom/squareup/okhttp/internal/DiskLruCache;Lcom/squareup/okhttp/internal/DiskLruCache$Entry;)V > Context: JavaTypeContext<point: <Application,Lcom/squareup/okhttp/internal/DiskLruCache$Editor>>
**IR:** < Application, Lcom/squareup/okhttp/internal/DiskLruCache$Editor, <init>(Lcom/squareup/okhttp/internal/DiskLruCache;Lcom/squareup/okhttp/internal/DiskLruCache$Entry;)V >
CFG:
BB0[-1..-2]
    -> BB1
BB1[0..2]
    -> BB2
    -> BB11
BB2[3..4]
    -> BB3
    -> BB11
BB3[5..7]
    -> BB4
    -> BB11
BB4[8..10]
    -> BB5
    -> BB11
BB5[11..12]
    -> BB7
    -> BB6
BB6[13..14]
    -> BB9
BB7[15..16]
    -> BB8
    -> BB11
BB8[17..17]
    -> BB9
    -> BB11
BB9[18..18]
    -> BB10
    -> BB11
BB10[19..19]
    -> BB11
BB11[-1..-2]
Instructions:
BB0
BB1
2   putfield v1 = v2 < Application, Lcom/squareup/okhttp/internal/DiskLruCache$Editor, this$0, <Application,Lcom/squareup/okhttp/internal/DiskLruCache> >(line 750)
BB2
4   invokespecial < Application, Ljava/lang/Object, <init>()V > v1 @6 exception:v5(line 747)
BB3
7   putfield v1 = v3 < Application, Lcom/squareup/okhttp/internal/DiskLruCache$Editor, entry, <Application,Lcom/squareup/okhttp/internal/DiskLruCache$Entry> >(line 748)
BB4
10   v7 = invokestatic < Application, Lcom/squareup/okhttp/internal/DiskLruCache$Entry, access$0(Lcom/squareup/okhttp/internal/DiskLruCache$Entry;)Z > v3 @16 exception:v6(line 749)
BB5
12   conditional branch(eq) v7,v8:#0         (line 749)
BB6
14   goto                                    (line 749)
BB7
16   v10 = invokestatic < Application, Lcom/squareup/okhttp/internal/DiskLruCache, access$7(Lcom/squareup/okhttp/internal/DiskLruCache;)I > v2 @27 exception:v9(line 749)
BB8
17   v11 = new <Primordial,[Z>@30v10         (line 749)
BB9
           v13 = phi  v12:#null,v11
18   putfield v1 = v13 < Application, Lcom/squareup/okhttp/internal/DiskLruCache$Editor, written, <Primordial,[Z> >(line 749)
BB10
19   return                                  (line 749)
BB11

**CGNode:** Node: < Application, Lcom/squareup/okhttp/internal/Platform$Android41, <init>(Ljava/lang/Class;Ljava/lang/reflect/Method;Ljava/lang/reflect/Method;Ljava/lang/reflect/Method;Ljava/lang/reflect/Method;)V > Context: JavaTypeContext<point: <Application,Lcom/squareup/okhttp/internal/Platform$Android41>>
**IR:** < Application, Lcom/squareup/okhttp/internal/Platform$Android41, <init>(Ljava/lang/Class;Ljava/lang/reflect/Method;Ljava/lang/reflect/Method;Ljava/lang/reflect/Method;Ljava/lang/reflect/Method;)V >
CFG:
BB0[-1..-2]
    -> BB1
BB1[0..5]
    -> BB2
    -> BB5
BB2[6..8]
    -> BB3
    -> BB5
BB3[9..11]
    -> BB4
    -> BB5
BB4[12..12]
    -> BB5
BB5[-1..-2]
Instructions:
BB0
BB1
5   invokespecial < Application, Lcom/squareup/okhttp/internal/Platform$Android23, <init>(Ljava/lang/Class;Ljava/lang/reflect/Method;Ljava/lang/reflect/Method;Lcom/squareup/okhttp/internal/Platform$Android23;)V > v1,v2,v3,v4,v8:#null @5 exception:v9(line 209)
BB2
8   putfield v1 = v5 < Application, Lcom/squareup/okhttp/internal/Platform$Android41, setNpnProtocols, <Application,Ljava/lang/reflect/Method> >(line 210)
BB3
11   putfield v1 = v6 < Application, Lcom/squareup/okhttp/internal/Platform$Android41, getNpnSelectedProtocol, <Application,Ljava/lang/reflect/Method> >(line 211)
BB4
12   return                                  (line 212)
BB5

**CGNode:** Node: < Application, Lcom/squareup/okhttp/internal/Platform$Android23, <init>(Ljava/lang/Class;Ljava/lang/reflect/Method;Ljava/lang/reflect/Method;)V > Context: JavaTypeContext<point: <Application,Lcom/squareup/okhttp/internal/Platform$Android23>>
**IR:** < Application, Lcom/squareup/okhttp/internal/Platform$Android23, <init>(Ljava/lang/Class;Ljava/lang/reflect/Method;Ljava/lang/reflect/Method;)V >
CFG:
BB0[-1..-2]
    -> BB1
BB1[0..1]
    -> BB2
    -> BB6
BB2[2..4]
    -> BB3
    -> BB6
BB3[5..7]
    -> BB4
    -> BB6
BB4[8..10]
    -> BB5
    -> BB6
BB5[11..11]
    -> BB6
BB6[-1..-2]
Instructions:
BB0
BB1
1   invokespecial < Application, Lcom/squareup/okhttp/internal/Platform, <init>()V > v1 @1 exception:v6(line 179)
BB2
4   putfield v1 = v2 < Application, Lcom/squareup/okhttp/internal/Platform$Android23, openSslSocketClass, <Application,Ljava/lang/Class> >(line 181)
BB3
7   putfield v1 = v3 < Application, Lcom/squareup/okhttp/internal/Platform$Android23, setUseSessionTickets, <Application,Ljava/lang/reflect/Method> >(line 182)
BB4
10   putfield v1 = v4 < Application, Lcom/squareup/okhttp/internal/Platform$Android23, setHostname, <Application,Ljava/lang/reflect/Method> >(line 183)
BB5
11   return                                  (line 184)
BB6

**CGNode:** Node: < Application, Lcom/squareup/okhttp/internal/Platform, <init>()V > Context: JavaTypeContext<point: <Application,Lcom/squareup/okhttp/internal/Platform$JdkWithJettyNpnPlatform>>
**IR:** < Application, Lcom/squareup/okhttp/internal/Platform, <init>()V >
CFG:
BB0[-1..-2]
    -> BB1
BB1[0..1]
    -> BB2
    -> BB3
BB2[2..2]
    -> BB3
BB3[-1..-2]
Instructions:
BB0
BB1
1   invokespecial < Application, Ljava/lang/Object, <init>()V > v1 @1 exception:v3(line 49)
BB2
2   return                                   (line 49)
BB3

**CGNode:** Node: < Application, Lcom/squareup/okhttp/internal/DiskLruCache, remove(Ljava/lang/String;)Z > Context: JavaTypeContext<point: <Application,Lcom/squareup/okhttp/internal/DiskLruCache>>
**IR:** < Application, Lcom/squareup/okhttp/internal/DiskLruCache, remove(Ljava/lang/String;)Z >
CFG:
BB0[-1..-2]
    -> BB1
BB1[0..1]
    -> BB2
    -> BB48
BB2[2..4]
    -> BB3
    -> BB48
BB3[5..6]
    -> BB4
    -> BB48
BB4[7..8]
    -> BB5
    -> BB48
BB5[9..9]
    -> BB6
    -> BB48
BB6[10..13]
    -> BB9
    -> BB7
BB7[14..15]
    -> BB8
    -> BB48
BB8[16..17]
    -> BB10
    -> BB9
BB9[18..19]
    -> BB48
BB10[20..22]
    -> BB28
BB11[23..25]
    -> BB12
    -> BB48
BB12[26..28]
    -> BB13
    -> BB48
BB13[29..30]
    -> BB21
    -> BB14
BB14[31..31]
    -> BB15
    -> BB48
BB15[32..33]
    -> BB16
    -> BB48
BB16[34..36]
    -> BB17
    -> BB48
BB17[37..38]
    -> BB18
    -> BB48
BB18[39..39]
    -> BB19
    -> BB48
BB19[40..40]
    -> BB20
    -> BB48
BB20[41..41]
    -> BB48
BB21[42..44]
    -> BB22
    -> BB48
BB22[45..46]
    -> BB23
    -> BB48
BB23[47..48]
    -> BB24
    -> BB48
BB24[49..50]
    -> BB25
    -> BB48
BB25[51..52]
    -> BB26
    -> BB48
BB26[53..55]
    -> BB27
    -> BB48
BB27[56..59]
    -> BB28
BB28[60..62]
    -> BB29
    -> BB48
BB29[63..63]
    -> BB11
    -> BB30
BB30[64..66]
    -> BB31
    -> BB48
BB31[67..69]
    -> BB32
    -> BB48
BB32[70..71]
    -> BB33
    -> BB48
BB33[72..72]
    -> BB34
    -> BB48
BB34[73..75]
    -> BB35
    -> BB48
BB35[76..77]
    -> BB36
    -> BB48
BB36[78..79]
    -> BB37
    -> BB48
BB37[80..80]
    -> BB38
    -> BB48
BB38[81..81]
    -> BB39
    -> BB48
BB39[82..84]
    -> BB40
    -> BB48
BB40[85..86]
    -> BB41
    -> BB48
BB41[87..89]
    -> BB42
    -> BB48
BB42[90..91]
    -> BB47
    -> BB43
BB43[92..93]
    -> BB44
    -> BB48
BB44[94..95]
    -> BB45
    -> BB48
BB45[96..96]
    -> BB46
    -> BB48
BB46[97..97]
    -> BB47
BB47[98..99]
    -> BB48
BB48[-1..-2]
Instructions:
BB0
BB1
1   invokespecial < Application, Lcom/squareup/okhttp/internal/DiskLruCache, checkNotClosed()V > v1 @1 exception:v4(line 583)
BB2
4   invokespecial < Application, Lcom/squareup/okhttp/internal/DiskLruCache, validateKey(Ljava/lang/String;)V > v1,v2 @6 exception:v5(line 584)
BB3
6   v6 = getfield < Application, Lcom/squareup/okhttp/internal/DiskLruCache, lruEntries, <Application,Ljava/util/LinkedHashMap> > v1(line 585)
BB4
8   v8 = invokevirtual < Application, Ljava/util/LinkedHashMap, get(Ljava/lang/Object;)Ljava/lang/Object; > v6,v2 @14 exception:v7(line 585)
BB5
9   v9 = checkcast <Application,Lcom/squareup/okhttp/internal/DiskLruCache$Entry>v8(line 585)
BB6
13   conditional branch(eq) v9,v10:#null     (line 586)
BB7
15   v12 = invokestatic < Application, Lcom/squareup/okhttp/internal/DiskLruCache$Entry, access$1(Lcom/squareup/okhttp/internal/DiskLruCache$Entry;)Lcom/squareup/okhttp/internal/DiskLruCache$Editor; > v9 @26 exception:v11(line 586)
BB8
17   conditional branch(eq) v12,v10:#null    (line 586)
BB9
19   return v13:#0                           (line 587)
BB10
22   goto                                    (line 590)
BB11
25   v16 = invokevirtual < Application, Lcom/squareup/okhttp/internal/DiskLruCache$Entry, getCleanFile(I)Ljava/io/File; > v9,v29 @41 exception:v15(line 591)
BB12
28   v18 = invokevirtual < Application, Ljava/io/File, delete()Z > v16 @48 exception:v17(line 592)
BB13
30   conditional branch(ne) v18,v13:#0       (line 592)
BB14
31   v54 = new <Application,Ljava/io/IOException>@54(line 593)
BB15
33   v55 = new <Application,Ljava/lang/StringBuilder>@58(line 593)
BB16
36   invokespecial < Application, Ljava/lang/StringBuilder, <init>(Ljava/lang/String;)V > v55,v56:#failed to delete  @65 exception:v57(line 593)
BB17
38   v59 = invokevirtual < Application, Ljava/lang/StringBuilder, append(Ljava/lang/Object;)Ljava/lang/StringBuilder; > v55,v16 @70 exception:v58(line 593)
BB18
39   v61 = invokevirtual < Application, Ljava/lang/StringBuilder, toString()Ljava/lang/String; > v59 @73 exception:v60(line 593)
BB19
40   invokespecial < Application, Ljava/io/IOException, <init>(Ljava/lang/String;)V > v54,v61 @76 exception:v62(line 593)
BB20
41   throw v54                               (line 593)
BB21
44   v19 = getfield < Application, Lcom/squareup/okhttp/internal/DiskLruCache, size, <Primordial,J> > v1(line 595)
BB22
46   v21 = invokestatic < Application, Lcom/squareup/okhttp/internal/DiskLruCache$Entry, access$7(Lcom/squareup/okhttp/internal/DiskLruCache$Entry;)[J > v9 @86 exception:v20(line 595)
BB23
48   v22 = arrayload v21[v29]                (line 595)
BB24
49   v23 = binaryop(sub) v19 , v22           (line 595)
50   putfield v1 = v23 < Application, Lcom/squareup/okhttp/internal/DiskLruCache, size, <Primordial,J> >(line 595)
BB25
52   v25 = invokestatic < Application, Lcom/squareup/okhttp/internal/DiskLruCache$Entry, access$7(Lcom/squareup/okhttp/internal/DiskLruCache$Entry;)[J > v9 @96 exception:v24(line 596)
BB26
55   arraystore v25[v29] = v26:#0            (line 596)
BB27
58   v28 = binaryop(add) v29 , v27:#1        (line 590)
BB28
           v29 = phi  v13:#0,v28
62   v14 = getfield < Application, Lcom/squareup/okhttp/internal/DiskLruCache, valueCount, <Primordial,I> > v1(line 590)
BB29
63   conditional branch(lt) v29,v14          (line 590)
BB30
66   v30 = getfield < Application, Lcom/squareup/okhttp/internal/DiskLruCache, redundantOpCount, <Primordial,I> > v1(line 599)
BB31
68   v31 = binaryop(add) v30 , v27:#1        (line 599)
69   putfield v1 = v31 < Application, Lcom/squareup/okhttp/internal/DiskLruCache, redundantOpCount, <Primordial,I> >(line 599)
BB32
71   v32 = getfield < Application, Lcom/squareup/okhttp/internal/DiskLruCache, journalWriter, <Application,Ljava/io/Writer> > v1(line 600)
BB33
72   v33 = new <Application,Ljava/lang/StringBuilder>@127(line 600)
BB34
75   invokespecial < Application, Ljava/lang/StringBuilder, <init>(Ljava/lang/String;)V > v33,v34:#REMOVE  @134 exception:v35(line 600)
BB35
77   v37 = invokevirtual < Application, Ljava/lang/StringBuilder, append(Ljava/lang/String;)Ljava/lang/StringBuilder; > v33,v2 @138 exception:v36(line 600)
BB36
79   v40 = invokevirtual < Application, Ljava/lang/StringBuilder, append(C)Ljava/lang/StringBuilder; > v37,v38:#10 @143 exception:v39(line 600)
BB37
80   v42 = invokevirtual < Application, Ljava/lang/StringBuilder, toString()Ljava/lang/String; > v40 @146 exception:v41(line 600)
BB38
81   v44 = invokevirtual < Application, Ljava/io/Writer, append(Ljava/lang/CharSequence;)Ljava/io/Writer; > v32,v42 @149 exception:v43(line 600)
BB39
84   v45 = getfield < Application, Lcom/squareup/okhttp/internal/DiskLruCache, lruEntries, <Application,Ljava/util/LinkedHashMap> > v1(line 601)
BB40
86   v47 = invokevirtual < Application, Ljava/util/LinkedHashMap, remove(Ljava/lang/Object;)Ljava/lang/Object; > v45,v2 @158 exception:v46(line 601)
BB41
89   v49 = invokespecial < Application, Lcom/squareup/okhttp/internal/DiskLruCache, journalRebuildRequired()Z > v1 @163 exception:v48(line 603)
BB42
91   conditional branch(eq) v49,v13:#0       (line 603)
BB43
93   v50 = getfield < Application, Lcom/squareup/okhttp/internal/DiskLruCache, executorService, <Application,Ljava/util/concurrent/ThreadPoolExecutor> > v1(line 604)
BB44
95   v51 = getfield < Application, Lcom/squareup/okhttp/internal/DiskLruCache, cleanupCallable, <Application,Ljava/util/concurrent/Callable> > v1(line 604)
BB45
96   v53 = invokevirtual < Application, Ljava/util/concurrent/ThreadPoolExecutor, submit(Ljava/util/concurrent/Callable;)Ljava/util/concurrent/Future; > v50,v51 @177 exception:v52(line 604)
BB46
BB47
99   return v27:#1                           (line 607)
BB48

**CGNode:** Node: < Application, Lcom/squareup/okhttp/internal/DiskLruCache, access$7(Lcom/squareup/okhttp/internal/DiskLruCache;)I > Context: JavaTypeContext<point: <Application,Lcom/squareup/okhttp/internal/DiskLruCache>>
**IR:** < Application, Lcom/squareup/okhttp/internal/DiskLruCache, access$7(Lcom/squareup/okhttp/internal/DiskLruCache;)I >
CFG:
BB0[-1..-2]
    -> BB1
BB1[0..1]
    -> BB2
    -> BB3
BB2[2..2]
    -> BB3
BB3[-1..-2]
Instructions:
BB0
BB1
1   v3 = getfield < Application, Lcom/squareup/okhttp/internal/DiskLruCache, valueCount, <Primordial,I> > v1(line 149)
BB2
2   return v3                                (line 149)
BB3

**CGNode:** Node: < Application, Lcom/squareup/okhttp/internal/DiskLruCache$Entry, invalidLengths([Ljava/lang/String;)Ljava/io/IOException; > Context: JavaTypeContext<point: <Application,Lcom/squareup/okhttp/internal/DiskLruCache$Entry>>
**IR:** < Application, Lcom/squareup/okhttp/internal/DiskLruCache$Entry, invalidLengths([Ljava/lang/String;)Ljava/io/IOException; >
CFG:
BB0[-1..-2]
    -> BB1
BB1[0..0]
    -> BB2
    -> BB9
BB2[1..2]
    -> BB3
    -> BB9
BB3[3..5]
    -> BB4
    -> BB9
BB4[6..7]
    -> BB5
    -> BB9
BB5[8..8]
    -> BB6
    -> BB9
BB6[9..9]
    -> BB7
    -> BB9
BB7[10..10]
    -> BB8
    -> BB9
BB8[11..11]
    -> BB9
BB9[-1..-2]
Instructions:
BB0
BB1
0   v4 = new <Application,Ljava/io/IOException>@0(line 943)
BB2
2   v5 = new <Application,Ljava/lang/StringBuilder>@4(line 943)
BB3
5   invokespecial < Application, Ljava/lang/StringBuilder, <init>(Ljava/lang/String;)V > v5,v6:#unexpected journal line:  @10 exception:v7(line 943)
BB4
7   v9 = invokestatic < Application, Ljava/util/Arrays, toString([Ljava/lang/Object;)Ljava/lang/String; > v2 @14 exception:v8(line 943)
BB5
8   v11 = invokevirtual < Application, Ljava/lang/StringBuilder, append(Ljava/lang/String;)Ljava/lang/StringBuilder; > v5,v9 @17 exception:v10(line 943)
BB6
9   v13 = invokevirtual < Application, Ljava/lang/StringBuilder, toString()Ljava/lang/String; > v11 @20 exception:v12(line 943)
BB7
10   invokespecial < Application, Ljava/io/IOException, <init>(Ljava/lang/String;)V > v4,v13 @23 exception:v14(line 943)
BB8
11   throw v4                                (line 943)
BB9

**CGNode:** Node: < Application, Lcom/squareup/okhttp/internal/DiskLruCache$Entry, access$0(Lcom/squareup/okhttp/internal/DiskLruCache$Entry;)Z > Context: JavaTypeContext<point: <Application,Lcom/squareup/okhttp/internal/DiskLruCache$Entry>>
**IR:** < Application, Lcom/squareup/okhttp/internal/DiskLruCache$Entry, access$0(Lcom/squareup/okhttp/internal/DiskLruCache$Entry;)Z >
CFG:
BB0[-1..-2]
    -> BB1
BB1[0..1]
    -> BB2
    -> BB3
BB2[2..2]
    -> BB3
BB3[-1..-2]
Instructions:
BB0
BB1
1   v3 = getfield < Application, Lcom/squareup/okhttp/internal/DiskLruCache$Entry, readable, <Primordial,Z> > v1(line 904)
BB2
2   return v3                                (line 904)
BB3

**CGNode:** Node: < Application, Lcom/squareup/okhttp/internal/Platform$Android23, <init>(Ljava/lang/Class;Ljava/lang/reflect/Method;Ljava/lang/reflect/Method;Lcom/squareup/okhttp/internal/Platform$Android23;)V > Context: JavaTypeContext<point: <Application,Lcom/squareup/okhttp/internal/Platform$Android41>>
**IR:** < Application, Lcom/squareup/okhttp/internal/Platform$Android23, <init>(Ljava/lang/Class;Ljava/lang/reflect/Method;Ljava/lang/reflect/Method;Lcom/squareup/okhttp/internal/Platform$Android23;)V >
CFG:
BB0[-1..-2]
    -> BB1
BB1[0..4]
    -> BB2
    -> BB3
BB2[5..5]
    -> BB3
BB3[-1..-2]
Instructions:
BB0
BB1
4   invokespecial < Application, Lcom/squareup/okhttp/internal/Platform$Android23, <init>(Ljava/lang/Class;Ljava/lang/reflect/Method;Ljava/lang/reflect/Method;)V > v1,v2,v3,v4 @4 exception:v7(line 179)
BB2
5   return                                   (line 179)
BB3

**CGNode:** Node: < Application, Lcom/squareup/okhttp/internal/Platform, <init>()V > Context: JavaTypeContext<point: <Application,Lcom/squareup/okhttp/internal/Platform$Android23>>
**IR:** < Application, Lcom/squareup/okhttp/internal/Platform, <init>()V >
CFG:
BB0[-1..-2]
    -> BB1
BB1[0..1]
    -> BB2
    -> BB3
BB2[2..2]
    -> BB3
BB3[-1..-2]
Instructions:
BB0
BB1
1   invokespecial < Application, Ljava/lang/Object, <init>()V > v1 @1 exception:v3(line 49)
BB2
2   return                                   (line 49)
BB3

**CGNode:** Node: < Application, Lcom/squareup/okhttp/internal/DiskLruCache, checkNotClosed()V > Context: JavaTypeContext<point: <Application,Lcom/squareup/okhttp/internal/DiskLruCache>>
**IR:** < Application, Lcom/squareup/okhttp/internal/DiskLruCache, checkNotClosed()V >
CFG:
BB0[-1..-2]
    -> BB1
BB1[0..1]
    -> BB2
    -> BB7
BB2[2..3]
    -> BB6
    -> BB3
BB3[4..4]
    -> BB4
    -> BB7
BB4[5..7]
    -> BB5
    -> BB7
BB5[8..8]
    -> BB7
BB6[9..9]
    -> BB7
BB7[-1..-2]
Instructions:
BB0
BB1
1   v3 = getfield < Application, Lcom/squareup/okhttp/internal/DiskLruCache, journalWriter, <Application,Ljava/io/Writer> > v1(line 618)
BB2
3   conditional branch(ne) v3,v4:#null       (line 618)
BB3
4   v5 = new <Application,Ljava/lang/IllegalStateException>@7(line 619)
BB4
7   invokespecial < Application, Ljava/lang/IllegalStateException, <init>(Ljava/lang/String;)V > v5,v6:#cache is closed @14 exception:v7(line 619)
BB5
8   throw v5                                 (line 619)
BB6
9   return                                   (line 621)
BB7

**CGNode:** Node: < Application, Lcom/squareup/okhttp/internal/DiskLruCache, validateKey(Ljava/lang/String;)V > Context: JavaTypeContext<point: <Application,Lcom/squareup/okhttp/internal/DiskLruCache>>
**IR:** < Application, Lcom/squareup/okhttp/internal/DiskLruCache, validateKey(Ljava/lang/String;)V >
CFG:
BB0[-1..-2]
    -> BB1
BB1[0..2]
    -> BB2
    -> BB13
BB2[3..5]
    -> BB3
    -> BB13
BB3[6..7]
    -> BB12
    -> BB4
BB4[8..8]
    -> BB5
    -> BB13
BB5[9..10]
    -> BB6
    -> BB13
BB6[11..13]
    -> BB7
    -> BB13
BB7[14..15]
    -> BB8
    -> BB13
BB8[16..17]
    -> BB9
    -> BB13
BB9[18..18]
    -> BB10
    -> BB13
BB10[19..19]
    -> BB11
    -> BB13
BB11[20..20]
    -> BB13
BB12[21..21]
    -> BB13
BB13[-1..-2]
Instructions:
BB0
BB1
0   v4 = getstatic < Application, Lcom/squareup/okhttp/internal/DiskLruCache, LEGAL_KEY_PATTERN, <Application,Ljava/util/regex/Pattern> >(line 667)
2   v6 = invokevirtual < Application, Ljava/util/regex/Pattern, matcher(Ljava/lang/CharSequence;)Ljava/util/regex/Matcher; > v4,v2 @4 exception:v5(line 667)
BB2
5   v8 = invokevirtual < Application, Ljava/util/regex/Matcher, matches()Z > v6 @9 exception:v7(line 668)
BB3
7   conditional branch(ne) v8,v9:#0          (line 668)
BB4
8   v10 = new <Application,Ljava/lang/IllegalArgumentException>@15(line 669)
BB5
10   v11 = new <Application,Ljava/lang/StringBuilder>@19(line 670)
BB6
13   invokespecial < Application, Ljava/lang/StringBuilder, <init>(Ljava/lang/String;)V > v11,v12:#keys must match regex [a-z0-9_-]{1,64}: " @26 exception:v13(line 670)
BB7
15   v15 = invokevirtual < Application, Ljava/lang/StringBuilder, append(Ljava/lang/String;)Ljava/lang/StringBuilder; > v11,v2 @30 exception:v14(line 670)
BB8
17   v18 = invokevirtual < Application, Ljava/lang/StringBuilder, append(Ljava/lang/String;)Ljava/lang/StringBuilder; > v15,v16:#" @36 exception:v17(line 670)
BB9
18   v20 = invokevirtual < Application, Ljava/lang/StringBuilder, toString()Ljava/lang/String; > v18 @39 exception:v19(line 670)
BB10
19   invokespecial < Application, Ljava/lang/IllegalArgumentException, <init>(Ljava/lang/String;)V > v10,v20 @42 exception:v21(line 669)
BB11
20   throw v10                               (line 669)
BB12
21   return                                  (line 672)
BB13

**CGNode:** Node: < Application, Lcom/squareup/okhttp/internal/DiskLruCache, journalRebuildRequired()Z > Context: JavaTypeContext<point: <Application,Lcom/squareup/okhttp/internal/DiskLruCache>>
**IR:** < Application, Lcom/squareup/okhttp/internal/DiskLruCache, journalRebuildRequired()Z >
CFG:
BB0[-1..-2]
    -> BB1
BB1[0..1]
    -> BB2
    -> BB9
BB2[2..3]
    -> BB8
    -> BB3
BB3[4..5]
    -> BB4
    -> BB9
BB4[6..7]
    -> BB5
    -> BB9
BB5[8..8]
    -> BB6
    -> BB9
BB6[9..9]
    -> BB8
    -> BB7
BB7[10..11]
    -> BB9
BB8[12..13]
    -> BB9
BB9[-1..-2]
Instructions:
BB0
BB1
1   v3 = getfield < Application, Lcom/squareup/okhttp/internal/DiskLruCache, redundantOpCount, <Primordial,I> > v1(line 573)
BB2
3   conditional branch(lt) v3,v4:#2000       (line 573)
BB3
5   v5 = getfield < Application, Lcom/squareup/okhttp/internal/DiskLruCache, redundantOpCount, <Primordial,I> > v1(line 573)
BB4
7   v6 = getfield < Application, Lcom/squareup/okhttp/internal/DiskLruCache, lruEntries, <Application,Ljava/util/LinkedHashMap> > v1(line 573)
BB5
8   v8 = invokevirtual < Application, Ljava/util/LinkedHashMap, size()I > v6 @18 exception:v7(line 573)
BB6
9   conditional branch(lt) v5,v8             (line 573)
BB7
11   return v10:#1                           (line 573)
BB8
13   return v9:#0                            (line 573)
BB9

**CGNode:** Node: < Application, Lcom/squareup/okhttp/internal/Platform$Android23, <init>(Ljava/lang/Class;Ljava/lang/reflect/Method;Ljava/lang/reflect/Method;)V > Context: JavaTypeContext<point: <Application,Lcom/squareup/okhttp/internal/Platform$Android41>>
**IR:** < Application, Lcom/squareup/okhttp/internal/Platform$Android23, <init>(Ljava/lang/Class;Ljava/lang/reflect/Method;Ljava/lang/reflect/Method;)V >
CFG:
BB0[-1..-2]
    -> BB1
BB1[0..1]
    -> BB2
    -> BB6
BB2[2..4]
    -> BB3
    -> BB6
BB3[5..7]
    -> BB4
    -> BB6
BB4[8..10]
    -> BB5
    -> BB6
BB5[11..11]
    -> BB6
BB6[-1..-2]
Instructions:
BB0
BB1
1   invokespecial < Application, Lcom/squareup/okhttp/internal/Platform, <init>()V > v1 @1 exception:v6(line 179)
BB2
4   putfield v1 = v2 < Application, Lcom/squareup/okhttp/internal/Platform$Android23, openSslSocketClass, <Application,Ljava/lang/Class> >(line 181)
BB3
7   putfield v1 = v3 < Application, Lcom/squareup/okhttp/internal/Platform$Android23, setUseSessionTickets, <Application,Ljava/lang/reflect/Method> >(line 182)
BB4
10   putfield v1 = v4 < Application, Lcom/squareup/okhttp/internal/Platform$Android23, setHostname, <Application,Ljava/lang/reflect/Method> >(line 183)
BB5
11   return                                  (line 184)
BB6

**CGNode:** Node: < Application, Lcom/squareup/okhttp/internal/Platform, <init>()V > Context: JavaTypeContext<point: <Application,Lcom/squareup/okhttp/internal/Platform$Android41>>
**IR:** < Application, Lcom/squareup/okhttp/internal/Platform, <init>()V >
CFG:
BB0[-1..-2]
    -> BB1
BB1[0..1]
    -> BB2
    -> BB3
BB2[2..2]
    -> BB3
BB3[-1..-2]
Instructions:
BB0
BB1
1   invokespecial < Application, Ljava/lang/Object, <init>()V > v1 @1 exception:v3(line 49)
BB2
2   return                                   (line 49)
BB3

**CGNode:** Node: < Application, Lcom/squareup/okhttp/internal/DiskLruCache$Entry, getCleanFile(I)Ljava/io/File; > Context: JavaTypeContext<point: <Application,Lcom/squareup/okhttp/internal/DiskLruCache$Entry>>
**IR:** < Application, Lcom/squareup/okhttp/internal/DiskLruCache$Entry, getCleanFile(I)Ljava/io/File; >
CFG:
BB0[-1..-2]
    -> BB1
BB1[0..0]
    -> BB2
    -> BB13
BB2[1..3]
    -> BB3
    -> BB13
BB3[4..4]
    -> BB4
    -> BB13
BB4[5..5]
    -> BB5
    -> BB13
BB5[6..8]
    -> BB6
    -> BB13
BB6[9..9]
    -> BB7
    -> BB13
BB7[10..10]
    -> BB8
    -> BB13
BB8[11..12]
    -> BB9
    -> BB13
BB9[13..14]
    -> BB10
    -> BB13
BB10[15..15]
    -> BB11
    -> BB13
BB11[16..16]
    -> BB12
    -> BB13
BB12[17..17]
    -> BB13
BB13[-1..-2]
Instructions:
BB0
BB1
0   v4 = new <Application,Ljava/io/File>@0   (line 947)
BB2
3   v5 = getfield < Application, Lcom/squareup/okhttp/internal/DiskLruCache$Entry, this$0, <Application,Lcom/squareup/okhttp/internal/DiskLruCache> > v1(line 947)
BB3
4   v7 = invokestatic < Application, Lcom/squareup/okhttp/internal/DiskLruCache, access$8(Lcom/squareup/okhttp/internal/DiskLruCache;)Ljava/io/File; > v5 @8 exception:v6(line 947)
BB4
5   v8 = new <Application,Ljava/lang/StringBuilder>@11(line 947)
BB5
8   v9 = getfield < Application, Lcom/squareup/okhttp/internal/DiskLruCache$Entry, key, <Application,Ljava/lang/String> > v1(line 947)
BB6
9   v11 = invokestatic < Application, Ljava/lang/String, valueOf(Ljava/lang/Object;)Ljava/lang/String; > v9 @19 exception:v10(line 947)
BB7
10   invokespecial < Application, Ljava/lang/StringBuilder, <init>(Ljava/lang/String;)V > v8,v11 @22 exception:v12(line 947)
BB8
12   v15 = invokevirtual < Application, Ljava/lang/StringBuilder, append(Ljava/lang/String;)Ljava/lang/StringBuilder; > v8,v13:#. @27 exception:v14(line 947)
BB9
14   v17 = invokevirtual < Application, Ljava/lang/StringBuilder, append(I)Ljava/lang/StringBuilder; > v15,v2 @31 exception:v16(line 947)
BB10
15   v19 = invokevirtual < Application, Ljava/lang/StringBuilder, toString()Ljava/lang/String; > v17 @34 exception:v18(line 947)
BB11
16   invokespecial < Application, Ljava/io/File, <init>(Ljava/io/File;Ljava/lang/String;)V > v4,v7,v19 @37 exception:v20(line 947)
BB12
17   return v4                               (line 947)
BB13

**CGNode:** Node: < Application, Lcom/squareup/okhttp/internal/Platform, logW(Ljava/lang/String;)V > Context: JavaTypeContext<point: <Application,Lcom/squareup/okhttp/internal/Platform$Android41>>
**IR:** < Application, Lcom/squareup/okhttp/internal/Platform, logW(Ljava/lang/String;)V >
CFG:
BB0[-1..-2]
    -> BB1
BB1[0..2]
    -> BB2
    -> BB3
BB2[3..3]
    -> BB3
BB3[-1..-2]
Instructions:
BB0
BB1
0   v4 = getstatic < Application, Ljava/lang/System, out, <Application,Ljava/io/PrintStream> >(line 59)
2   invokevirtual < Application, Ljava/io/PrintStream, println(Ljava/lang/String;)V > v4,v2 @4 exception:v5(line 59)
BB2
3   return                                   (line 60)
BB3

**CGNode:** Node: < Application, Lcom/squareup/okhttp/internal/Platform, logW(Ljava/lang/String;)V > Context: JavaTypeContext<point: <Application,Lcom/squareup/okhttp/internal/Platform$Android23>>
**IR:** < Application, Lcom/squareup/okhttp/internal/Platform, logW(Ljava/lang/String;)V >
CFG:
BB0[-1..-2]
    -> BB1
BB1[0..2]
    -> BB2
    -> BB3
BB2[3..3]
    -> BB3
BB3[-1..-2]
Instructions:
BB0
BB1
0   v4 = getstatic < Application, Ljava/lang/System, out, <Application,Ljava/io/PrintStream> >(line 59)
2   invokevirtual < Application, Ljava/io/PrintStream, println(Ljava/lang/String;)V > v4,v2 @4 exception:v5(line 59)
BB2
3   return                                   (line 60)
BB3

**CGNode:** Node: < Application, Lcom/squareup/okhttp/internal/Platform, logW(Ljava/lang/String;)V > Context: JavaTypeContext<point: <Application,Lcom/squareup/okhttp/internal/Platform$JdkWithJettyNpnPlatform>>
**IR:** < Application, Lcom/squareup/okhttp/internal/Platform, logW(Ljava/lang/String;)V >
CFG:
BB0[-1..-2]
    -> BB1
BB1[0..2]
    -> BB2
    -> BB3
BB2[3..3]
    -> BB3
BB3[-1..-2]
Instructions:
BB0
BB1
0   v4 = getstatic < Application, Ljava/lang/System, out, <Application,Ljava/io/PrintStream> >(line 59)
2   invokevirtual < Application, Ljava/io/PrintStream, println(Ljava/lang/String;)V > v4,v2 @4 exception:v5(line 59)
BB2
3   return                                   (line 60)
BB3

**CGNode:** Node: < Application, Lcom/squareup/okhttp/internal/Platform, logW(Ljava/lang/String;)V > Context: JavaTypeContext<point: <Application,Lcom/squareup/okhttp/internal/Platform>>
**IR:** < Application, Lcom/squareup/okhttp/internal/Platform, logW(Ljava/lang/String;)V >
CFG:
BB0[-1..-2]
    -> BB1
BB1[0..2]
    -> BB2
    -> BB3
BB2[3..3]
    -> BB3
BB3[-1..-2]
Instructions:
BB0
BB1
0   v4 = getstatic < Application, Ljava/lang/System, out, <Application,Ljava/io/PrintStream> >(line 59)
2   invokevirtual < Application, Ljava/io/PrintStream, println(Ljava/lang/String;)V > v4,v2 @4 exception:v5(line 59)
BB2
3   return                                   (line 60)
BB3

**CGNode:** Node: < Application, Lcom/squareup/okhttp/internal/DiskLruCache, access$8(Lcom/squareup/okhttp/internal/DiskLruCache;)Ljava/io/File; > Context: JavaTypeContext<point: <Application,Lcom/squareup/okhttp/internal/DiskLruCache>>
**IR:** < Application, Lcom/squareup/okhttp/internal/DiskLruCache, access$8(Lcom/squareup/okhttp/internal/DiskLruCache;)Ljava/io/File; >
CFG:
BB0[-1..-2]
    -> BB1
BB1[0..1]
    -> BB2
    -> BB3
BB2[2..2]
    -> BB3
BB3[-1..-2]
Instructions:
BB0
BB1
1   v3 = getfield < Application, Lcom/squareup/okhttp/internal/DiskLruCache, directory, <Application,Ljava/io/File> > v1(line 143)
BB2
2   return v3                                (line 143)
BB3

**CGNode:** Node: < Application, Lcom/squareup/okhttp/internal/DiskLruCache$Entry, getLengths()Ljava/lang/String; > Context: JavaTypeContext<point: <Application,Lcom/squareup/okhttp/internal/DiskLruCache$Entry>>
**IR:** < Application, Lcom/squareup/okhttp/internal/DiskLruCache$Entry, getLengths()Ljava/lang/String; >
CFG:
BB0[-1..-2]
    -> BB1
BB1[0..0]
    -> BB2
    -> BB13
BB2[1..2]
    -> BB3
    -> BB13
BB3[3..5]
    -> BB4
    -> BB13
BB4[6..8]
    -> BB5
    -> BB13
BB5[9..12]
    -> BB10
BB6[13..15]
    -> BB7
    -> BB13
BB7[16..19]
    -> BB8
    -> BB13
BB8[20..21]
    -> BB9
    -> BB13
BB9[22..26]
    -> BB10
BB10[27..29]
    -> BB6
    -> BB11
BB11[30..31]
    -> BB12
    -> BB13
BB12[32..32]
    -> BB13
BB13[-1..-2]
Instructions:
BB0
BB1
0   v3 = new <Application,Ljava/lang/StringBuilder>@0(line 918)
BB2
2   invokespecial < Application, Ljava/lang/StringBuilder, <init>()V > v3 @4 exception:v4(line 918)
BB3
5   v5 = getfield < Application, Lcom/squareup/okhttp/internal/DiskLruCache$Entry, lengths, <Primordial,[J> > v1(line 919)
BB4
8   v6 = arraylength v5                      (line 919)
BB5
12   goto                                    (line 919)
BB6
15   v8 = arrayload v5[v16]                  (line 919)
BB7
19   v11 = invokevirtual < Application, Ljava/lang/StringBuilder, append(C)Ljava/lang/StringBuilder; > v3,v9:#32 @33 exception:v10(line 920)
BB8
21   v13 = invokevirtual < Application, Ljava/lang/StringBuilder, append(J)Ljava/lang/StringBuilder; > v11,v8 @37 exception:v12(line 920)
BB9
25   v15 = binaryop(add) v16 , v14:#1        (line 919)
BB10
           v16 = phi  v7:#0,v15
29   conditional branch(lt) v16,v6           (line 919)
BB11
31   v18 = invokevirtual < Application, Ljava/lang/StringBuilder, toString()Ljava/lang/String; > v3 @52 exception:v17(line 922)
BB12
32   return v18                              (line 922)
BB13

**CGNode:** Node: < Application, Lcom/squareup/okhttp/internal/DiskLruCache$Entry, getDirtyFile(I)Ljava/io/File; > Context: JavaTypeContext<point: <Application,Lcom/squareup/okhttp/internal/DiskLruCache$Entry>>
**IR:** < Application, Lcom/squareup/okhttp/internal/DiskLruCache$Entry, getDirtyFile(I)Ljava/io/File; >
CFG:
BB0[-1..-2]
    -> BB1
BB1[0..0]
    -> BB2
    -> BB14
BB2[1..3]
    -> BB3
    -> BB14
BB3[4..4]
    -> BB4
    -> BB14
BB4[5..5]
    -> BB5
    -> BB14
BB5[6..8]
    -> BB6
    -> BB14
BB6[9..9]
    -> BB7
    -> BB14
BB7[10..10]
    -> BB8
    -> BB14
BB8[11..12]
    -> BB9
    -> BB14
BB9[13..14]
    -> BB10
    -> BB14
BB10[15..16]
    -> BB11
    -> BB14
BB11[17..17]
    -> BB12
    -> BB14
BB12[18..18]
    -> BB13
    -> BB14
BB13[19..19]
    -> BB14
BB14[-1..-2]
Instructions:
BB0
BB1
0   v4 = new <Application,Ljava/io/File>@0   (line 951)
BB2
3   v5 = getfield < Application, Lcom/squareup/okhttp/internal/DiskLruCache$Entry, this$0, <Application,Lcom/squareup/okhttp/internal/DiskLruCache> > v1(line 951)
BB3
4   v7 = invokestatic < Application, Lcom/squareup/okhttp/internal/DiskLruCache, access$8(Lcom/squareup/okhttp/internal/DiskLruCache;)Ljava/io/File; > v5 @8 exception:v6(line 951)
BB4
5   v8 = new <Application,Ljava/lang/StringBuilder>@11(line 951)
BB5
8   v9 = getfield < Application, Lcom/squareup/okhttp/internal/DiskLruCache$Entry, key, <Application,Ljava/lang/String> > v1(line 951)
BB6
9   v11 = invokestatic < Application, Ljava/lang/String, valueOf(Ljava/lang/Object;)Ljava/lang/String; > v9 @19 exception:v10(line 951)
BB7
10   invokespecial < Application, Ljava/lang/StringBuilder, <init>(Ljava/lang/String;)V > v8,v11 @22 exception:v12(line 951)
BB8
12   v15 = invokevirtual < Application, Ljava/lang/StringBuilder, append(Ljava/lang/String;)Ljava/lang/StringBuilder; > v8,v13:#. @27 exception:v14(line 951)
BB9
14   v17 = invokevirtual < Application, Ljava/lang/StringBuilder, append(I)Ljava/lang/StringBuilder; > v15,v2 @31 exception:v16(line 951)
BB10
16   v20 = invokevirtual < Application, Ljava/lang/StringBuilder, append(Ljava/lang/String;)Ljava/lang/StringBuilder; > v17,v18:#.tmp @36 exception:v19(line 951)
BB11
17   v22 = invokevirtual < Application, Ljava/lang/StringBuilder, toString()Ljava/lang/String; > v20 @39 exception:v21(line 951)
BB12
18   invokespecial < Application, Ljava/io/File, <init>(Ljava/io/File;Ljava/lang/String;)V > v4,v7,v22 @42 exception:v23(line 951)
BB13
19   return v4                               (line 951)
BB14

**CGNode:** Node: < Application, Lcom/squareup/okhttp/internal/DiskLruCache$1, call()Ljava/lang/Object; > Context: JavaTypeContext<point: <Application,Lcom/squareup/okhttp/internal/DiskLruCache$1>>
**IR:** < Application, Lcom/squareup/okhttp/internal/DiskLruCache$1, call()Ljava/lang/Object; >
CFG:
BB0[-1..-2]
    -> BB1
BB1[0..1]
    -> BB2
    -> BB3
BB2[2..2]
    -> BB3
BB3[-1..-2]
Instructions:
BB0
BB1
1   v4 = invokevirtual < Application, Lcom/squareup/okhttp/internal/DiskLruCache$1, call()Ljava/lang/Void; > v1 @1 exception:v3(line 1)
BB2
2   return v4                                (line 1)
BB3

**CGNode:** Node: < Application, Lcom/squareup/okhttp/internal/DiskLruCache$1, call()Ljava/lang/Void; > Context: JavaTypeContext<point: <Application,Lcom/squareup/okhttp/internal/DiskLruCache$1>>
**IR:** < Application, Lcom/squareup/okhttp/internal/DiskLruCache$1, call()Ljava/lang/Void; >
CFG:
BB0[-1..-2]
    -> BB1
BB1[0..1]
    -> BB2
    -> BB22
BB2[2..4]
    -> BB3
    -> BB22
BB3[5..6]
    -> BB4
    -> BB19
BB4[7..7]
    -> BB5
    -> BB19
BB5[8..9]
    -> BB8
    -> BB6
BB6[10..11]
    -> BB7
    -> BB19
BB7[12..13]
    -> BB22
BB8[14..15]
    -> BB9
    -> BB19
BB9[16..16]
    -> BB10
    -> BB19
BB10[17..18]
    -> BB11
    -> BB19
BB11[19..19]
    -> BB12
    -> BB19
BB12[20..21]
    -> BB17
    -> BB13
BB13[22..23]
    -> BB14
    -> BB19
BB14[24..24]
    -> BB15
    -> BB19
BB15[25..26]
    -> BB16
    -> BB19
BB16[27..28]
    -> BB17
    -> BB19
BB17[29..30]
    -> BB18
    -> BB19
BB18[31..31]
    -> BB21
BB19[32..33]
    -> BB20
    -> BB19
BB20[34..34]
    -> BB22
BB21[35..36]
    -> BB22
BB22[-1..-2]
Instructions:
BB0
BB1
1   v3 = getfield < Application, Lcom/squareup/okhttp/internal/DiskLruCache$1, this$0, <Application,Lcom/squareup/okhttp/internal/DiskLruCache> > v1(line 168)
BB2
4   monitorenter v3                          (line 168)
BB3
6   v4 = getfield < Application, Lcom/squareup/okhttp/internal/DiskLruCache$1, this$0, <Application,Lcom/squareup/okhttp/internal/DiskLruCache> > v1(line 169)
BB4
7   v6 = invokestatic < Application, Lcom/squareup/okhttp/internal/DiskLruCache, access$0(Lcom/squareup/okhttp/internal/DiskLruCache;)Ljava/io/Writer; > v4 @11 exception:v5(line 169)
BB5
9   conditional branch(ne) v6,v7:#null       (line 169)
BB6
11   monitorexit v3                          (line 170)
BB7
13   return v7:#null                         (line 170)
BB8
15   v8 = getfield < Application, Lcom/squareup/okhttp/internal/DiskLruCache$1, this$0, <Application,Lcom/squareup/okhttp/internal/DiskLruCache> > v1(line 172)
BB9
16   invokestatic < Application, Lcom/squareup/okhttp/internal/DiskLruCache, access$1(Lcom/squareup/okhttp/internal/DiskLruCache;)V > v8 @25 exception:v9(line 172)
BB10
18   v10 = getfield < Application, Lcom/squareup/okhttp/internal/DiskLruCache$1, this$0, <Application,Lcom/squareup/okhttp/internal/DiskLruCache> > v1(line 173)
BB11
19   v12 = invokestatic < Application, Lcom/squareup/okhttp/internal/DiskLruCache, access$2(Lcom/squareup/okhttp/internal/DiskLruCache;)Z > v10 @32 exception:v11(line 173)
BB12
21   conditional branch(eq) v12,v13:#0       (line 173)
BB13
23   v14 = getfield < Application, Lcom/squareup/okhttp/internal/DiskLruCache$1, this$0, <Application,Lcom/squareup/okhttp/internal/DiskLruCache> > v1(line 174)
BB14
24   invokestatic < Application, Lcom/squareup/okhttp/internal/DiskLruCache, access$3(Lcom/squareup/okhttp/internal/DiskLruCache;)V > v14 @42 exception:v15(line 174)
BB15
26   v16 = getfield < Application, Lcom/squareup/okhttp/internal/DiskLruCache$1, this$0, <Application,Lcom/squareup/okhttp/internal/DiskLruCache> > v1(line 175)
BB16
28   invokestatic < Application, Lcom/squareup/okhttp/internal/DiskLruCache, access$4(Lcom/squareup/okhttp/internal/DiskLruCache;I)V > v16,v13:#0 @50 exception:v17(line 175)
BB17
30   monitorexit v3                          (line 168)
BB18
31   goto                                    (line 168)
BB19<Handler>
           v18 = getCaughtException 
33   monitorexit v3                          (line 168)
BB20
34   throw v18                               (line 168)
BB21
36   return v7:#null                         (line 178)
BB22

**CGNode:** Node: < Application, Lcom/squareup/okhttp/internal/DiskLruCache, access$0(Lcom/squareup/okhttp/internal/DiskLruCache;)Ljava/io/Writer; > Context: JavaTypeContext<point: <Application,Lcom/squareup/okhttp/internal/DiskLruCache>>
**IR:** < Application, Lcom/squareup/okhttp/internal/DiskLruCache, access$0(Lcom/squareup/okhttp/internal/DiskLruCache;)Ljava/io/Writer; >
CFG:
BB0[-1..-2]
    -> BB1
BB1[0..1]
    -> BB2
    -> BB3
BB2[2..2]
    -> BB3
BB3[-1..-2]
Instructions:
BB0
BB1
1   v3 = getfield < Application, Lcom/squareup/okhttp/internal/DiskLruCache, journalWriter, <Application,Ljava/io/Writer> > v1(line 151)
BB2
2   return v3                                (line 151)
BB3

**CGNode:** Node: < Application, Lcom/squareup/okhttp/internal/DiskLruCache, access$1(Lcom/squareup/okhttp/internal/DiskLruCache;)V > Context: JavaTypeContext<point: <Application,Lcom/squareup/okhttp/internal/DiskLruCache>>
**IR:** < Application, Lcom/squareup/okhttp/internal/DiskLruCache, access$1(Lcom/squareup/okhttp/internal/DiskLruCache;)V >
CFG:
BB0[-1..-2]
    -> BB1
BB1[0..1]
    -> BB2
    -> BB3
BB2[2..2]
    -> BB3
BB3[-1..-2]
Instructions:
BB0
BB1
1   invokespecial < Application, Lcom/squareup/okhttp/internal/DiskLruCache, trimToSize()V > v1 @1 exception:v3(line 649)
BB2
2   return                                   (line 649)
BB3

**CGNode:** Node: < Application, Lcom/squareup/okhttp/internal/DiskLruCache, access$2(Lcom/squareup/okhttp/internal/DiskLruCache;)Z > Context: JavaTypeContext<point: <Application,Lcom/squareup/okhttp/internal/DiskLruCache>>
**IR:** < Application, Lcom/squareup/okhttp/internal/DiskLruCache, access$2(Lcom/squareup/okhttp/internal/DiskLruCache;)Z >
CFG:
BB0[-1..-2]
    -> BB1
BB1[0..1]
    -> BB2
    -> BB3
BB2[2..2]
    -> BB3
BB3[-1..-2]
Instructions:
BB0
BB1
1   v4 = invokespecial < Application, Lcom/squareup/okhttp/internal/DiskLruCache, journalRebuildRequired()Z > v1 @1 exception:v3(line 572)
BB2
2   return v4                                (line 572)
BB3

**CGNode:** Node: < Application, Lcom/squareup/okhttp/internal/DiskLruCache, access$3(Lcom/squareup/okhttp/internal/DiskLruCache;)V > Context: JavaTypeContext<point: <Application,Lcom/squareup/okhttp/internal/DiskLruCache>>
**IR:** < Application, Lcom/squareup/okhttp/internal/DiskLruCache, access$3(Lcom/squareup/okhttp/internal/DiskLruCache;)V >
CFG:
BB0[-1..-2]
    -> BB1
BB1[0..1]
    -> BB2
    -> BB3
BB2[2..2]
    -> BB3
BB3[-1..-2]
Instructions:
BB0
BB1
1   invokespecial < Application, Lcom/squareup/okhttp/internal/DiskLruCache, rebuildJournal()V > v1 @1 exception:v3(line 345)
BB2
2   return                                   (line 345)
BB3

**CGNode:** Node: < Application, Lcom/squareup/okhttp/internal/DiskLruCache, access$4(Lcom/squareup/okhttp/internal/DiskLruCache;I)V > Context: JavaTypeContext<point: <Application,Lcom/squareup/okhttp/internal/DiskLruCache>>
**IR:** < Application, Lcom/squareup/okhttp/internal/DiskLruCache, access$4(Lcom/squareup/okhttp/internal/DiskLruCache;I)V >
CFG:
BB0[-1..-2]
    -> BB1
BB1[0..2]
    -> BB2
    -> BB3
BB2[3..3]
    -> BB3
BB3[-1..-2]
Instructions:
BB0
BB1
2   putfield v1 = v2 < Application, Lcom/squareup/okhttp/internal/DiskLruCache, redundantOpCount, <Primordial,I> >(line 154)
BB2
3   return                                   (line 154)
BB3

